// class version 52.0 (52)
// access flags 0x31
public final class al/aoli/exchain/runtime/analyzers/AffectedVarDriver {

  // compiled from: AffectedVarDriver.kt

  @Lkotlin/Metadata;(mv={1, 7, 1}, k=1, xi=48, d1={"\u0000`\n\u0002\u0018\u0002\n\u0002\u0010\u0000\n\u0002\u0008\u0002\n\u0002\u0010%\n\u0002\u0010\u0008\n\u0002\u0010\u000b\n\u0002\u0008\u0004\n\u0002\u0010\u000e\n\u0002\u0008\u0005\n\u0002\u0018\u0002\n\u0002\u0008\u0005\n\u0002\u0018\u0002\n\u0002\u0008\u0005\n\u0002\u0018\u0002\n\u0000\n\u0002\u0010\u0003\n\u0002\u0008\u0003\n\u0002\u0010\u0009\n\u0002\u0008\u0009\n\u0002\u0010\u0002\n\u0002\u0018\u0002\n\u0002\u0008\u0002\n\u0002\u0018\u0002\n\u0002\u0018\u0002\n\u0000\u0008\u00c6\u0002\u0018\u00002\u00020\u0001B\u0007\u0008\u0002\u00a2\u0006\u0002\u0010\u0002J8\u0010\u001c\u001a\u0004\u0018\u00010\u001d2\u0006\u0010\u001e\u001a\u00020\u001f2\u0006\u0010 \u001a\u00020\u000b2\u0006\u0010!\u001a\u00020\u000b2\u0006\u0010\"\u001a\u00020#2\u0006\u0010$\u001a\u00020#2\u0006\u0010%\u001a\u00020\u0006J(\u0010&\u001a\u00020\u00062\u0008\u0010'\u001a\u0004\u0018\u00010\u00012\u0006\u0010(\u001a\u00020\u001d2\u0006\u0010)\u001a\u00020\u00012\u0006\u0010*\u001a\u00020\u000bJ\u001e\u0010+\u001a\u00020\u00062\u0006\u0010'\u001a\u00020\u00012\u0006\u0010)\u001a\u00020\u00012\u0006\u0010*\u001a\u00020\u000bJ\u0016\u0010,\u001a\u00020-2\u0006\u0010'\u001a\u00020.2\u0006\u0010)\u001a\u00020\u0001J \u0010/\u001a\u00020-2\u0008\u0010'\u001a\u0004\u0018\u00010\u00012\u0006\u0010(\u001a\u00020\u001d2\u0006\u0010)\u001a\u00020\u0001J\u001a\u00100\u001a\u0006\u0012\u0002\u0008\u0003012\u0006\u0010'\u001a\u0002022\u0006\u0010)\u001a\u00020\u0001R\u001d\u0010\u0003\u001a\u000e\u0012\u0004\u0012\u00020\u0005\u0012\u0004\u0012\u00020\u00060\u0004\u00a2\u0006\u0008\n\u0000\u001a\u0004\u0008\u0007\u0010\u0008R\u001a\u0010\u0009\u001a\u000e\u0012\u0004\u0012\u00020\u0005\u0012\u0004\u0012\u00020\u00010\u0004X\u0082\u0004\u00a2\u0006\u0002\n\u0000R\u001c\u0010\n\u001a\u0004\u0018\u00010\u000bX\u0086\u000e\u00a2\u0006\u000e\n\u0000\u001a\u0004\u0008\u000c\u0010\r\"\u0004\u0008\u000e\u0010\u000fR\u001b\u0010\u0010\u001a\u00020\u00118FX\u0086\u0084\u0002\u00a2\u0006\u000c\n\u0004\u0008\u0014\u0010\u0015\u001a\u0004\u0008\u0012\u0010\u0013R\u001a\u0010\u0016\u001a\u00020\u0017X\u0086\u000e\u00a2\u0006\u000e\n\u0000\u001a\u0004\u0008\u0018\u0010\u0019\"\u0004\u0008\u001a\u0010\u001b\u00a8\u00063"}, d2={"Lal/aoli/exchain/runtime/analyzers/AffectedVarDriver;", "", "()V", "exceptionSourceIdentified", "", "", "", "getExceptionSourceIdentified", "()Ljava/util/Map;", "exceptionStore", "instrumentedClassPath", "", "getInstrumentedClassPath", "()Ljava/lang/String;", "setInstrumentedClassPath", "(Ljava/lang/String;)V", "store", "Lal/aoli/exchain/runtime/store/AffectedVarStore;", "getStore", "()Lal/aoli/exchain/runtime/store/AffectedVarStore;", "store$delegate", "Lkotlin/Lazy;", "type", "Lal/aoli/exchain/runtime/objects/Type;", "getType", "()Lal/aoli/exchain/runtime/objects/Type;", "setType", "(Lal/aoli/exchain/runtime/objects/Type;)V", "analyzeAffectedVar", "Lal/aoli/exchain/runtime/objects/AffectedVarResult;", "e", "", "clazz", "method", "throwIndex", "", "catchIndex", "isThrowInsn", "analyzeSourceFields", "obj", "affectedVarResult", "exception", "location", "analyzeSourceVars", "taintObject", "", "Ledu/columbia/cs/psl/phosphor/struct/TaintedWithObjTag;", "updateAffectedFields", "updateTaint", "Ledu/columbia/cs/psl/phosphor/runtime/Taint;", "Ledu/columbia/cs/psl/phosphor/struct/PowerSetTree$SetNode;", "runtime"})
  // access flags 0x18
  final static INNERCLASS al/aoli/exchain/runtime/analyzers/AffectedVarDriver$analyzeAffectedVar$1 null null
  // access flags 0x18
  final static INNERCLASS al/aoli/exchain/runtime/analyzers/AffectedVarDriver$analyzeAffectedVar$classReader$1 null null
  // access flags 0x18
  final static INNERCLASS al/aoli/exchain/runtime/analyzers/AffectedVarDriver$analyzeAffectedVar$2 null null
  // access flags 0x18
  final static INNERCLASS al/aoli/exchain/runtime/analyzers/AffectedVarDriver$updateAffectedFields$1 null null
  // access flags 0x18
  final static INNERCLASS al/aoli/exchain/runtime/analyzers/AffectedVarDriver$updateAffectedFields$2 null null
  // access flags 0x18
  final static INNERCLASS al/aoli/exchain/runtime/analyzers/AffectedVarDriver$analyzeSourceFields$1 null null
  // access flags 0x18
  final static INNERCLASS al/aoli/exchain/runtime/analyzers/AffectedVarDriver$analyzeSourceFields$2 null null
  // access flags 0x18
  final static INNERCLASS al/aoli/exchain/runtime/analyzers/AffectedVarDriver$analyzeSourceFields$3 null null
  // access flags 0x18
  final static INNERCLASS al/aoli/exchain/runtime/analyzers/AffectedVarDriver$analyzeSourceVars$1 null null
  // access flags 0x18
  final static INNERCLASS al/aoli/exchain/runtime/analyzers/AffectedVarDriver$store$2 null null

  // access flags 0x19
  public final static Lal/aoli/exchain/runtime/analyzers/AffectedVarDriver; INSTANCE

  // access flags 0xA
  private static Ljava/lang/String; instrumentedClassPath

  // access flags 0xA
  private static Lal/aoli/exchain/runtime/objects/Type; type

  // access flags 0x1A
  private final static Lkotlin/Lazy; store$delegate

  // access flags 0x1A
  // signature Ljava/util/Map<Ljava/lang/Integer;Ljava/lang/Boolean;>;
  // declaration: exceptionSourceIdentified extends java.util.Map<java.lang.Integer, java.lang.Boolean>
  private final static Ljava/util/Map; exceptionSourceIdentified

  // access flags 0x1A
  // signature Ljava/util/Map<Ljava/lang/Integer;Ljava/lang/Object;>;
  // declaration: exceptionStore extends java.util.Map<java.lang.Integer, java.lang.Object>
  private final static Ljava/util/Map; exceptionStore

  // access flags 0x11
  public final setType(Lal/aoli/exchain/runtime/objects/Type;)V
   L0
    ALOAD 1
    LDC "<set-?>"
    INVOKESTATIC kotlin/jvm/internal/Intrinsics.checkNotNullParameter (Ljava/lang/Object;Ljava/lang/String;)V
   L1
    LINENUMBER 20 L1
    ALOAD 1
    PUTSTATIC al/aoli/exchain/runtime/analyzers/AffectedVarDriver.type : Lal/aoli/exchain/runtime/objects/Type;
    RETURN
   L2
    LOCALVARIABLE this Lal/aoli/exchain/runtime/analyzers/AffectedVarDriver; L0 L2 0
    LOCALVARIABLE <set-?> Lal/aoli/exchain/runtime/objects/Type; L0 L2 1
    MAXSTACK = 2
    MAXLOCALS = 2

  // access flags 0x11
  public final setInstrumentedClassPath(Ljava/lang/String;)V
   L0
    LINENUMBER 19 L0
    ALOAD 1
    PUTSTATIC al/aoli/exchain/runtime/analyzers/AffectedVarDriver.instrumentedClassPath : Ljava/lang/String;
    RETURN
   L1
    LOCALVARIABLE this Lal/aoli/exchain/runtime/analyzers/AffectedVarDriver; L0 L1 0
    LOCALVARIABLE <set-?> Ljava/lang/String; L0 L1 1
    MAXSTACK = 1
    MAXLOCALS = 2

  // access flags 0x11
  // signature ()Ljava/util/Map<Ljava/lang/Integer;Ljava/lang/Boolean;>;
  // declaration: java.util.Map<java.lang.Integer, java.lang.Boolean> getExceptionSourceIdentified()
  public final getExceptionSourceIdentified()Ljava/util/Map;
   L0
    LINENUMBER 28 L0
    GETSTATIC al/aoli/exchain/runtime/analyzers/AffectedVarDriver.exceptionSourceIdentified : Ljava/util/Map;
    ARETURN
   L1
    LOCALVARIABLE this Lal/aoli/exchain/runtime/analyzers/AffectedVarDriver; L0 L1 0
    MAXSTACK = 1
    MAXLOCALS = 1

  // access flags 0x11
  public final getInstrumentedClassPath()Ljava/lang/String;
   L0
    LINENUMBER 19 L0
    GETSTATIC al/aoli/exchain/runtime/analyzers/AffectedVarDriver.instrumentedClassPath : Ljava/lang/String;
    ARETURN
   L1
    LOCALVARIABLE this Lal/aoli/exchain/runtime/analyzers/AffectedVarDriver; L0 L1 0
    MAXSTACK = 1
    MAXLOCALS = 1

  // access flags 0x11
  public final getStore()Lal/aoli/exchain/runtime/store/AffectedVarStore;
   L0
    LINENUMBER 21 L0
    GETSTATIC al/aoli/exchain/runtime/analyzers/AffectedVarDriver.store$delegate : Lkotlin/Lazy;
    ASTORE 1
    ALOAD 1
    INVOKEINTERFACE kotlin/Lazy.getValue ()Ljava/lang/Object; (itf)
    CHECKCAST al/aoli/exchain/runtime/store/AffectedVarStore
   L1
    LINENUMBER 21 L1
    ARETURN
   L2
    LOCALVARIABLE this Lal/aoli/exchain/runtime/analyzers/AffectedVarDriver; L0 L2 0
    MAXSTACK = 1
    MAXLOCALS = 2

  // access flags 0x11
  public final analyzeAffectedVar(Ljava/lang/Throwable;Ljava/lang/String;Ljava/lang/String;JJZ)Lal/aoli/exchain/runtime/objects/AffectedVarResult;
    TRYCATCHBLOCK L0 L1 L2 java/lang/Throwable
    TRYCATCHBLOCK L3 L4 L5 java/io/IOException
   L6
    ALOAD 1
    LDC "e"
    INVOKESTATIC kotlin/jvm/internal/Intrinsics.checkNotNullParameter (Ljava/lang/Object;Ljava/lang/String;)V
    ALOAD 2
    LDC "clazz"
    INVOKESTATIC kotlin/jvm/internal/Intrinsics.checkNotNullParameter (Ljava/lang/Object;Ljava/lang/String;)V
    ALOAD 3
    LDC "method"
    INVOKESTATIC kotlin/jvm/internal/Intrinsics.checkNotNullParameter (Ljava/lang/Object;Ljava/lang/String;)V
   L7
    LINENUMBER 37 L7
    GETSTATIC al/aoli/exchain/runtime/analyzers/ExceptionLogger.INSTANCE : Lal/aoli/exchain/runtime/analyzers/ExceptionLogger;
    ALOAD 1
    INVOKEVIRTUAL al/aoli/exchain/runtime/analyzers/ExceptionLogger.logException (Ljava/lang/Throwable;)I
    ISTORE 9
   L8
    LINENUMBER 38 L8
    GETSTATIC al/aoli/exchain/runtime/analyzers/AffectedVarDriver.type : Lal/aoli/exchain/runtime/objects/Type;
    GETSTATIC al/aoli/exchain/runtime/objects/Type.Static : Lal/aoli/exchain/runtime/objects/Type;
    IF_ACMPNE L9
   L10
    LINENUMBER 40 L10
    NEW al/aoli/exchain/runtime/objects/AffectedVarResult
    DUP
   L11
    LINENUMBER 41 L11
    ILOAD 9
   L12
    LINENUMBER 42 L12
    ALOAD 1
    INVOKEVIRTUAL java/lang/Object.getClass ()Ljava/lang/Class;
    INVOKEVIRTUAL java/lang/Class.getName ()Ljava/lang/String;
    DUP
    LDC "e.javaClass.name"
    INVOKESTATIC kotlin/jvm/internal/Intrinsics.checkNotNullExpressionValue (Ljava/lang/Object;Ljava/lang/String;)V
   L13
    LINENUMBER 43 L13
    ALOAD 2
   L14
    LINENUMBER 44 L14
    ALOAD 3
   L15
    LINENUMBER 45 L15
    LLOAD 4
   L16
    LINENUMBER 46 L16
    LLOAD 6
   L17
    LINENUMBER 47 L17
    ILOAD 8
   L18
    LINENUMBER 40 L18
    ACONST_NULL
    ACONST_NULL
    ACONST_NULL
    ACONST_NULL
    ACONST_NULL
    ACONST_NULL
    ACONST_NULL
    ACONST_NULL
    ACONST_NULL
    ACONST_NULL
    ACONST_NULL
    LDC 262016
    ACONST_NULL
    INVOKESPECIAL al/aoli/exchain/runtime/objects/AffectedVarResult.<init> (ILjava/lang/String;Ljava/lang/String;Ljava/lang/String;JJZ[I[Ljava/lang/String;[I[Ljava/lang/String;[I[Ljava/lang/String;[I[Lkotlin/Pair;[I[Ljava/lang/String;[Ljava/lang/String;ILkotlin/jvm/internal/DefaultConstructorMarker;)V
   L19
    LINENUMBER 39 L19
    ASTORE 10
   L20
    LINENUMBER 49 L20
    GETSTATIC al/aoli/exchain/runtime/analyzers/ExceptionLogger.INSTANCE : Lal/aoli/exchain/runtime/analyzers/ExceptionLogger;
    ALOAD 10
    INVOKEVIRTUAL al/aoli/exchain/runtime/analyzers/ExceptionLogger.logAffectedVarResult (Lal/aoli/exchain/runtime/objects/AffectedVarResult;)V
   L21
    LINENUMBER 50 L21
    ACONST_NULL
    ARETURN
   L9
    LINENUMBER 53 L9
   FRAME FULL [al/aoli/exchain/runtime/analyzers/AffectedVarDriver java/lang/Throwable java/lang/String java/lang/String J J I I] []
    ALOAD 0
    INVOKEVIRTUAL al/aoli/exchain/runtime/analyzers/AffectedVarDriver.getStore ()Lal/aoli/exchain/runtime/store/AffectedVarStore;
    ALOAD 2
    ALOAD 3
    LLOAD 4
    LLOAD 6
    ILOAD 8
    INVOKEINTERFACE al/aoli/exchain/runtime/store/AffectedVarStore.getCachedAffectedVarResult (Ljava/lang/String;Ljava/lang/String;JJZ)Lal/aoli/exchain/runtime/objects/AffectedVarResult; (itf)
   L22
    LINENUMBER 52 L22
    ASTORE 10
   L23
    LINENUMBER 54 L23
    ALOAD 10
    IFNULL L24
   L25
    LINENUMBER 55 L25
    ALOAD 10
    ILOAD 9
    INVOKEVIRTUAL al/aoli/exchain/runtime/objects/AffectedVarResult.setLabel (I)V
   L26
    LINENUMBER 56 L26
    GETSTATIC al/aoli/exchain/runtime/analyzers/ExceptionLogger.INSTANCE : Lal/aoli/exchain/runtime/analyzers/ExceptionLogger;
    ALOAD 10
    INVOKEVIRTUAL al/aoli/exchain/runtime/analyzers/ExceptionLogger.logAffectedVarResult (Lal/aoli/exchain/runtime/objects/AffectedVarResult;)V
   L27
    LINENUMBER 57 L27
    ALOAD 10
    ARETURN
   L24
    LINENUMBER 59 L24
   FRAME FULL [al/aoli/exchain/runtime/analyzers/AffectedVarDriver java/lang/Throwable java/lang/String java/lang/String J J I I al/aoli/exchain/runtime/objects/AffectedVarResult] []
    ALOAD 2
    ICONST_1
    ALOAD 2
    INVOKEVIRTUAL java/lang/String.length ()I
    ICONST_1
    ISUB
    INVOKESTATIC kotlin/ranges/RangesKt.until (II)Lkotlin/ranges/IntRange;
    INVOKESTATIC kotlin/text/StringsKt.substring (Ljava/lang/String;Lkotlin/ranges/IntRange;)Ljava/lang/String;
    ASTORE 11
   L28
    LINENUMBER 60 L28
    ALOAD 11
    LDC "/"
    LDC "."
    ICONST_0
    ICONST_4
    ACONST_NULL
    INVOKESTATIC kotlin/text/StringsKt.replace$default (Ljava/lang/String;Ljava/lang/String;Ljava/lang/String;ZILjava/lang/Object;)Ljava/lang/String;
    ASTORE 12
   L29
    LINENUMBER 61 L29
    INVOKESTATIC al/aoli/exchain/runtime/analyzers/AffectedVarDriverKt.access$getLogger$p ()Lal/aoli/exchain/runtime/logger/Logger;
    NEW al/aoli/exchain/runtime/analyzers/AffectedVarDriver$analyzeAffectedVar$1
    DUP
    ALOAD 12
    ALOAD 3
    LLOAD 4
    LLOAD 6
    INVOKESPECIAL al/aoli/exchain/runtime/analyzers/AffectedVarDriver$analyzeAffectedVar$1.<init> (Ljava/lang/String;Ljava/lang/String;JJ)V
    CHECKCAST kotlin/jvm/functions/Function0
    INVOKEVIRTUAL al/aoli/exchain/runtime/logger/Logger.info (Lkotlin/jvm/functions/Function0;)V
   L3
    LINENUMBER 65 L3
    NOP
   L30
    LINENUMBER 66 L30
    NEW al/aoli/exchain/runtime/analyzers/AffectedVarClassReader
    DUP
    ALOAD 12
    INVOKESPECIAL al/aoli/exchain/runtime/analyzers/AffectedVarClassReader.<init> (Ljava/lang/String;)V
    ASTORE 14
   L4
    GOTO L31
   L5
    LINENUMBER 67 L5
   FRAME FULL [al/aoli/exchain/runtime/analyzers/AffectedVarDriver java/lang/Throwable java/lang/String java/lang/String J J I I al/aoli/exchain/runtime/objects/AffectedVarResult java/lang/String java/lang/String] [java/io/IOException]
    ASTORE 15
   L0
    LINENUMBER 68 L0
    NOP
   L32
    LINENUMBER 69 L32
    GETSTATIC al/aoli/exchain/runtime/analyzers/AffectedVarDriver.instrumentedClassPath : Ljava/lang/String;
    DUP
    IFNONNULL L33
    POP
    ACONST_NULL
    ARETURN
   L33
   FRAME FULL [al/aoli/exchain/runtime/analyzers/AffectedVarDriver java/lang/Throwable java/lang/String java/lang/String J J I I al/aoli/exchain/runtime/objects/AffectedVarResult java/lang/String java/lang/String T T java/io/IOException] [java/lang/String]
    ASTORE 16
   L34
    LINENUMBER 70 L34
    NEW al/aoli/exchain/runtime/analyzers/AffectedVarClassReader
    DUP
    NEW java/io/File
    DUP
    NEW java/lang/StringBuilder
    DUP
    INVOKESPECIAL java/lang/StringBuilder.<init> ()V
    ALOAD 16
    INVOKEVIRTUAL java/lang/StringBuilder.append (Ljava/lang/String;)Ljava/lang/StringBuilder;
    BIPUSH 47
    INVOKEVIRTUAL java/lang/StringBuilder.append (C)Ljava/lang/StringBuilder;
    ALOAD 11
    INVOKEVIRTUAL java/lang/StringBuilder.append (Ljava/lang/String;)Ljava/lang/StringBuilder;
    LDC ".class"
    INVOKEVIRTUAL java/lang/StringBuilder.append (Ljava/lang/String;)Ljava/lang/StringBuilder;
    INVOKEVIRTUAL java/lang/StringBuilder.toString ()Ljava/lang/String;
    INVOKESPECIAL java/io/File.<init> (Ljava/lang/String;)V
    INVOKESTATIC kotlin/io/FilesKt.readBytes (Ljava/io/File;)[B
    INVOKESPECIAL al/aoli/exchain/runtime/analyzers/AffectedVarClassReader.<init> ([B)V
   L35
    ASTORE 16
   L1
    GOTO L36
   L2
    LINENUMBER 71 L2
   FRAME FULL [al/aoli/exchain/runtime/analyzers/AffectedVarDriver java/lang/Throwable java/lang/String java/lang/String J J I I al/aoli/exchain/runtime/objects/AffectedVarResult java/lang/String java/lang/String T T java/io/IOException] [java/lang/Throwable]
    ASTORE 17
   L37
    LINENUMBER 72 L37
    INVOKESTATIC al/aoli/exchain/runtime/analyzers/AffectedVarDriverKt.access$getLogger$p ()Lal/aoli/exchain/runtime/logger/Logger;
    NEW al/aoli/exchain/runtime/analyzers/AffectedVarDriver$analyzeAffectedVar$classReader$1
    DUP
    ALOAD 12
    INVOKESPECIAL al/aoli/exchain/runtime/analyzers/AffectedVarDriver$analyzeAffectedVar$classReader$1.<init> (Ljava/lang/String;)V
    CHECKCAST kotlin/jvm/functions/Function0
    INVOKEVIRTUAL al/aoli/exchain/runtime/logger/Logger.error (Lkotlin/jvm/functions/Function0;)V
   L38
    LINENUMBER 73 L38
    ACONST_NULL
    ARETURN
   L36
   FRAME FULL [al/aoli/exchain/runtime/analyzers/AffectedVarDriver java/lang/Throwable java/lang/String java/lang/String J J I I al/aoli/exchain/runtime/objects/AffectedVarResult java/lang/String java/lang/String T T java/io/IOException al/aoli/exchain/runtime/analyzers/AffectedVarClassReader] []
    ALOAD 16
    ASTORE 14
   L31
    LINENUMBER 65 L31
   FRAME FULL [al/aoli/exchain/runtime/analyzers/AffectedVarDriver java/lang/Throwable java/lang/String java/lang/String J J I I al/aoli/exchain/runtime/objects/AffectedVarResult java/lang/String java/lang/String T al/aoli/exchain/runtime/analyzers/AffectedVarClassReader] []
    ALOAD 14
   L39
    LINENUMBER 64 L39
    ASTORE 13
   L40
    LINENUMBER 76 L40
    GETSTATIC al/aoli/exchain/runtime/analyzers/AffectedVarDriver.exceptionSourceIdentified : Ljava/util/Map;
    ILOAD 9
    INVOKESTATIC java/lang/Integer.valueOf (I)Ljava/lang/Integer;
    ICONST_0
    INVOKESTATIC java/lang/Boolean.valueOf (Z)Ljava/lang/Boolean;
    INVOKEINTERFACE java/util/Map.getOrDefault (Ljava/lang/Object;Ljava/lang/Object;)Ljava/lang/Object; (itf)
    CHECKCAST java/lang/Boolean
    INVOKEVIRTUAL java/lang/Boolean.booleanValue ()Z
    ISTORE 14
   L41
    LINENUMBER 79 L41
    NEW al/aoli/exchain/runtime/analyzers/AffectedVarClassVisitor
    DUP
   L42
    LINENUMBER 80 L42
    ALOAD 1
   L43
    LINENUMBER 81 L43
    LLOAD 4
   L44
    LINENUMBER 82 L44
    LLOAD 6
   L45
    LINENUMBER 83 L45
    ILOAD 8
   L46
    LINENUMBER 84 L46
    ILOAD 14
    IFNE L47
    ICONST_1
    GOTO L48
   L47
   FRAME FULL [al/aoli/exchain/runtime/analyzers/AffectedVarDriver java/lang/Throwable java/lang/String java/lang/String J J I I al/aoli/exchain/runtime/objects/AffectedVarResult java/lang/String java/lang/String al/aoli/exchain/runtime/analyzers/AffectedVarClassReader I] [L41 L41 java/lang/Throwable J J I]
    ICONST_0
   L48
    LINENUMBER 85 L48
   FRAME FULL [al/aoli/exchain/runtime/analyzers/AffectedVarDriver java/lang/Throwable java/lang/String java/lang/String J J I I al/aoli/exchain/runtime/objects/AffectedVarResult java/lang/String java/lang/String al/aoli/exchain/runtime/analyzers/AffectedVarClassReader I] [L41 L41 java/lang/Throwable J J I I]
    ALOAD 12
   L49
    LINENUMBER 86 L49
    ALOAD 3
   L50
    LINENUMBER 87 L50
    ALOAD 13
   L51
    LINENUMBER 79 L51
    INVOKESPECIAL al/aoli/exchain/runtime/analyzers/AffectedVarClassVisitor.<init> (Ljava/lang/Throwable;JJZZLjava/lang/String;Ljava/lang/String;Lal/aoli/exchain/runtime/analyzers/AffectedVarClassReader;)V
   L52
    LINENUMBER 78 L52
    ASTORE 15
   L53
    LINENUMBER 89 L53
    ALOAD 13
    ALOAD 15
    CHECKCAST al/aoli/exchain/instrumentation/asm/ClassVisitor
    ICONST_0
    INVOKEVIRTUAL al/aoli/exchain/runtime/analyzers/AffectedVarClassReader.accept (Lal/aoli/exchain/instrumentation/asm/ClassVisitor;I)V
   L54
    LINENUMBER 93 L54
    ALOAD 15
    INVOKEVIRTUAL al/aoli/exchain/runtime/analyzers/AffectedVarClassVisitor.getMethodVisitor ()Lal/aoli/exchain/runtime/analyzers/AffectedVarMethodVisitor;
    ASTORE 17
   L55
    LINENUMBER 94 L55
    ALOAD 17
    IFNULL L56
   L57
    LINENUMBER 93 L57
    ALOAD 17
   L58
    LINENUMBER 94 L58
    INVOKEVIRTUAL al/aoli/exchain/runtime/analyzers/AffectedVarMethodVisitor.getAffectedFields ()Ljava/util/Set;
    ASTORE 18
   L59
    LINENUMBER 95 L59
    ALOAD 18
    IFNULL L56
   L60
    LINENUMBER 94 L60
    ALOAD 18
    CHECKCAST java/lang/Iterable
    ASTORE 20
   L61
    LINENUMBER 95 L61
    NOP
   L62
    ICONST_0
    ISTORE 21
   L63
    LINENUMBER 325 L63
    ALOAD 20
    ASTORE 22
    NEW java/util/ArrayList
    DUP
    INVOKESPECIAL java/util/ArrayList.<init> ()V
    CHECKCAST java/util/Collection
    ASTORE 23
   L64
    ICONST_0
    ISTORE 24
   L65
    LINENUMBER 326 L65
    ALOAD 22
    INVOKEINTERFACE java/lang/Iterable.iterator ()Ljava/util/Iterator; (itf)
    ASTORE 25
   L66
   FRAME FULL [al/aoli/exchain/runtime/analyzers/AffectedVarDriver java/lang/Throwable java/lang/String java/lang/String J J I I al/aoli/exchain/runtime/objects/AffectedVarResult java/lang/String java/lang/String al/aoli/exchain/runtime/analyzers/AffectedVarClassReader I al/aoli/exchain/runtime/analyzers/AffectedVarClassVisitor T al/aoli/exchain/runtime/analyzers/AffectedVarMethodVisitor java/util/Set T java/lang/Iterable I java/lang/Iterable java/util/Collection I java/util/Iterator] []
    ALOAD 25
    INVOKEINTERFACE java/util/Iterator.hasNext ()Z (itf)
    IFEQ L67
    ALOAD 25
    INVOKEINTERFACE java/util/Iterator.next ()Ljava/lang/Object; (itf)
    ASTORE 26
   L68
    ALOAD 26
    CHECKCAST kotlin/Pair
    ASTORE 27
   L69
    ICONST_0
    ISTORE 28
   L70
    LINENUMBER 95 L70
    ALOAD 27
    INVOKEVIRTUAL kotlin/Pair.getSecond ()Ljava/lang/Object;
    CHECKCAST java/lang/CharSequence
    LDC "PHOSPHOR"
    CHECKCAST java/lang/CharSequence
    ICONST_0
    ICONST_2
    ACONST_NULL
    INVOKESTATIC kotlin/text/StringsKt.contains$default (Ljava/lang/CharSequence;Ljava/lang/CharSequence;ZILjava/lang/Object;)Z
    IFNE L71
    ICONST_1
    GOTO L72
   L71
   FRAME FULL [al/aoli/exchain/runtime/analyzers/AffectedVarDriver java/lang/Throwable java/lang/String java/lang/String J J I I al/aoli/exchain/runtime/objects/AffectedVarResult java/lang/String java/lang/String al/aoli/exchain/runtime/analyzers/AffectedVarClassReader I al/aoli/exchain/runtime/analyzers/AffectedVarClassVisitor T al/aoli/exchain/runtime/analyzers/AffectedVarMethodVisitor java/util/Set T java/lang/Iterable I java/lang/Iterable java/util/Collection I java/util/Iterator java/lang/Object kotlin/Pair I] []
    ICONST_0
   L72
   FRAME FULL [al/aoli/exchain/runtime/analyzers/AffectedVarDriver java/lang/Throwable java/lang/String java/lang/String J J I I al/aoli/exchain/runtime/objects/AffectedVarResult java/lang/String java/lang/String al/aoli/exchain/runtime/analyzers/AffectedVarClassReader I al/aoli/exchain/runtime/analyzers/AffectedVarClassVisitor T al/aoli/exchain/runtime/analyzers/AffectedVarMethodVisitor java/util/Set T java/lang/Iterable I java/lang/Iterable java/util/Collection I java/util/Iterator java/lang/Object kotlin/Pair I] [I]
    IFEQ L66
    ALOAD 23
    ALOAD 26
    INVOKEINTERFACE java/util/Collection.add (Ljava/lang/Object;)Z (itf)
    POP
   L73
    GOTO L66
   L67
    LINENUMBER 327 L67
   FRAME FULL [al/aoli/exchain/runtime/analyzers/AffectedVarDriver java/lang/Throwable java/lang/String java/lang/String J J I I al/aoli/exchain/runtime/objects/AffectedVarResult java/lang/String java/lang/String al/aoli/exchain/runtime/analyzers/AffectedVarClassReader I al/aoli/exchain/runtime/analyzers/AffectedVarClassVisitor T al/aoli/exchain/runtime/analyzers/AffectedVarMethodVisitor java/util/Set T java/lang/Iterable I java/lang/Iterable java/util/Collection I java/util/Iterator] []
    ALOAD 23
   L74
    CHECKCAST java/util/List
   L75
    LINENUMBER 325 L75
    NOP
   L76
    LINENUMBER 95 L76
    LINENUMBER 96 L76
    LINENUMBER 95 L76
    CHECKCAST java/util/Collection
    ASTORE 21
   L77
    LINENUMBER 96 L77
    NOP
   L78
    ICONST_0
    ISTORE 22
   L79
    LINENUMBER 328 L79
    ALOAD 21
   L80
    LINENUMBER 329 L80
    ASTORE 23
   L81
    LINENUMBER 331 L81
    ALOAD 23
    ICONST_0
    ANEWARRAY kotlin/Pair
    INVOKEINTERFACE java/util/Collection.toArray ([Ljava/lang/Object;)[Ljava/lang/Object; (itf)
    DUP
    LDC "null cannot be cast to non-null type kotlin.Array<T of kotlin.collections.ArraysKt__ArraysJVMKt.toTypedArray>"
    INVOKESTATIC kotlin/jvm/internal/Intrinsics.checkNotNull (Ljava/lang/Object;Ljava/lang/String;)V
   L82
    LINENUMBER 96 L82
    CHECKCAST [Lkotlin/Pair;
   L83
    LINENUMBER 93 L83
    ASTORE 20
    ALOAD 20
    IFNULL L56
    ALOAD 20
    GOTO L84
   L56
    LINENUMBER 97 L56
   FRAME FULL [al/aoli/exchain/runtime/analyzers/AffectedVarDriver java/lang/Throwable java/lang/String java/lang/String J J I I al/aoli/exchain/runtime/objects/AffectedVarResult java/lang/String java/lang/String al/aoli/exchain/runtime/analyzers/AffectedVarClassReader I al/aoli/exchain/runtime/analyzers/AffectedVarClassVisitor T al/aoli/exchain/runtime/analyzers/AffectedVarMethodVisitor] []
    ICONST_0
    ISTORE 21
   L85
    LINENUMBER 332 L85
    ICONST_0
    ANEWARRAY kotlin/Pair
    CHECKCAST [Ljava/lang/Object;
   L86
    CHECKCAST [Lkotlin/Pair;
   L84
    LINENUMBER 93 L84
    LINENUMBER 92 L84
   FRAME FULL [al/aoli/exchain/runtime/analyzers/AffectedVarDriver java/lang/Throwable java/lang/String java/lang/String J J I I al/aoli/exchain/runtime/objects/AffectedVarResult java/lang/String java/lang/String al/aoli/exchain/runtime/analyzers/AffectedVarClassReader I al/aoli/exchain/runtime/analyzers/AffectedVarClassVisitor T al/aoli/exchain/runtime/analyzers/AffectedVarMethodVisitor] [[Lkotlin/Pair;]
    ASTORE 16
   L87
    LINENUMBER 98 L87
    ALOAD 16
    INVOKESTATIC kotlin/collections/ArraysKt.unzip ([Lkotlin/Pair;)Lkotlin/Pair;
    ASTORE 17
    ALOAD 17
    INVOKEVIRTUAL kotlin/Pair.component1 ()Ljava/lang/Object;
    CHECKCAST java/util/List
    ASTORE 18
   L88
    ALOAD 17
    INVOKEVIRTUAL kotlin/Pair.component2 ()Ljava/lang/Object;
    CHECKCAST java/util/List
    ASTORE 19
   L89
    LINENUMBER 100 L89
    ALOAD 15
    INVOKEVIRTUAL al/aoli/exchain/runtime/analyzers/AffectedVarClassVisitor.getMethodVisitor ()Lal/aoli/exchain/runtime/analyzers/AffectedVarMethodVisitor;
    DUP
    IFNULL L90
    INVOKEVIRTUAL al/aoli/exchain/runtime/analyzers/AffectedVarMethodVisitor.getAffectedVars ()Ljava/util/Set;
    DUP
    IFNULL L90
    CHECKCAST java/util/Collection
    ASTORE 24
   L91
    ICONST_0
    ISTORE 25
   L92
    LINENUMBER 333 L92
    ALOAD 24
   L93
    LINENUMBER 334 L93
    ASTORE 26
   L94
    LINENUMBER 336 L94
    ALOAD 26
    ICONST_0
    ANEWARRAY kotlin/Triple
    INVOKEINTERFACE java/util/Collection.toArray ([Ljava/lang/Object;)[Ljava/lang/Object; (itf)
    DUP
    LDC "null cannot be cast to non-null type kotlin.Array<T of kotlin.collections.ArraysKt__ArraysJVMKt.toTypedArray>"
    INVOKESTATIC kotlin/jvm/internal/Intrinsics.checkNotNull (Ljava/lang/Object;Ljava/lang/String;)V
   L95
    LINENUMBER 100 L95
    CHECKCAST [Lkotlin/Triple;
    DUP
    IFNONNULL L96
   L90
   FRAME FULL [al/aoli/exchain/runtime/analyzers/AffectedVarDriver java/lang/Throwable java/lang/String java/lang/String J J I I al/aoli/exchain/runtime/objects/AffectedVarResult java/lang/String java/lang/String al/aoli/exchain/runtime/analyzers/AffectedVarClassReader I al/aoli/exchain/runtime/analyzers/AffectedVarClassVisitor [Lkotlin/Pair; kotlin/Pair java/util/List java/util/List] [java/lang/Object]
    POP
    ICONST_0
    ISTORE 24
   L97
    LINENUMBER 337 L97
    ICONST_0
    ANEWARRAY kotlin/Triple
    CHECKCAST [Ljava/lang/Object;
   L98
    CHECKCAST [Lkotlin/Triple;
   L96
    LINENUMBER 100 L96
   FRAME FULL [al/aoli/exchain/runtime/analyzers/AffectedVarDriver java/lang/Throwable java/lang/String java/lang/String J J I I al/aoli/exchain/runtime/objects/AffectedVarResult java/lang/String java/lang/String al/aoli/exchain/runtime/analyzers/AffectedVarClassReader I al/aoli/exchain/runtime/analyzers/AffectedVarClassVisitor [Lkotlin/Pair; kotlin/Pair java/util/List java/util/List] [[Lkotlin/Triple;]
    ASTORE 20
   L99
    LINENUMBER 102 L99
    ALOAD 15
    INVOKEVIRTUAL al/aoli/exchain/runtime/analyzers/AffectedVarClassVisitor.getMethodVisitor ()Lal/aoli/exchain/runtime/analyzers/AffectedVarMethodVisitor;
    DUP
    IFNULL L100
    INVOKEVIRTUAL al/aoli/exchain/runtime/analyzers/AffectedVarMethodVisitor.getSourceLocalVariable ()Ljava/util/Set;
    DUP
    IFNULL L100
    CHECKCAST java/util/Collection
    INVOKESTATIC kotlin/collections/CollectionsKt.toIntArray (Ljava/util/Collection;)[I
    DUP
    IFNONNULL L101
   L100
   FRAME FULL [al/aoli/exchain/runtime/analyzers/AffectedVarDriver java/lang/Throwable java/lang/String java/lang/String J J I I al/aoli/exchain/runtime/objects/AffectedVarResult java/lang/String java/lang/String al/aoli/exchain/runtime/analyzers/AffectedVarClassReader I al/aoli/exchain/runtime/analyzers/AffectedVarClassVisitor [Lkotlin/Pair; kotlin/Pair java/util/List java/util/List [Lkotlin/Triple;] [java/lang/Object]
    POP
    ICONST_0
    NEWARRAY T_INT
   L101
    LINENUMBER 101 L101
   FRAME FULL [al/aoli/exchain/runtime/analyzers/AffectedVarDriver java/lang/Throwable java/lang/String java/lang/String J J I I al/aoli/exchain/runtime/objects/AffectedVarResult java/lang/String java/lang/String al/aoli/exchain/runtime/analyzers/AffectedVarClassReader I al/aoli/exchain/runtime/analyzers/AffectedVarClassVisitor [Lkotlin/Pair; kotlin/Pair java/util/List java/util/List [Lkotlin/Triple;] [[I]
    ASTORE 21
   L102
    LINENUMBER 103 L102
    ALOAD 3
    CHECKCAST java/lang/CharSequence
    LDC "clinit"
    CHECKCAST java/lang/CharSequence
    ICONST_0
    ICONST_2
    ACONST_NULL
    INVOKESTATIC kotlin/text/StringsKt.contains$default (Ljava/lang/CharSequence;Ljava/lang/CharSequence;ZILjava/lang/Object;)Z
    IFEQ L103
   L104
    LINENUMBER 104 L104
    ALOAD 15
    INVOKEVIRTUAL al/aoli/exchain/runtime/analyzers/AffectedVarClassVisitor.getMethodVisitor ()Lal/aoli/exchain/runtime/analyzers/AffectedVarMethodVisitor;
    DUP
    IFNULL L105
    INVOKEVIRTUAL al/aoli/exchain/runtime/analyzers/AffectedVarMethodVisitor.getAffectedStaticField ()Ljava/util/Set;
    DUP
    IFNULL L105
    INVOKEINTERFACE java/util/Set.clear ()V (itf)
    GETSTATIC kotlin/Unit.INSTANCE : Lkotlin/Unit;
    GOTO L106
   L105
   FRAME FULL [al/aoli/exchain/runtime/analyzers/AffectedVarDriver java/lang/Throwable java/lang/String java/lang/String J J I I al/aoli/exchain/runtime/objects/AffectedVarResult java/lang/String java/lang/String al/aoli/exchain/runtime/analyzers/AffectedVarClassReader I al/aoli/exchain/runtime/analyzers/AffectedVarClassVisitor [Lkotlin/Pair; kotlin/Pair java/util/List java/util/List [Lkotlin/Triple; [I] [java/lang/Object]
    POP
    ACONST_NULL
   L106
   FRAME FULL [al/aoli/exchain/runtime/analyzers/AffectedVarDriver java/lang/Throwable java/lang/String java/lang/String J J I I al/aoli/exchain/runtime/objects/AffectedVarResult java/lang/String java/lang/String al/aoli/exchain/runtime/analyzers/AffectedVarClassReader I al/aoli/exchain/runtime/analyzers/AffectedVarClassVisitor [Lkotlin/Pair; kotlin/Pair java/util/List java/util/List [Lkotlin/Triple; [I] [kotlin/Unit]
    POP
   L107
    LINENUMBER 105 L107
    ALOAD 15
    INVOKEVIRTUAL al/aoli/exchain/runtime/analyzers/AffectedVarClassVisitor.getMethodVisitor ()Lal/aoli/exchain/runtime/analyzers/AffectedVarMethodVisitor;
    DUP
    IFNULL L108
    INVOKEVIRTUAL al/aoli/exchain/runtime/analyzers/AffectedVarMethodVisitor.getSourceStaticField ()Ljava/util/Set;
    DUP
    IFNULL L108
    INVOKEINTERFACE java/util/Set.clear ()V (itf)
    GETSTATIC kotlin/Unit.INSTANCE : Lkotlin/Unit;
    GOTO L109
   L108
   FRAME FULL [al/aoli/exchain/runtime/analyzers/AffectedVarDriver java/lang/Throwable java/lang/String java/lang/String J J I I al/aoli/exchain/runtime/objects/AffectedVarResult java/lang/String java/lang/String al/aoli/exchain/runtime/analyzers/AffectedVarClassReader I al/aoli/exchain/runtime/analyzers/AffectedVarClassVisitor [Lkotlin/Pair; kotlin/Pair java/util/List java/util/List [Lkotlin/Triple; [I] [java/lang/Object]
    POP
    ACONST_NULL
   L109
   FRAME FULL [al/aoli/exchain/runtime/analyzers/AffectedVarDriver java/lang/Throwable java/lang/String java/lang/String J J I I al/aoli/exchain/runtime/objects/AffectedVarResult java/lang/String java/lang/String al/aoli/exchain/runtime/analyzers/AffectedVarClassReader I al/aoli/exchain/runtime/analyzers/AffectedVarClassVisitor [Lkotlin/Pair; kotlin/Pair java/util/List java/util/List [Lkotlin/Triple; [I] [kotlin/Unit]
    POP
   L103
    LINENUMBER 108 L103
   FRAME FULL [al/aoli/exchain/runtime/analyzers/AffectedVarDriver java/lang/Throwable java/lang/String java/lang/String J J I I al/aoli/exchain/runtime/objects/AffectedVarResult java/lang/String java/lang/String al/aoli/exchain/runtime/analyzers/AffectedVarClassReader I al/aoli/exchain/runtime/analyzers/AffectedVarClassVisitor [Lkotlin/Pair; kotlin/Pair java/util/List java/util/List [Lkotlin/Triple; [I] []
    ALOAD 20
    INVOKESTATIC al/aoli/exchain/runtime/analyzers/AffectedVarDriverKt.access$unzip ([Lkotlin/Triple;)Lkotlin/Triple;
    ASTORE 22
    ALOAD 22
    INVOKEVIRTUAL kotlin/Triple.component1 ()Ljava/lang/Object;
    CHECKCAST java/util/List
    ASTORE 23
   L110
    ALOAD 22
    INVOKEVIRTUAL kotlin/Triple.component2 ()Ljava/lang/Object;
    CHECKCAST java/util/List
    ASTORE 24
   L111
    ALOAD 22
    INVOKEVIRTUAL kotlin/Triple.component3 ()Ljava/lang/Object;
    CHECKCAST java/util/List
    ASTORE 25
   L112
    LINENUMBER 110 L112
    ALOAD 15
    INVOKEVIRTUAL al/aoli/exchain/runtime/analyzers/AffectedVarClassVisitor.getMethodVisitor ()Lal/aoli/exchain/runtime/analyzers/AffectedVarMethodVisitor;
    DUP
    IFNULL L113
    INVOKEVIRTUAL al/aoli/exchain/runtime/analyzers/AffectedVarMethodVisitor.getAffectedStaticField ()Ljava/util/Set;
    DUP
    IFNULL L113
    CHECKCAST java/util/Collection
    ASTORE 30
   L114
    ICONST_0
    ISTORE 31
   L115
    LINENUMBER 338 L115
    ALOAD 30
   L116
    LINENUMBER 339 L116
    ASTORE 32
   L117
    LINENUMBER 341 L117
    ALOAD 32
    ICONST_0
    ANEWARRAY kotlin/Pair
    INVOKEINTERFACE java/util/Collection.toArray ([Ljava/lang/Object;)[Ljava/lang/Object; (itf)
    DUP
    LDC "null cannot be cast to non-null type kotlin.Array<T of kotlin.collections.ArraysKt__ArraysJVMKt.toTypedArray>"
    INVOKESTATIC kotlin/jvm/internal/Intrinsics.checkNotNull (Ljava/lang/Object;Ljava/lang/String;)V
   L118
    LINENUMBER 110 L118
    CHECKCAST [Lkotlin/Pair;
    DUP
    IFNONNULL L119
   L113
   FRAME FULL [al/aoli/exchain/runtime/analyzers/AffectedVarDriver java/lang/Throwable java/lang/String java/lang/String J J I I al/aoli/exchain/runtime/objects/AffectedVarResult java/lang/String java/lang/String al/aoli/exchain/runtime/analyzers/AffectedVarClassReader I al/aoli/exchain/runtime/analyzers/AffectedVarClassVisitor [Lkotlin/Pair; kotlin/Pair java/util/List java/util/List [Lkotlin/Triple; [I kotlin/Triple java/util/List java/util/List java/util/List] [java/lang/Object]
    POP
    ICONST_0
    ISTORE 30
   L120
    LINENUMBER 342 L120
    ICONST_0
    ANEWARRAY kotlin/Pair
    CHECKCAST [Ljava/lang/Object;
   L121
    CHECKCAST [Lkotlin/Pair;
   L119
    LINENUMBER 110 L119
   FRAME FULL [al/aoli/exchain/runtime/analyzers/AffectedVarDriver java/lang/Throwable java/lang/String java/lang/String J J I I al/aoli/exchain/runtime/objects/AffectedVarResult java/lang/String java/lang/String al/aoli/exchain/runtime/analyzers/AffectedVarClassReader I al/aoli/exchain/runtime/analyzers/AffectedVarClassVisitor [Lkotlin/Pair; kotlin/Pair java/util/List java/util/List [Lkotlin/Triple; [I kotlin/Triple java/util/List java/util/List java/util/List] [[Lkotlin/Pair;]
    INVOKESTATIC kotlin/collections/ArraysKt.unzip ([Lkotlin/Pair;)Lkotlin/Pair;
    ASTORE 26
    ALOAD 26
   L122
    LINENUMBER 109 L122
    INVOKEVIRTUAL kotlin/Pair.component1 ()Ljava/lang/Object;
    CHECKCAST java/util/List
    ASTORE 27
   L123
    LINENUMBER 110 L123
    ALOAD 26
   L124
    LINENUMBER 109 L124
    INVOKEVIRTUAL kotlin/Pair.component2 ()Ljava/lang/Object;
    CHECKCAST java/util/List
    ASTORE 28
   L125
    LINENUMBER 111 L125
    ALOAD 15
    INVOKEVIRTUAL al/aoli/exchain/runtime/analyzers/AffectedVarClassVisitor.getMethodVisitor ()Lal/aoli/exchain/runtime/analyzers/AffectedVarMethodVisitor;
    DUP
    IFNULL L126
    INVOKEVIRTUAL al/aoli/exchain/runtime/analyzers/AffectedVarMethodVisitor.getSourceLines ()Ljava/util/Set;
    DUP
    IFNULL L126
    CHECKCAST java/util/Collection
    ASTORE 33
   L127
    ICONST_0
    ISTORE 34
   L128
    LINENUMBER 343 L128
    ALOAD 33
   L129
    LINENUMBER 344 L129
    ASTORE 35
   L130
    LINENUMBER 346 L130
    ALOAD 35
    ICONST_0
    ANEWARRAY kotlin/Pair
    INVOKEINTERFACE java/util/Collection.toArray ([Ljava/lang/Object;)[Ljava/lang/Object; (itf)
    DUP
    LDC "null cannot be cast to non-null type kotlin.Array<T of kotlin.collections.ArraysKt__ArraysJVMKt.toTypedArray>"
    INVOKESTATIC kotlin/jvm/internal/Intrinsics.checkNotNull (Ljava/lang/Object;Ljava/lang/String;)V
   L131
    LINENUMBER 111 L131
    CHECKCAST [Lkotlin/Pair;
    DUP
    IFNONNULL L132
   L126
   FRAME FULL [al/aoli/exchain/runtime/analyzers/AffectedVarDriver java/lang/Throwable java/lang/String java/lang/String J J I I al/aoli/exchain/runtime/objects/AffectedVarResult java/lang/String java/lang/String al/aoli/exchain/runtime/analyzers/AffectedVarClassReader I al/aoli/exchain/runtime/analyzers/AffectedVarClassVisitor [Lkotlin/Pair; kotlin/Pair java/util/List java/util/List [Lkotlin/Triple; [I kotlin/Triple java/util/List java/util/List java/util/List kotlin/Pair java/util/List java/util/List] [java/lang/Object]
    POP
    ICONST_0
    ISTORE 33
   L133
    LINENUMBER 347 L133
    ICONST_0
    ANEWARRAY kotlin/Pair
    CHECKCAST [Ljava/lang/Object;
   L134
    CHECKCAST [Lkotlin/Pair;
   L132
    LINENUMBER 111 L132
   FRAME FULL [al/aoli/exchain/runtime/analyzers/AffectedVarDriver java/lang/Throwable java/lang/String java/lang/String J J I I al/aoli/exchain/runtime/objects/AffectedVarResult java/lang/String java/lang/String al/aoli/exchain/runtime/analyzers/AffectedVarClassReader I al/aoli/exchain/runtime/analyzers/AffectedVarClassVisitor [Lkotlin/Pair; kotlin/Pair java/util/List java/util/List [Lkotlin/Triple; [I kotlin/Triple java/util/List java/util/List java/util/List kotlin/Pair java/util/List java/util/List] [[Lkotlin/Pair;]
    ASTORE 29
   L135
    LINENUMBER 112 L135
    ALOAD 29
    ARRAYLENGTH
    IFNE L136
    ICONST_1
    GOTO L137
   L136
   FRAME FULL [al/aoli/exchain/runtime/analyzers/AffectedVarDriver java/lang/Throwable java/lang/String java/lang/String J J I I al/aoli/exchain/runtime/objects/AffectedVarResult java/lang/String java/lang/String al/aoli/exchain/runtime/analyzers/AffectedVarClassReader I al/aoli/exchain/runtime/analyzers/AffectedVarClassVisitor [Lkotlin/Pair; kotlin/Pair java/util/List java/util/List [Lkotlin/Triple; [I kotlin/Triple java/util/List java/util/List java/util/List kotlin/Pair java/util/List java/util/List [Lkotlin/Pair;] []
    ICONST_0
   L137
   FRAME FULL [al/aoli/exchain/runtime/analyzers/AffectedVarDriver java/lang/Throwable java/lang/String java/lang/String J J I I al/aoli/exchain/runtime/objects/AffectedVarResult java/lang/String java/lang/String al/aoli/exchain/runtime/analyzers/AffectedVarClassReader I al/aoli/exchain/runtime/analyzers/AffectedVarClassVisitor [Lkotlin/Pair; kotlin/Pair java/util/List java/util/List [Lkotlin/Triple; [I kotlin/Triple java/util/List java/util/List java/util/List kotlin/Pair java/util/List java/util/List [Lkotlin/Pair;] [I]
    IFNE L138
    ICONST_1
    GOTO L139
   L138
   FRAME FULL [al/aoli/exchain/runtime/analyzers/AffectedVarDriver java/lang/Throwable java/lang/String java/lang/String J J I I al/aoli/exchain/runtime/objects/AffectedVarResult java/lang/String java/lang/String al/aoli/exchain/runtime/analyzers/AffectedVarClassReader I al/aoli/exchain/runtime/analyzers/AffectedVarClassVisitor [Lkotlin/Pair; kotlin/Pair java/util/List java/util/List [Lkotlin/Triple; [I kotlin/Triple java/util/List java/util/List java/util/List kotlin/Pair java/util/List java/util/List [Lkotlin/Pair;] []
    ICONST_0
   L139
    LINENUMBER 112 L139
   FRAME FULL [al/aoli/exchain/runtime/analyzers/AffectedVarDriver java/lang/Throwable java/lang/String java/lang/String J J I I al/aoli/exchain/runtime/objects/AffectedVarResult java/lang/String java/lang/String al/aoli/exchain/runtime/analyzers/AffectedVarClassReader I al/aoli/exchain/runtime/analyzers/AffectedVarClassVisitor [Lkotlin/Pair; kotlin/Pair java/util/List java/util/List [Lkotlin/Triple; [I kotlin/Triple java/util/List java/util/List java/util/List kotlin/Pair java/util/List java/util/List [Lkotlin/Pair;] [I]
    IFEQ L140
    ILOAD 9
    INVOKESTATIC java/lang/Integer.valueOf (I)Ljava/lang/Integer;
    ASTORE 31
   L141
    LINENUMBER 113 L141
    GETSTATIC al/aoli/exchain/runtime/analyzers/AffectedVarDriver.exceptionSourceIdentified : Ljava/util/Map;
    ALOAD 31
    ICONST_1
    INVOKESTATIC java/lang/Boolean.valueOf (Z)Ljava/lang/Boolean;
    INVOKEINTERFACE java/util/Map.put (Ljava/lang/Object;Ljava/lang/Object;)Ljava/lang/Object; (itf)
    POP
   L140
    LINENUMBER 115 L140
   FRAME FULL [al/aoli/exchain/runtime/analyzers/AffectedVarDriver java/lang/Throwable java/lang/String java/lang/String J J I I al/aoli/exchain/runtime/objects/AffectedVarResult java/lang/String java/lang/String al/aoli/exchain/runtime/analyzers/AffectedVarClassReader I al/aoli/exchain/runtime/analyzers/AffectedVarClassVisitor [Lkotlin/Pair; kotlin/Pair java/util/List java/util/List [Lkotlin/Triple; [I kotlin/Triple java/util/List java/util/List java/util/List kotlin/Pair java/util/List java/util/List [Lkotlin/Pair;] []
    ALOAD 15
    INVOKEVIRTUAL al/aoli/exchain/runtime/analyzers/AffectedVarClassVisitor.getMethodVisitor ()Lal/aoli/exchain/runtime/analyzers/AffectedVarMethodVisitor;
    DUP
    IFNULL L142
    INVOKEVIRTUAL al/aoli/exchain/runtime/analyzers/AffectedVarMethodVisitor.getSourceField ()Ljava/util/Set;
    DUP
    IFNULL L142
    CHECKCAST java/util/Collection
    ASTORE 34
   L143
    ICONST_0
    ISTORE 35
   L144
    LINENUMBER 348 L144
    ALOAD 34
   L145
    LINENUMBER 349 L145
    ASTORE 36
   L146
    LINENUMBER 351 L146
    ALOAD 36
    ICONST_0
    ANEWARRAY java/lang/String
    INVOKEINTERFACE java/util/Collection.toArray ([Ljava/lang/Object;)[Ljava/lang/Object; (itf)
    DUP
    LDC "null cannot be cast to non-null type kotlin.Array<T of kotlin.collections.ArraysKt__ArraysJVMKt.toTypedArray>"
    INVOKESTATIC kotlin/jvm/internal/Intrinsics.checkNotNull (Ljava/lang/Object;Ljava/lang/String;)V
   L147
    LINENUMBER 115 L147
    CHECKCAST [Ljava/lang/String;
    DUP
    IFNONNULL L148
   L142
   FRAME FULL [al/aoli/exchain/runtime/analyzers/AffectedVarDriver java/lang/Throwable java/lang/String java/lang/String J J I I al/aoli/exchain/runtime/objects/AffectedVarResult java/lang/String java/lang/String al/aoli/exchain/runtime/analyzers/AffectedVarClassReader I al/aoli/exchain/runtime/analyzers/AffectedVarClassVisitor [Lkotlin/Pair; kotlin/Pair java/util/List java/util/List [Lkotlin/Triple; [I kotlin/Triple java/util/List java/util/List java/util/List kotlin/Pair java/util/List java/util/List [Lkotlin/Pair;] [java/lang/Object]
    POP
    ICONST_0
    ISTORE 34
   L149
    LINENUMBER 352 L149
    ICONST_0
    ANEWARRAY java/lang/String
    CHECKCAST [Ljava/lang/Object;
   L150
    CHECKCAST [Ljava/lang/String;
   L148
    LINENUMBER 115 L148
   FRAME FULL [al/aoli/exchain/runtime/analyzers/AffectedVarDriver java/lang/Throwable java/lang/String java/lang/String J J I I al/aoli/exchain/runtime/objects/AffectedVarResult java/lang/String java/lang/String al/aoli/exchain/runtime/analyzers/AffectedVarClassReader I al/aoli/exchain/runtime/analyzers/AffectedVarClassVisitor [Lkotlin/Pair; kotlin/Pair java/util/List java/util/List [Lkotlin/Triple; [I kotlin/Triple java/util/List java/util/List java/util/List kotlin/Pair java/util/List java/util/List [Lkotlin/Pair;] [[Ljava/lang/String;]
    ASTORE 30
   L151
    LINENUMBER 116 L151
    ALOAD 15
    INVOKEVIRTUAL al/aoli/exchain/runtime/analyzers/AffectedVarClassVisitor.getMethodVisitor ()Lal/aoli/exchain/runtime/analyzers/AffectedVarMethodVisitor;
    DUP
    IFNULL L152
    INVOKEVIRTUAL al/aoli/exchain/runtime/analyzers/AffectedVarMethodVisitor.getSourceStaticField ()Ljava/util/Set;
    DUP
    IFNULL L152
    CHECKCAST java/util/Collection
    ASTORE 35
   L153
    ICONST_0
    ISTORE 36
   L154
    LINENUMBER 353 L154
    ALOAD 35
   L155
    LINENUMBER 354 L155
    ASTORE 37
   L156
    LINENUMBER 356 L156
    ALOAD 37
    ICONST_0
    ANEWARRAY java/lang/String
    INVOKEINTERFACE java/util/Collection.toArray ([Ljava/lang/Object;)[Ljava/lang/Object; (itf)
    DUP
    LDC "null cannot be cast to non-null type kotlin.Array<T of kotlin.collections.ArraysKt__ArraysJVMKt.toTypedArray>"
    INVOKESTATIC kotlin/jvm/internal/Intrinsics.checkNotNull (Ljava/lang/Object;Ljava/lang/String;)V
   L157
    LINENUMBER 116 L157
    CHECKCAST [Ljava/lang/String;
    DUP
    IFNONNULL L158
   L152
   FRAME FULL [al/aoli/exchain/runtime/analyzers/AffectedVarDriver java/lang/Throwable java/lang/String java/lang/String J J I I al/aoli/exchain/runtime/objects/AffectedVarResult java/lang/String java/lang/String al/aoli/exchain/runtime/analyzers/AffectedVarClassReader I al/aoli/exchain/runtime/analyzers/AffectedVarClassVisitor [Lkotlin/Pair; kotlin/Pair java/util/List java/util/List [Lkotlin/Triple; [I kotlin/Triple java/util/List java/util/List java/util/List kotlin/Pair java/util/List java/util/List [Lkotlin/Pair; [Ljava/lang/String;] [java/lang/Object]
    POP
    ICONST_0
    ISTORE 35
   L159
    LINENUMBER 357 L159
    ICONST_0
    ANEWARRAY java/lang/String
    CHECKCAST [Ljava/lang/Object;
   L160
    CHECKCAST [Ljava/lang/String;
   L158
    LINENUMBER 116 L158
   FRAME FULL [al/aoli/exchain/runtime/analyzers/AffectedVarDriver java/lang/Throwable java/lang/String java/lang/String J J I I al/aoli/exchain/runtime/objects/AffectedVarResult java/lang/String java/lang/String al/aoli/exchain/runtime/analyzers/AffectedVarClassReader I al/aoli/exchain/runtime/analyzers/AffectedVarClassVisitor [Lkotlin/Pair; kotlin/Pair java/util/List java/util/List [Lkotlin/Triple; [I kotlin/Triple java/util/List java/util/List java/util/List kotlin/Pair java/util/List java/util/List [Lkotlin/Pair; [Ljava/lang/String;] [[Ljava/lang/String;]
    ASTORE 31
   L161
    LINENUMBER 118 L161
    NEW al/aoli/exchain/runtime/objects/AffectedVarResult
    DUP
   L162
    LINENUMBER 119 L162
    ILOAD 9
   L163
    LINENUMBER 120 L163
    ALOAD 1
    INVOKEVIRTUAL java/lang/Object.getClass ()Ljava/lang/Class;
    INVOKEVIRTUAL java/lang/Class.getName ()Ljava/lang/String;
    DUP
    LDC "e.javaClass.name"
    INVOKESTATIC kotlin/jvm/internal/Intrinsics.checkNotNullExpressionValue (Ljava/lang/Object;Ljava/lang/String;)V
   L164
    LINENUMBER 121 L164
    ALOAD 2
   L165
    LINENUMBER 122 L165
    ALOAD 3
   L166
    LINENUMBER 123 L166
    LLOAD 4
   L167
    LINENUMBER 124 L167
    LLOAD 6
   L168
    LINENUMBER 125 L168
    ILOAD 8
   L169
    LINENUMBER 126 L169
    GETSTATIC al/aoli/exchain/runtime/analyzers/AffectedVarDriver.type : Lal/aoli/exchain/runtime/objects/Type;
    GETSTATIC al/aoli/exchain/runtime/objects/Type.Hybrid : Lal/aoli/exchain/runtime/objects/Type;
    IF_ACMPNE L170
    ICONST_0
    NEWARRAY T_INT
    GOTO L171
   L170
    LINENUMBER 129 L170
   FRAME FULL [al/aoli/exchain/runtime/analyzers/AffectedVarDriver java/lang/Throwable java/lang/String java/lang/String J J I I al/aoli/exchain/runtime/objects/AffectedVarResult java/lang/String java/lang/String al/aoli/exchain/runtime/analyzers/AffectedVarClassReader I al/aoli/exchain/runtime/analyzers/AffectedVarClassVisitor [Lkotlin/Pair; kotlin/Pair java/util/List java/util/List [Lkotlin/Triple; [I kotlin/Triple java/util/List java/util/List java/util/List kotlin/Pair java/util/List java/util/List [Lkotlin/Pair; [Ljava/lang/String; [Ljava/lang/String;] [L161 L161 I java/lang/String java/lang/String java/lang/String J J I]
    ALOAD 24
    CHECKCAST java/util/Collection
    INVOKESTATIC kotlin/collections/CollectionsKt.toIntArray (Ljava/util/Collection;)[I
   L171
    LINENUMBER 131 L171
   FRAME FULL [al/aoli/exchain/runtime/analyzers/AffectedVarDriver java/lang/Throwable java/lang/String java/lang/String J J I I al/aoli/exchain/runtime/objects/AffectedVarResult java/lang/String java/lang/String al/aoli/exchain/runtime/analyzers/AffectedVarClassReader I al/aoli/exchain/runtime/analyzers/AffectedVarClassVisitor [Lkotlin/Pair; kotlin/Pair java/util/List java/util/List [Lkotlin/Triple; [I kotlin/Triple java/util/List java/util/List java/util/List kotlin/Pair java/util/List java/util/List [Lkotlin/Pair; [Ljava/lang/String; [Ljava/lang/String;] [L161 L161 I java/lang/String java/lang/String java/lang/String J J I [I]
    ALOAD 25
    CHECKCAST java/util/Collection
    ASTORE 33
   L172
    ICONST_0
    ISTORE 34
   L173
    LINENUMBER 358 L173
    ALOAD 33
   L174
    LINENUMBER 359 L174
    ASTORE 35
   L175
    LINENUMBER 361 L175
    ALOAD 35
    ICONST_0
    ANEWARRAY java/lang/String
    INVOKEINTERFACE java/util/Collection.toArray ([Ljava/lang/Object;)[Ljava/lang/Object; (itf)
    DUP
    LDC "null cannot be cast to non-null type kotlin.Array<T of kotlin.collections.ArraysKt__ArraysJVMKt.toTypedArray>"
    INVOKESTATIC kotlin/jvm/internal/Intrinsics.checkNotNull (Ljava/lang/Object;Ljava/lang/String;)V
   L176
    CHECKCAST [Ljava/lang/String;
   L177
    LINENUMBER 132 L177
    ALOAD 23
    CHECKCAST java/util/Collection
    INVOKESTATIC kotlin/collections/CollectionsKt.toIntArray (Ljava/util/Collection;)[I
   L178
    LINENUMBER 133 L178
    ALOAD 19
    CHECKCAST java/util/Collection
    ASTORE 33
   L179
    ICONST_0
    ISTORE 34
   L180
    LINENUMBER 362 L180
    ALOAD 33
   L181
    LINENUMBER 363 L181
    ASTORE 35
   L182
    LINENUMBER 365 L182
    ALOAD 35
    ICONST_0
    ANEWARRAY java/lang/String
    INVOKEINTERFACE java/util/Collection.toArray ([Ljava/lang/Object;)[Ljava/lang/Object; (itf)
    DUP
    LDC "null cannot be cast to non-null type kotlin.Array<T of kotlin.collections.ArraysKt__ArraysJVMKt.toTypedArray>"
    INVOKESTATIC kotlin/jvm/internal/Intrinsics.checkNotNull (Ljava/lang/Object;Ljava/lang/String;)V
   L183
    CHECKCAST [Ljava/lang/String;
   L184
    LINENUMBER 134 L184
    ALOAD 18
    CHECKCAST java/util/Collection
    INVOKESTATIC kotlin/collections/CollectionsKt.toIntArray (Ljava/util/Collection;)[I
   L185
    LINENUMBER 135 L185
    ALOAD 28
    CHECKCAST java/util/Collection
    ASTORE 33
   L186
    ICONST_0
    ISTORE 34
   L187
    LINENUMBER 366 L187
    ALOAD 33
   L188
    LINENUMBER 367 L188
    ASTORE 35
   L189
    LINENUMBER 369 L189
    ALOAD 35
    ICONST_0
    ANEWARRAY java/lang/String
    INVOKEINTERFACE java/util/Collection.toArray ([Ljava/lang/Object;)[Ljava/lang/Object; (itf)
    DUP
    LDC "null cannot be cast to non-null type kotlin.Array<T of kotlin.collections.ArraysKt__ArraysJVMKt.toTypedArray>"
    INVOKESTATIC kotlin/jvm/internal/Intrinsics.checkNotNull (Ljava/lang/Object;Ljava/lang/String;)V
   L190
    CHECKCAST [Ljava/lang/String;
   L191
    LINENUMBER 136 L191
    ALOAD 27
    CHECKCAST java/util/Collection
    INVOKESTATIC kotlin/collections/CollectionsKt.toIntArray (Ljava/util/Collection;)[I
   L192
    LINENUMBER 137 L192
    ALOAD 29
   L193
    LINENUMBER 138 L193
    GETSTATIC al/aoli/exchain/runtime/analyzers/AffectedVarDriver.type : Lal/aoli/exchain/runtime/objects/Type;
    GETSTATIC al/aoli/exchain/runtime/objects/Type.Hybrid : Lal/aoli/exchain/runtime/objects/Type;
    IF_ACMPNE L194
    ICONST_0
    NEWARRAY T_INT
    GOTO L195
   L194
    LINENUMBER 141 L194
   FRAME FULL [al/aoli/exchain/runtime/analyzers/AffectedVarDriver java/lang/Throwable java/lang/String java/lang/String J J I I al/aoli/exchain/runtime/objects/AffectedVarResult java/lang/String java/lang/String al/aoli/exchain/runtime/analyzers/AffectedVarClassReader I al/aoli/exchain/runtime/analyzers/AffectedVarClassVisitor [Lkotlin/Pair; kotlin/Pair java/util/List java/util/List [Lkotlin/Triple; [I kotlin/Triple java/util/List java/util/List java/util/List kotlin/Pair java/util/List java/util/List [Lkotlin/Pair; [Ljava/lang/String; [Ljava/lang/String; T java/util/Collection I java/util/Collection] [L161 L161 I java/lang/String java/lang/String java/lang/String J J I [I [Ljava/lang/String; [I [Ljava/lang/String; [I [Ljava/lang/String; [I [Lkotlin/Pair;]
    ALOAD 21
   L195
    LINENUMBER 143 L195
   FRAME FULL [al/aoli/exchain/runtime/analyzers/AffectedVarDriver java/lang/Throwable java/lang/String java/lang/String J J I I al/aoli/exchain/runtime/objects/AffectedVarResult java/lang/String java/lang/String al/aoli/exchain/runtime/analyzers/AffectedVarClassReader I al/aoli/exchain/runtime/analyzers/AffectedVarClassVisitor [Lkotlin/Pair; kotlin/Pair java/util/List java/util/List [Lkotlin/Triple; [I kotlin/Triple java/util/List java/util/List java/util/List kotlin/Pair java/util/List java/util/List [Lkotlin/Pair; [Ljava/lang/String; [Ljava/lang/String; T java/util/Collection I java/util/Collection] [L161 L161 I java/lang/String java/lang/String java/lang/String J J I [I [Ljava/lang/String; [I [Ljava/lang/String; [I [Ljava/lang/String; [I [Lkotlin/Pair; [I]
    ALOAD 30
   L196
    LINENUMBER 144 L196
    ALOAD 31
   L197
    LINENUMBER 118 L197
    INVOKESPECIAL al/aoli/exchain/runtime/objects/AffectedVarResult.<init> (ILjava/lang/String;Ljava/lang/String;Ljava/lang/String;JJZ[I[Ljava/lang/String;[I[Ljava/lang/String;[I[Ljava/lang/String;[I[Lkotlin/Pair;[I[Ljava/lang/String;[Ljava/lang/String;)V
   L198
    LINENUMBER 117 L198
    ASTORE 32
   L199
    LINENUMBER 146 L199
    GETSTATIC al/aoli/exchain/runtime/analyzers/ExceptionLogger.INSTANCE : Lal/aoli/exchain/runtime/analyzers/ExceptionLogger;
    ALOAD 32
    INVOKEVIRTUAL al/aoli/exchain/runtime/analyzers/ExceptionLogger.logAffectedVarResult (Lal/aoli/exchain/runtime/objects/AffectedVarResult;)V
   L200
    LINENUMBER 147 L200
    ALOAD 0
    INVOKEVIRTUAL al/aoli/exchain/runtime/analyzers/AffectedVarDriver.getStore ()Lal/aoli/exchain/runtime/store/AffectedVarStore;
    ALOAD 2
    ALOAD 3
    LLOAD 4
    LLOAD 6
    ILOAD 8
    ALOAD 32
    INVOKEINTERFACE al/aoli/exchain/runtime/store/AffectedVarStore.putCachedAffectedVarResult (Ljava/lang/String;Ljava/lang/String;JJZLal/aoli/exchain/runtime/objects/AffectedVarResult;)V (itf)
   L201
    LINENUMBER 148 L201
    INVOKESTATIC al/aoli/exchain/runtime/analyzers/AffectedVarDriverKt.access$getLogger$p ()Lal/aoli/exchain/runtime/logger/Logger;
    NEW al/aoli/exchain/runtime/analyzers/AffectedVarDriver$analyzeAffectedVar$2
    DUP
    ALOAD 32
    INVOKESPECIAL al/aoli/exchain/runtime/analyzers/AffectedVarDriver$analyzeAffectedVar$2.<init> (Lal/aoli/exchain/runtime/objects/AffectedVarResult;)V
    CHECKCAST kotlin/jvm/functions/Function0
    INVOKEVIRTUAL al/aoli/exchain/runtime/logger/Logger.info (Lkotlin/jvm/functions/Function0;)V
   L202
    LINENUMBER 149 L202
    ALOAD 32
    ARETURN
   L203
    LOCALVARIABLE result Lal/aoli/exchain/runtime/objects/AffectedVarResult; L20 L9 10
    LOCALVARIABLE path Ljava/lang/String; L34 L35 16
    LOCALVARIABLE e2 Ljava/lang/Throwable; L37 L36 17
    LOCALVARIABLE e1 Ljava/io/IOException; L0 L31 15
    LOCALVARIABLE $i$a$-filter-AffectedVarDriver$analyzeAffectedVar$affectedFields$1 I L70 L72 28
    LOCALVARIABLE it Lkotlin/Pair; L69 L72 27
    LOCALVARIABLE element$iv$iv Ljava/lang/Object; L68 L73 26
    LOCALVARIABLE $i$f$filterTo I L65 L74 24
    LOCALVARIABLE $this$filterTo$iv$iv Ljava/lang/Iterable; L64 L74 22
    LOCALVARIABLE destination$iv$iv Ljava/util/Collection; L64 L74 23
    LOCALVARIABLE $i$f$filter I L63 L76 21
    LOCALVARIABLE $this$filter$iv Ljava/lang/Iterable; L62 L76 20
    LOCALVARIABLE $i$f$toTypedArray I L79 L82 22
    LOCALVARIABLE thisCollection$iv Ljava/util/Collection; L81 L82 23
    LOCALVARIABLE $this$toTypedArray$iv Ljava/util/Collection; L78 L82 21
    LOCALVARIABLE $i$f$emptyArray I L85 L86 21
    LOCALVARIABLE $i$f$toTypedArray I L92 L95 25
    LOCALVARIABLE thisCollection$iv Ljava/util/Collection; L94 L95 26
    LOCALVARIABLE $this$toTypedArray$iv Ljava/util/Collection; L91 L95 24
    LOCALVARIABLE $i$f$emptyArray I L97 L98 24
    LOCALVARIABLE $i$f$toTypedArray I L115 L118 31
    LOCALVARIABLE thisCollection$iv Ljava/util/Collection; L117 L118 32
    LOCALVARIABLE $this$toTypedArray$iv Ljava/util/Collection; L114 L118 30
    LOCALVARIABLE $i$f$emptyArray I L120 L121 30
    LOCALVARIABLE $i$f$toTypedArray I L128 L131 34
    LOCALVARIABLE thisCollection$iv Ljava/util/Collection; L130 L131 35
    LOCALVARIABLE $this$toTypedArray$iv Ljava/util/Collection; L127 L131 33
    LOCALVARIABLE $i$f$emptyArray I L133 L134 33
    LOCALVARIABLE $i$f$toTypedArray I L144 L147 35
    LOCALVARIABLE thisCollection$iv Ljava/util/Collection; L146 L147 36
    LOCALVARIABLE $this$toTypedArray$iv Ljava/util/Collection; L143 L147 34
    LOCALVARIABLE $i$f$emptyArray I L149 L150 34
    LOCALVARIABLE $i$f$toTypedArray I L154 L157 36
    LOCALVARIABLE thisCollection$iv Ljava/util/Collection; L156 L157 37
    LOCALVARIABLE $this$toTypedArray$iv Ljava/util/Collection; L153 L157 35
    LOCALVARIABLE $i$f$emptyArray I L159 L160 35
    LOCALVARIABLE $i$f$toTypedArray I L173 L176 34
    LOCALVARIABLE thisCollection$iv Ljava/util/Collection; L175 L176 35
    LOCALVARIABLE $this$toTypedArray$iv Ljava/util/Collection; L172 L176 33
    LOCALVARIABLE $i$f$toTypedArray I L180 L183 34
    LOCALVARIABLE thisCollection$iv Ljava/util/Collection; L182 L183 35
    LOCALVARIABLE $this$toTypedArray$iv Ljava/util/Collection; L179 L183 33
    LOCALVARIABLE $i$f$toTypedArray I L187 L190 34
    LOCALVARIABLE thisCollection$iv Ljava/util/Collection; L189 L190 35
    LOCALVARIABLE $this$toTypedArray$iv Ljava/util/Collection; L186 L190 33
    LOCALVARIABLE label I L8 L203 9
    LOCALVARIABLE cached Lal/aoli/exchain/runtime/objects/AffectedVarResult; L23 L203 10
    LOCALVARIABLE classPath Ljava/lang/String; L28 L203 11
    LOCALVARIABLE className Ljava/lang/String; L29 L203 12
    LOCALVARIABLE classReader Lal/aoli/exchain/runtime/analyzers/AffectedVarClassReader; L40 L203 13
    LOCALVARIABLE sourceIdentified Z L41 L203 14
    LOCALVARIABLE visitor Lal/aoli/exchain/runtime/analyzers/AffectedVarClassVisitor; L53 L203 15
    LOCALVARIABLE affectedFields [Lkotlin/Pair; L87 L203 16
    LOCALVARIABLE affectedFieldLine Ljava/util/List; L88 L203 18
    LOCALVARIABLE affectedFieldName Ljava/util/List; L89 L203 19
    LOCALVARIABLE affectedVars [Lkotlin/Triple; L99 L203 20
    LOCALVARIABLE sourceLocalVariable [I L102 L203 21
    LOCALVARIABLE affectedLocalLine Ljava/util/List; L110 L203 23
    LOCALVARIABLE affectedLocalIndex Ljava/util/List; L111 L203 24
    LOCALVARIABLE affectedLocalName Ljava/util/List; L112 L203 25
    LOCALVARIABLE affectedStaticFieldLine Ljava/util/List; L123 L203 27
    LOCALVARIABLE affectedStaticFieldName Ljava/util/List; L125 L203 28
    LOCALVARIABLE sourceLines [Lkotlin/Pair; L135 L203 29
    LOCALVARIABLE sourceField [Ljava/lang/String; L151 L203 30
    LOCALVARIABLE sourceStaticField [Ljava/lang/String; L161 L203 31
    LOCALVARIABLE result Lal/aoli/exchain/runtime/objects/AffectedVarResult; L199 L203 32
    LOCALVARIABLE this Lal/aoli/exchain/runtime/analyzers/AffectedVarDriver; L6 L203 0
    LOCALVARIABLE e Ljava/lang/Throwable; L6 L203 1
    LOCALVARIABLE clazz Ljava/lang/String; L6 L203 2
    LOCALVARIABLE method Ljava/lang/String; L6 L203 3
    LOCALVARIABLE throwIndex J L6 L203 4
    LOCALVARIABLE catchIndex J L6 L203 6
    LOCALVARIABLE isThrowInsn Z L6 L203 8
    MAXSTACK = 24
    MAXLOCALS = 38

  // access flags 0x11
  public final analyzeSourceFields(Ljava/lang/Object;Lal/aoli/exchain/runtime/objects/AffectedVarResult;Ljava/lang/Object;Ljava/lang/String;)Z
    TRYCATCHBLOCK L0 L1 L1 java/lang/Exception
    TRYCATCHBLOCK L2 L3 L3 java/lang/Exception
    TRYCATCHBLOCK L4 L5 L5 java/lang/Exception
   L6
    ALOAD 2
    LDC "affectedVarResult"
    INVOKESTATIC kotlin/jvm/internal/Intrinsics.checkNotNullParameter (Ljava/lang/Object;Ljava/lang/String;)V
    ALOAD 3
    LDC "exception"
    INVOKESTATIC kotlin/jvm/internal/Intrinsics.checkNotNullParameter (Ljava/lang/Object;Ljava/lang/String;)V
    ALOAD 4
    LDC "location"
    INVOKESTATIC kotlin/jvm/internal/Intrinsics.checkNotNullParameter (Ljava/lang/Object;Ljava/lang/String;)V
   L7
    LINENUMBER 234 L7
    ALOAD 3
    INVOKESTATIC java/lang/System.identityHashCode (Ljava/lang/Object;)I
    ISTORE 5
   L8
    LINENUMBER 235 L8
    ICONST_0
    ISTORE 6
   L9
    LINENUMBER 236 L9
    ALOAD 1
    IFNULL L10
    ALOAD 1
    INSTANCEOF edu/columbia/cs/psl/phosphor/struct/TaintedWithObjTag
    IFEQ L10
   L0
    LINENUMBER 237 L0
    NOP
   L11
    LINENUMBER 238 L11
    ALOAD 1
    CHECKCAST edu/columbia/cs/psl/phosphor/struct/TaintedWithObjTag
    INVOKEINTERFACE edu/columbia/cs/psl/phosphor/struct/TaintedWithObjTag.getPHOSPHOR_TAG ()Ljava/lang/Object; (itf)
    CHECKCAST edu/columbia/cs/psl/phosphor/runtime/Taint
    ASTORE 7
   L12
    LINENUMBER 239 L12
    ALOAD 7
    IFNULL L10
   L13
    LINENUMBER 240 L13
    ALOAD 7
    INVOKEVIRTUAL edu/columbia/cs/psl/phosphor/runtime/Taint.getLabels ()[Ljava/lang/Object;
    DUP
    LDC "taint.labels"
    INVOKESTATIC kotlin/jvm/internal/Intrinsics.checkNotNullExpressionValue (Ljava/lang/Object;Ljava/lang/String;)V
    ASTORE 8
    ICONST_0
    ISTORE 9
    ALOAD 8
    ARRAYLENGTH
    ISTORE 10
   L14
   FRAME FULL [al/aoli/exchain/runtime/analyzers/AffectedVarDriver java/lang/Object al/aoli/exchain/runtime/objects/AffectedVarResult java/lang/Object java/lang/String I I edu/columbia/cs/psl/phosphor/runtime/Taint [Ljava/lang/Object; I I] []
    ILOAD 9
    ILOAD 10
    IF_ICMPGE L10
    ALOAD 8
    ILOAD 9
    AALOAD
    ASTORE 11
   L15
    LINENUMBER 241 L15
    ALOAD 11
    INSTANCEOF java/lang/Integer
    IFEQ L16
    GETSTATIC al/aoli/exchain/runtime/analyzers/AffectedVarDriver.exceptionStore : Ljava/util/Map;
    ALOAD 11
    INVOKEINTERFACE java/util/Map.containsKey (Ljava/lang/Object;)Z (itf)
   L17
    LINENUMBER 241 L17
    IFEQ L16
    ALOAD 11
    ILOAD 5
    INVOKESTATIC java/lang/Integer.valueOf (I)Ljava/lang/Integer;
    INVOKESTATIC kotlin/jvm/internal/Intrinsics.areEqual (Ljava/lang/Object;Ljava/lang/Object;)Z
    IFNE L16
   L18
    LINENUMBER 242 L18
    GETSTATIC al/aoli/exchain/runtime/analyzers/ExceptionLogger.INSTANCE : Lal/aoli/exchain/runtime/analyzers/ExceptionLogger;
    ALOAD 11
    CHECKCAST java/lang/Number
    INVOKEVIRTUAL java/lang/Number.intValue ()I
    ILOAD 5
    INVOKEVIRTUAL al/aoli/exchain/runtime/analyzers/ExceptionLogger.logDependency (II)V
   L19
    LINENUMBER 243 L19
    ICONST_1
    ISTORE 6
   L16
    LINENUMBER 240 L16
   FRAME FULL [al/aoli/exchain/runtime/analyzers/AffectedVarDriver java/lang/Object al/aoli/exchain/runtime/objects/AffectedVarResult java/lang/Object java/lang/String I I edu/columbia/cs/psl/phosphor/runtime/Taint [Ljava/lang/Object; I I java/lang/Object] []
    IINC 9 1
    GOTO L14
   L1
    LINENUMBER 247 L1
   FRAME FULL [al/aoli/exchain/runtime/analyzers/AffectedVarDriver java/lang/Object al/aoli/exchain/runtime/objects/AffectedVarResult java/lang/Object java/lang/String I I] [java/lang/Exception]
    ASTORE 7
   L20
    LINENUMBER 248 L20
    INVOKESTATIC al/aoli/exchain/runtime/analyzers/AffectedVarDriverKt.access$getLogger$p ()Lal/aoli/exchain/runtime/logger/Logger;
    NEW al/aoli/exchain/runtime/analyzers/AffectedVarDriver$analyzeSourceFields$1
    DUP
    ALOAD 1
    ALOAD 7
    INVOKESPECIAL al/aoli/exchain/runtime/analyzers/AffectedVarDriver$analyzeSourceFields$1.<init> (Ljava/lang/Object;Ljava/lang/Exception;)V
    CHECKCAST kotlin/jvm/functions/Function0
    INVOKEVIRTUAL al/aoli/exchain/runtime/logger/Logger.warn (Lkotlin/jvm/functions/Function0;)V
   L10
    LINENUMBER 252 L10
   FRAME FULL [al/aoli/exchain/runtime/analyzers/AffectedVarDriver java/lang/Object al/aoli/exchain/runtime/objects/AffectedVarResult java/lang/Object java/lang/String I I] []
    ALOAD 1
    IFNULL L21
   L22
    LINENUMBER 253 L22
    ALOAD 2
    INVOKEVIRTUAL al/aoli/exchain/runtime/objects/AffectedVarResult.getSourceField ()[Ljava/lang/String;
    ASTORE 7
    ICONST_0
    ISTORE 8
    ALOAD 7
    ARRAYLENGTH
    ISTORE 9
   L23
   FRAME FULL [al/aoli/exchain/runtime/analyzers/AffectedVarDriver java/lang/Object al/aoli/exchain/runtime/objects/AffectedVarResult java/lang/Object java/lang/String I I [Ljava/lang/String; I I] []
    ILOAD 8
    ILOAD 9
    IF_ICMPGE L21
    ALOAD 7
    ILOAD 8
    AALOAD
    ASTORE 10
   L2
    LINENUMBER 254 L2
    NOP
   L24
    LINENUMBER 255 L24
    ALOAD 1
    INVOKEVIRTUAL java/lang/Object.getClass ()Ljava/lang/Class;
    NEW java/lang/StringBuilder
    DUP
    INVOKESPECIAL java/lang/StringBuilder.<init> ()V
    ALOAD 10
    INVOKEVIRTUAL java/lang/StringBuilder.append (Ljava/lang/String;)Ljava/lang/StringBuilder;
    LDC "PHOSPHOR_TAG"
    INVOKEVIRTUAL java/lang/StringBuilder.append (Ljava/lang/String;)Ljava/lang/StringBuilder;
    INVOKEVIRTUAL java/lang/StringBuilder.toString ()Ljava/lang/String;
    INVOKEVIRTUAL java/lang/Class.getDeclaredField (Ljava/lang/String;)Ljava/lang/reflect/Field;
    ASTORE 11
   L25
    LINENUMBER 256 L25
    ALOAD 11
    ICONST_1
    INVOKEVIRTUAL java/lang/reflect/Field.setAccessible (Z)V
   L26
    LINENUMBER 257 L26
    ALOAD 11
    ALOAD 1
    INVOKEVIRTUAL java/lang/reflect/Field.get (Ljava/lang/Object;)Ljava/lang/Object;
    CHECKCAST edu/columbia/cs/psl/phosphor/runtime/Taint
    DUP
    IFNONNULL L27
    POP
    GOTO L28
   L27
   FRAME FULL [al/aoli/exchain/runtime/analyzers/AffectedVarDriver java/lang/Object al/aoli/exchain/runtime/objects/AffectedVarResult java/lang/Object java/lang/String I I [Ljava/lang/String; I I java/lang/String java/lang/reflect/Field] [edu/columbia/cs/psl/phosphor/runtime/Taint]
    ASTORE 12
   L29
    LINENUMBER 258 L29
    ALOAD 12
    INVOKEVIRTUAL edu/columbia/cs/psl/phosphor/runtime/Taint.getLabels ()[Ljava/lang/Object;
    DUP
    LDC "taint.labels"
    INVOKESTATIC kotlin/jvm/internal/Intrinsics.checkNotNullExpressionValue (Ljava/lang/Object;Ljava/lang/String;)V
    ASTORE 13
    ICONST_0
    ISTORE 14
    ALOAD 13
    ARRAYLENGTH
    ISTORE 15
   L30
   FRAME FULL [al/aoli/exchain/runtime/analyzers/AffectedVarDriver java/lang/Object al/aoli/exchain/runtime/objects/AffectedVarResult java/lang/Object java/lang/String I I [Ljava/lang/String; I I java/lang/String java/lang/reflect/Field edu/columbia/cs/psl/phosphor/runtime/Taint [Ljava/lang/Object; I I] []
    ILOAD 14
    ILOAD 15
    IF_ICMPGE L28
    ALOAD 13
    ILOAD 14
    AALOAD
    ASTORE 16
   L31
    LINENUMBER 259 L31
    ALOAD 16
    INSTANCEOF java/lang/Integer
    IFEQ L32
    GETSTATIC al/aoli/exchain/runtime/analyzers/AffectedVarDriver.exceptionStore : Ljava/util/Map;
    ALOAD 16
    INVOKEINTERFACE java/util/Map.containsKey (Ljava/lang/Object;)Z (itf)
   L33
    LINENUMBER 259 L33
    IFEQ L32
    ALOAD 16
    ILOAD 5
    INVOKESTATIC java/lang/Integer.valueOf (I)Ljava/lang/Integer;
    INVOKESTATIC kotlin/jvm/internal/Intrinsics.areEqual (Ljava/lang/Object;Ljava/lang/Object;)Z
    IFNE L32
   L34
    LINENUMBER 260 L34
    GETSTATIC al/aoli/exchain/runtime/analyzers/ExceptionLogger.INSTANCE : Lal/aoli/exchain/runtime/analyzers/ExceptionLogger;
    ALOAD 16
    CHECKCAST java/lang/Number
    INVOKEVIRTUAL java/lang/Number.intValue ()I
    ILOAD 5
    INVOKEVIRTUAL al/aoli/exchain/runtime/analyzers/ExceptionLogger.logDependency (II)V
   L35
    LINENUMBER 261 L35
    ICONST_1
    ISTORE 6
   L32
    LINENUMBER 258 L32
   FRAME FULL [al/aoli/exchain/runtime/analyzers/AffectedVarDriver java/lang/Object al/aoli/exchain/runtime/objects/AffectedVarResult java/lang/Object java/lang/String I I [Ljava/lang/String; I I java/lang/String java/lang/reflect/Field edu/columbia/cs/psl/phosphor/runtime/Taint [Ljava/lang/Object; I I java/lang/Object] []
    IINC 14 1
    GOTO L30
   L3
    LINENUMBER 264 L3
   FRAME FULL [al/aoli/exchain/runtime/analyzers/AffectedVarDriver java/lang/Object al/aoli/exchain/runtime/objects/AffectedVarResult java/lang/Object java/lang/String I I [Ljava/lang/String; I I java/lang/String] [java/lang/Exception]
    ASTORE 11
   L36
    LINENUMBER 265 L36
    INVOKESTATIC al/aoli/exchain/runtime/analyzers/AffectedVarDriverKt.access$getLogger$p ()Lal/aoli/exchain/runtime/logger/Logger;
    NEW al/aoli/exchain/runtime/analyzers/AffectedVarDriver$analyzeSourceFields$2
    DUP
    ALOAD 10
    ALOAD 1
    ALOAD 11
    INVOKESPECIAL al/aoli/exchain/runtime/analyzers/AffectedVarDriver$analyzeSourceFields$2.<init> (Ljava/lang/String;Ljava/lang/Object;Ljava/lang/Exception;)V
    CHECKCAST kotlin/jvm/functions/Function0
    INVOKEVIRTUAL al/aoli/exchain/runtime/logger/Logger.warn (Lkotlin/jvm/functions/Function0;)V
   L28
    LINENUMBER 253 L28
   FRAME FULL [al/aoli/exchain/runtime/analyzers/AffectedVarDriver java/lang/Object al/aoli/exchain/runtime/objects/AffectedVarResult java/lang/Object java/lang/String I I [Ljava/lang/String; I I java/lang/String java/lang/Object] []
    IINC 8 1
    GOTO L23
   L21
    LINENUMBER 273 L21
   FRAME FULL [al/aoli/exchain/runtime/analyzers/AffectedVarDriver java/lang/Object al/aoli/exchain/runtime/objects/AffectedVarResult java/lang/Object java/lang/String I I] []
    ALOAD 2
    INVOKEVIRTUAL al/aoli/exchain/runtime/objects/AffectedVarResult.getSourceStaticField ()[Ljava/lang/String;
    ASTORE 7
    ICONST_0
    ISTORE 8
    ALOAD 7
    ARRAYLENGTH
    ISTORE 9
   L37
   FRAME FULL [al/aoli/exchain/runtime/analyzers/AffectedVarDriver java/lang/Object al/aoli/exchain/runtime/objects/AffectedVarResult java/lang/Object java/lang/String I I [Ljava/lang/String; I I] []
    ILOAD 8
    ILOAD 9
    IF_ICMPGE L38
    ALOAD 7
    ILOAD 8
    AALOAD
    ASTORE 10
   L4
    LINENUMBER 274 L4
    NOP
   L39
    LINENUMBER 275 L39
    ALOAD 10
    CHECKCAST java/lang/CharSequence
    ICONST_1
    ANEWARRAY java/lang/String
    ASTORE 12
    ALOAD 12
    ICONST_0
    LDC "#"
    AASTORE
    ALOAD 12
    ICONST_0
    ICONST_0
    BIPUSH 6
    ACONST_NULL
    INVOKESTATIC kotlin/text/StringsKt.split$default (Ljava/lang/CharSequence;[Ljava/lang/String;ZIILjava/lang/Object;)Ljava/util/List;
    ASTORE 11
    ALOAD 11
    ICONST_0
    INVOKEINTERFACE java/util/List.get (I)Ljava/lang/Object; (itf)
   L40
    LINENUMBER 275 L40
    CHECKCAST java/lang/String
    ASTORE 12
   L41
    ALOAD 11
    ICONST_1
    INVOKEINTERFACE java/util/List.get (I)Ljava/lang/Object; (itf)
   L42
    LINENUMBER 275 L42
    CHECKCAST java/lang/String
    ASTORE 13
   L43
    LINENUMBER 276 L43
    ALOAD 12
    LDC "/"
    LDC "."
    ICONST_0
    ICONST_4
    ACONST_NULL
    INVOKESTATIC kotlin/text/StringsKt.replace$default (Ljava/lang/String;Ljava/lang/String;Ljava/lang/String;ZILjava/lang/Object;)Ljava/lang/String;
    INVOKESTATIC java/lang/Class.forName (Ljava/lang/String;)Ljava/lang/Class;
    ASTORE 14
   L44
    LINENUMBER 277 L44
    ALOAD 14
    NEW java/lang/StringBuilder
    DUP
    INVOKESPECIAL java/lang/StringBuilder.<init> ()V
    ALOAD 13
    INVOKEVIRTUAL java/lang/StringBuilder.append (Ljava/lang/String;)Ljava/lang/StringBuilder;
    LDC "PHOSPHOR_TAG"
    INVOKEVIRTUAL java/lang/StringBuilder.append (Ljava/lang/String;)Ljava/lang/StringBuilder;
    INVOKEVIRTUAL java/lang/StringBuilder.toString ()Ljava/lang/String;
    INVOKEVIRTUAL java/lang/Class.getField (Ljava/lang/String;)Ljava/lang/reflect/Field;
    ASTORE 15
   L45
    LINENUMBER 278 L45
    ALOAD 15
    ALOAD 1
    INVOKEVIRTUAL java/lang/reflect/Field.get (Ljava/lang/Object;)Ljava/lang/Object;
    CHECKCAST edu/columbia/cs/psl/phosphor/runtime/Taint
    DUP
    IFNONNULL L46
    POP
    GOTO L47
   L46
   FRAME FULL [al/aoli/exchain/runtime/analyzers/AffectedVarDriver java/lang/Object al/aoli/exchain/runtime/objects/AffectedVarResult java/lang/Object java/lang/String I I [Ljava/lang/String; I I java/lang/String java/util/List java/lang/String java/lang/String java/lang/Class java/lang/reflect/Field] [edu/columbia/cs/psl/phosphor/runtime/Taint]
    ASTORE 16
   L48
    LINENUMBER 279 L48
    ALOAD 16
    INVOKEVIRTUAL edu/columbia/cs/psl/phosphor/runtime/Taint.getLabels ()[Ljava/lang/Object;
    DUP
    LDC "taint.labels"
    INVOKESTATIC kotlin/jvm/internal/Intrinsics.checkNotNullExpressionValue (Ljava/lang/Object;Ljava/lang/String;)V
    ASTORE 17
    ICONST_0
    ISTORE 18
    ALOAD 17
    ARRAYLENGTH
    ISTORE 19
   L49
   FRAME FULL [al/aoli/exchain/runtime/analyzers/AffectedVarDriver java/lang/Object al/aoli/exchain/runtime/objects/AffectedVarResult java/lang/Object java/lang/String I I [Ljava/lang/String; I I java/lang/String java/util/List java/lang/String java/lang/String java/lang/Class java/lang/reflect/Field edu/columbia/cs/psl/phosphor/runtime/Taint [Ljava/lang/Object; I I] []
    ILOAD 18
    ILOAD 19
    IF_ICMPGE L47
    ALOAD 17
    ILOAD 18
    AALOAD
    ASTORE 20
   L50
    LINENUMBER 280 L50
    ALOAD 20
    INSTANCEOF java/lang/Integer
    IFEQ L51
    GETSTATIC al/aoli/exchain/runtime/analyzers/AffectedVarDriver.exceptionStore : Ljava/util/Map;
    ALOAD 20
    INVOKEINTERFACE java/util/Map.containsKey (Ljava/lang/Object;)Z (itf)
   L52
    LINENUMBER 280 L52
    IFEQ L51
    ALOAD 20
    ILOAD 5
    INVOKESTATIC java/lang/Integer.valueOf (I)Ljava/lang/Integer;
    INVOKESTATIC kotlin/jvm/internal/Intrinsics.areEqual (Ljava/lang/Object;Ljava/lang/Object;)Z
    IFNE L51
   L53
    LINENUMBER 281 L53
    GETSTATIC al/aoli/exchain/runtime/analyzers/ExceptionLogger.INSTANCE : Lal/aoli/exchain/runtime/analyzers/ExceptionLogger;
    ALOAD 20
    CHECKCAST java/lang/Number
    INVOKEVIRTUAL java/lang/Number.intValue ()I
    ILOAD 5
    INVOKEVIRTUAL al/aoli/exchain/runtime/analyzers/ExceptionLogger.logDependency (II)V
   L54
    LINENUMBER 282 L54
    ICONST_1
    ISTORE 6
   L51
    LINENUMBER 279 L51
   FRAME FULL [al/aoli/exchain/runtime/analyzers/AffectedVarDriver java/lang/Object al/aoli/exchain/runtime/objects/AffectedVarResult java/lang/Object java/lang/String I I [Ljava/lang/String; I I java/lang/String java/util/List java/lang/String java/lang/String java/lang/Class java/lang/reflect/Field edu/columbia/cs/psl/phosphor/runtime/Taint [Ljava/lang/Object; I I java/lang/Object] []
    IINC 18 1
    GOTO L49
   L5
    LINENUMBER 285 L5
   FRAME FULL [al/aoli/exchain/runtime/analyzers/AffectedVarDriver java/lang/Object al/aoli/exchain/runtime/objects/AffectedVarResult java/lang/Object java/lang/String I I [Ljava/lang/String; I I java/lang/String] [java/lang/Exception]
    ASTORE 11
   L55
    LINENUMBER 286 L55
    INVOKESTATIC al/aoli/exchain/runtime/analyzers/AffectedVarDriverKt.access$getLogger$p ()Lal/aoli/exchain/runtime/logger/Logger;
    NEW al/aoli/exchain/runtime/analyzers/AffectedVarDriver$analyzeSourceFields$3
    DUP
    ALOAD 10
    ALOAD 11
    INVOKESPECIAL al/aoli/exchain/runtime/analyzers/AffectedVarDriver$analyzeSourceFields$3.<init> (Ljava/lang/String;Ljava/lang/Exception;)V
    CHECKCAST kotlin/jvm/functions/Function0
    INVOKEVIRTUAL al/aoli/exchain/runtime/logger/Logger.warn (Lkotlin/jvm/functions/Function0;)V
   L47
    LINENUMBER 273 L47
   FRAME FULL [al/aoli/exchain/runtime/analyzers/AffectedVarDriver java/lang/Object al/aoli/exchain/runtime/objects/AffectedVarResult java/lang/Object java/lang/String I I [Ljava/lang/String; I I java/lang/String java/lang/Object] []
    IINC 8 1
    GOTO L37
   L38
    LINENUMBER 289 L38
   FRAME FULL [al/aoli/exchain/runtime/analyzers/AffectedVarDriver java/lang/Object al/aoli/exchain/runtime/objects/AffectedVarResult java/lang/Object java/lang/String I I [Ljava/lang/String; I I] []
    ILOAD 6
    IRETURN
   L56
    LOCALVARIABLE label Ljava/lang/Object; L15 L1 11
    LOCALVARIABLE taint Ledu/columbia/cs/psl/phosphor/runtime/Taint; L12 L1 7
    LOCALVARIABLE e Ljava/lang/Exception; L20 L10 7
    LOCALVARIABLE label Ljava/lang/Object; L31 L3 16
    LOCALVARIABLE field Ljava/lang/reflect/Field; L25 L3 11
    LOCALVARIABLE taint Ledu/columbia/cs/psl/phosphor/runtime/Taint; L29 L3 12
    LOCALVARIABLE e Ljava/lang/Exception; L36 L28 11
    LOCALVARIABLE name Ljava/lang/String; L2 L21 10
    LOCALVARIABLE label Ljava/lang/Object; L50 L5 20
    LOCALVARIABLE clazzName Ljava/lang/String; L41 L5 12
    LOCALVARIABLE fieldName Ljava/lang/String; L43 L5 13
    LOCALVARIABLE clazz Ljava/lang/Class; L44 L5 14
    LOCALVARIABLE field Ljava/lang/reflect/Field; L45 L5 15
    LOCALVARIABLE taint Ledu/columbia/cs/psl/phosphor/runtime/Taint; L48 L5 16
    LOCALVARIABLE e Ljava/lang/Exception; L55 L47 11
    LOCALVARIABLE name Ljava/lang/String; L4 L38 10
    LOCALVARIABLE origin I L8 L56 5
    LOCALVARIABLE causeIdentified Z L9 L56 6
    LOCALVARIABLE this Lal/aoli/exchain/runtime/analyzers/AffectedVarDriver; L6 L56 0
    LOCALVARIABLE obj Ljava/lang/Object; L6 L56 1
    LOCALVARIABLE affectedVarResult Lal/aoli/exchain/runtime/objects/AffectedVarResult; L6 L56 2
    LOCALVARIABLE exception Ljava/lang/Object; L6 L56 3
    LOCALVARIABLE location Ljava/lang/String; L6 L56 4
    MAXSTACK = 6
    MAXLOCALS = 21

  // access flags 0x11
  public final analyzeSourceVars(Ljava/lang/Object;Ljava/lang/Object;Ljava/lang/String;)Z
   L0
    ALOAD 1
    LDC "obj"
    INVOKESTATIC kotlin/jvm/internal/Intrinsics.checkNotNullParameter (Ljava/lang/Object;Ljava/lang/String;)V
    ALOAD 2
    LDC "exception"
    INVOKESTATIC kotlin/jvm/internal/Intrinsics.checkNotNullParameter (Ljava/lang/Object;Ljava/lang/String;)V
    ALOAD 3
    LDC "location"
    INVOKESTATIC kotlin/jvm/internal/Intrinsics.checkNotNullParameter (Ljava/lang/Object;Ljava/lang/String;)V
   L1
    LINENUMBER 293 L1
    INVOKESTATIC al/aoli/exchain/runtime/analyzers/AffectedVarDriverKt.access$getLogger$p ()Lal/aoli/exchain/runtime/logger/Logger;
    NEW al/aoli/exchain/runtime/analyzers/AffectedVarDriver$analyzeSourceVars$1
    DUP
    ALOAD 1
    ALOAD 3
    INVOKESPECIAL al/aoli/exchain/runtime/analyzers/AffectedVarDriver$analyzeSourceVars$1.<init> (Ljava/lang/Object;Ljava/lang/String;)V
    CHECKCAST kotlin/jvm/functions/Function0
    INVOKEVIRTUAL al/aoli/exchain/runtime/logger/Logger.info (Lkotlin/jvm/functions/Function0;)V
   L2
    LINENUMBER 294 L2
    ALOAD 2
    INVOKESTATIC java/lang/System.identityHashCode (Ljava/lang/Object;)I
    ISTORE 4
   L3
    LINENUMBER 296 L3
    ALOAD 1
    ASTORE 7
   L4
    LINENUMBER 297 L4
    ALOAD 7
    INSTANCEOF edu/columbia/cs/psl/phosphor/runtime/Taint
    IFEQ L5
    ALOAD 1
    CHECKCAST edu/columbia/cs/psl/phosphor/runtime/Taint
    GOTO L6
   L5
    LINENUMBER 298 L5
   FRAME FULL [al/aoli/exchain/runtime/analyzers/AffectedVarDriver java/lang/Object java/lang/Object java/lang/String I T T java/lang/Object] []
    ALOAD 7
    INSTANCEOF edu/columbia/cs/psl/phosphor/struct/TaintedWithObjTag
    IFEQ L7
    ALOAD 1
    CHECKCAST edu/columbia/cs/psl/phosphor/struct/TaintedWithObjTag
    INVOKEINTERFACE edu/columbia/cs/psl/phosphor/struct/TaintedWithObjTag.getPHOSPHOR_TAG ()Ljava/lang/Object; (itf)
    CHECKCAST edu/columbia/cs/psl/phosphor/runtime/Taint
    GOTO L6
   L7
    LINENUMBER 299 L7
   FRAME FULL [al/aoli/exchain/runtime/analyzers/AffectedVarDriver java/lang/Object java/lang/Object java/lang/String I T T java/lang/Object] []
    ACONST_NULL
   L6
    LINENUMBER 296 L6
   FRAME FULL [al/aoli/exchain/runtime/analyzers/AffectedVarDriver java/lang/Object java/lang/Object java/lang/String I T T java/lang/Object] [edu/columbia/cs/psl/phosphor/runtime/Taint]
    DUP
    IFNONNULL L8
    POP
   L9
    LINENUMBER 301 L9
    ICONST_0
    IRETURN
   L8
    LINENUMBER 296 L8
    LINENUMBER 295 L8
   FRAME FULL [al/aoli/exchain/runtime/analyzers/AffectedVarDriver java/lang/Object java/lang/Object java/lang/String I T T java/lang/Object] [edu/columbia/cs/psl/phosphor/runtime/Taint]
    ASTORE 5
   L10
    LINENUMBER 302 L10
    ICONST_0
    ISTORE 6
   L11
    LINENUMBER 303 L11
    ALOAD 5
    INVOKEVIRTUAL edu/columbia/cs/psl/phosphor/runtime/Taint.getLabels ()[Ljava/lang/Object;
    DUP
    LDC "taint.labels"
    INVOKESTATIC kotlin/jvm/internal/Intrinsics.checkNotNullExpressionValue (Ljava/lang/Object;Ljava/lang/String;)V
    ASTORE 7
    ICONST_0
    ISTORE 8
    ALOAD 7
    ARRAYLENGTH
    ISTORE 9
   L12
   FRAME FULL [al/aoli/exchain/runtime/analyzers/AffectedVarDriver java/lang/Object java/lang/Object java/lang/String I edu/columbia/cs/psl/phosphor/runtime/Taint I [Ljava/lang/Object; I I] []
    ILOAD 8
    ILOAD 9
    IF_ICMPGE L13
    ALOAD 7
    ILOAD 8
    AALOAD
    ASTORE 10
   L14
    LINENUMBER 304 L14
    ALOAD 10
    INSTANCEOF java/lang/Integer
    IFEQ L15
    GETSTATIC al/aoli/exchain/runtime/analyzers/AffectedVarDriver.exceptionStore : Ljava/util/Map;
    ALOAD 10
    INVOKEINTERFACE java/util/Map.containsKey (Ljava/lang/Object;)Z (itf)
   L16
    LINENUMBER 304 L16
    IFEQ L15
    ALOAD 10
    ILOAD 4
    INVOKESTATIC java/lang/Integer.valueOf (I)Ljava/lang/Integer;
    INVOKESTATIC kotlin/jvm/internal/Intrinsics.areEqual (Ljava/lang/Object;Ljava/lang/Object;)Z
    IFNE L15
   L17
    LINENUMBER 305 L17
    GETSTATIC al/aoli/exchain/runtime/analyzers/ExceptionLogger.INSTANCE : Lal/aoli/exchain/runtime/analyzers/ExceptionLogger;
    ALOAD 10
    CHECKCAST java/lang/Number
    INVOKEVIRTUAL java/lang/Number.intValue ()I
    ILOAD 4
    INVOKEVIRTUAL al/aoli/exchain/runtime/analyzers/ExceptionLogger.logDependency (II)V
   L18
    LINENUMBER 306 L18
    ICONST_1
    ISTORE 6
   L15
    LINENUMBER 303 L15
   FRAME FULL [al/aoli/exchain/runtime/analyzers/AffectedVarDriver java/lang/Object java/lang/Object java/lang/String I edu/columbia/cs/psl/phosphor/runtime/Taint I [Ljava/lang/Object; I I java/lang/Object] []
    IINC 8 1
    GOTO L12
   L13
    LINENUMBER 309 L13
   FRAME FULL [al/aoli/exchain/runtime/analyzers/AffectedVarDriver java/lang/Object java/lang/Object java/lang/String I edu/columbia/cs/psl/phosphor/runtime/Taint I [Ljava/lang/Object; I I] []
    ILOAD 6
    IRETURN
   L19
    LOCALVARIABLE label Ljava/lang/Object; L14 L13 10
    LOCALVARIABLE origin I L3 L19 4
    LOCALVARIABLE taint Ledu/columbia/cs/psl/phosphor/runtime/Taint; L10 L19 5
    LOCALVARIABLE causeIdentified Z L11 L19 6
    LOCALVARIABLE this Lal/aoli/exchain/runtime/analyzers/AffectedVarDriver; L0 L19 0
    LOCALVARIABLE obj Ljava/lang/Object; L0 L19 1
    LOCALVARIABLE exception Ljava/lang/Object; L0 L19 2
    LOCALVARIABLE location Ljava/lang/String; L0 L19 3
    MAXSTACK = 5
    MAXLOCALS = 11

  // access flags 0x11
  public final taintObject(Ledu/columbia/cs/psl/phosphor/struct/TaintedWithObjTag;Ljava/lang/Object;)V
   L0
    ALOAD 1
    LDC "obj"
    INVOKESTATIC kotlin/jvm/internal/Intrinsics.checkNotNullParameter (Ljava/lang/Object;Ljava/lang/String;)V
    ALOAD 2
    LDC "exception"
    INVOKESTATIC kotlin/jvm/internal/Intrinsics.checkNotNullParameter (Ljava/lang/Object;Ljava/lang/String;)V
   L1
    LINENUMBER 219 L1
    ALOAD 2
    INVOKESTATIC java/lang/System.identityHashCode (Ljava/lang/Object;)I
    ISTORE 3
   L2
    ILOAD 3
    INVOKESTATIC java/lang/Integer.valueOf (I)Ljava/lang/Integer;
    ASTORE 4
   L3
    LINENUMBER 220 L3
    GETSTATIC al/aoli/exchain/runtime/analyzers/AffectedVarDriver.exceptionStore : Ljava/util/Map;
    ALOAD 4
    ALOAD 2
    INVOKEINTERFACE java/util/Map.put (Ljava/lang/Object;Ljava/lang/Object;)Ljava/lang/Object; (itf)
    POP
   L4
    LINENUMBER 221 L4
    ALOAD 1
    INVOKEINTERFACE edu/columbia/cs/psl/phosphor/struct/TaintedWithObjTag.getPHOSPHOR_TAG ()Ljava/lang/Object; (itf)
    IFNULL L5
   L6
    LINENUMBER 222 L6
    ALOAD 1
    ALOAD 1
    INVOKEINTERFACE edu/columbia/cs/psl/phosphor/struct/TaintedWithObjTag.getPHOSPHOR_TAG ()Ljava/lang/Object; (itf)
    DUP
    LDC "null cannot be cast to non-null type edu.columbia.cs.psl.phosphor.runtime.Taint<kotlin.Int>"
    INVOKESTATIC kotlin/jvm/internal/Intrinsics.checkNotNull (Ljava/lang/Object;Ljava/lang/String;)V
    CHECKCAST edu/columbia/cs/psl/phosphor/runtime/Taint
    ILOAD 3
    INVOKESTATIC java/lang/Integer.valueOf (I)Ljava/lang/Integer;
    INVOKESTATIC edu/columbia/cs/psl/phosphor/runtime/Taint.withLabel (Ljava/lang/Object;)Ledu/columbia/cs/psl/phosphor/runtime/Taint;
    INVOKEVIRTUAL edu/columbia/cs/psl/phosphor/runtime/Taint.union (Ledu/columbia/cs/psl/phosphor/runtime/Taint;)Ledu/columbia/cs/psl/phosphor/runtime/Taint;
    INVOKEINTERFACE edu/columbia/cs/psl/phosphor/struct/TaintedWithObjTag.setPHOSPHOR_TAG (Ljava/lang/Object;)V (itf)
    GOTO L7
   L5
    LINENUMBER 224 L5
   FRAME FULL [al/aoli/exchain/runtime/analyzers/AffectedVarDriver edu/columbia/cs/psl/phosphor/struct/TaintedWithObjTag java/lang/Object I java/lang/Integer] []
    ALOAD 1
    ILOAD 3
    INVOKESTATIC java/lang/Integer.valueOf (I)Ljava/lang/Integer;
    INVOKESTATIC edu/columbia/cs/psl/phosphor/runtime/Taint.withLabel (Ljava/lang/Object;)Ledu/columbia/cs/psl/phosphor/runtime/Taint;
    INVOKEINTERFACE edu/columbia/cs/psl/phosphor/struct/TaintedWithObjTag.setPHOSPHOR_TAG (Ljava/lang/Object;)V (itf)
   L7
    LINENUMBER 226 L7
   FRAME FULL [al/aoli/exchain/runtime/analyzers/AffectedVarDriver edu/columbia/cs/psl/phosphor/struct/TaintedWithObjTag java/lang/Object I java/lang/Integer] []
    RETURN
   L8
    LOCALVARIABLE label I L2 L8 3
    LOCALVARIABLE this Lal/aoli/exchain/runtime/analyzers/AffectedVarDriver; L0 L8 0
    LOCALVARIABLE obj Ledu/columbia/cs/psl/phosphor/struct/TaintedWithObjTag; L0 L8 1
    LOCALVARIABLE exception Ljava/lang/Object; L0 L8 2
    MAXSTACK = 4
    MAXLOCALS = 5

  // access flags 0x11
  public final updateAffectedFields(Ljava/lang/Object;Lal/aoli/exchain/runtime/objects/AffectedVarResult;Ljava/lang/Object;)V
    TRYCATCHBLOCK L0 L1 L2 java/lang/Exception
    TRYCATCHBLOCK L3 L4 L5 java/lang/Exception
   L6
    ALOAD 2
    LDC "affectedVarResult"
    INVOKESTATIC kotlin/jvm/internal/Intrinsics.checkNotNullParameter (Ljava/lang/Object;Ljava/lang/String;)V
    ALOAD 3
    LDC "exception"
    INVOKESTATIC kotlin/jvm/internal/Intrinsics.checkNotNullParameter (Ljava/lang/Object;Ljava/lang/String;)V
   L7
    LINENUMBER 161 L7
    ALOAD 3
    INVOKESTATIC java/lang/System.identityHashCode (Ljava/lang/Object;)I
    ISTORE 4
   L8
    ILOAD 4
    INVOKESTATIC java/lang/Integer.valueOf (I)Ljava/lang/Integer;
    ASTORE 6
   L9
    LINENUMBER 162 L9
    GETSTATIC al/aoli/exchain/runtime/analyzers/AffectedVarDriver.exceptionStore : Ljava/util/Map;
    ALOAD 6
    ALOAD 3
    INVOKEINTERFACE java/util/Map.put (Ljava/lang/Object;Ljava/lang/Object;)Ljava/lang/Object; (itf)
    POP
   L10
    LINENUMBER 163 L10
    ALOAD 1
    IFNULL L11
   L12
    LINENUMBER 164 L12
    ALOAD 2
    INVOKEVIRTUAL al/aoli/exchain/runtime/objects/AffectedVarResult.getAffectedFieldName ()[Ljava/lang/String;
    ASTORE 5
    ICONST_0
    ISTORE 6
    ALOAD 5
    ARRAYLENGTH
    ISTORE 7
   L13
   FRAME FULL [al/aoli/exchain/runtime/analyzers/AffectedVarDriver java/lang/Object al/aoli/exchain/runtime/objects/AffectedVarResult java/lang/Object I [Ljava/lang/String; I I] []
    ILOAD 6
    ILOAD 7
    IF_ICMPGE L11
    ALOAD 5
    ILOAD 6
    AALOAD
    ASTORE 8
   L0
    LINENUMBER 165 L0
    NOP
   L14
    LINENUMBER 166 L14
    ALOAD 1
    INVOKEVIRTUAL java/lang/Object.getClass ()Ljava/lang/Class;
    NEW java/lang/StringBuilder
    DUP
    INVOKESPECIAL java/lang/StringBuilder.<init> ()V
    ALOAD 8
    INVOKEVIRTUAL java/lang/StringBuilder.append (Ljava/lang/String;)Ljava/lang/StringBuilder;
    LDC "PHOSPHOR_TAG"
    INVOKEVIRTUAL java/lang/StringBuilder.append (Ljava/lang/String;)Ljava/lang/StringBuilder;
    INVOKEVIRTUAL java/lang/StringBuilder.toString ()Ljava/lang/String;
    INVOKEVIRTUAL java/lang/Class.getField (Ljava/lang/String;)Ljava/lang/reflect/Field;
    ASTORE 9
   L15
    LINENUMBER 167 L15
    ALOAD 9
    ICONST_1
    INVOKEVIRTUAL java/lang/reflect/Field.setAccessible (Z)V
   L16
    LINENUMBER 168 L16
    ALOAD 9
    ALOAD 1
    INVOKEVIRTUAL java/lang/reflect/Field.get (Ljava/lang/Object;)Ljava/lang/Object;
    CHECKCAST edu/columbia/cs/psl/phosphor/runtime/Taint
    ASTORE 10
   L17
    LINENUMBER 170 L17
    ALOAD 10
    IFNONNULL L18
   L19
    LINENUMBER 171 L19
    ILOAD 4
    INVOKESTATIC java/lang/Integer.valueOf (I)Ljava/lang/Integer;
    INVOKESTATIC edu/columbia/cs/psl/phosphor/runtime/Taint.withLabel (Ljava/lang/Object;)Ledu/columbia/cs/psl/phosphor/runtime/Taint;
    GOTO L20
   L18
    LINENUMBER 173 L18
   FRAME FULL [al/aoli/exchain/runtime/analyzers/AffectedVarDriver java/lang/Object al/aoli/exchain/runtime/objects/AffectedVarResult java/lang/Object I [Ljava/lang/String; I I java/lang/String java/lang/reflect/Field edu/columbia/cs/psl/phosphor/runtime/Taint] []
    ALOAD 10
    ILOAD 4
    INVOKESTATIC java/lang/Integer.valueOf (I)Ljava/lang/Integer;
    INVOKESTATIC edu/columbia/cs/psl/phosphor/runtime/Taint.withLabel (Ljava/lang/Object;)Ledu/columbia/cs/psl/phosphor/runtime/Taint;
    INVOKEVIRTUAL edu/columbia/cs/psl/phosphor/runtime/Taint.union (Ledu/columbia/cs/psl/phosphor/runtime/Taint;)Ledu/columbia/cs/psl/phosphor/runtime/Taint;
   L20
    LINENUMBER 170 L20
    LINENUMBER 169 L20
   FRAME FULL [al/aoli/exchain/runtime/analyzers/AffectedVarDriver java/lang/Object al/aoli/exchain/runtime/objects/AffectedVarResult java/lang/Object I [Ljava/lang/String; I I java/lang/String java/lang/reflect/Field edu/columbia/cs/psl/phosphor/runtime/Taint] [edu/columbia/cs/psl/phosphor/runtime/Taint]
    ASTORE 11
   L21
    LINENUMBER 175 L21
    ALOAD 9
    ALOAD 1
    ALOAD 11
    INVOKEVIRTUAL java/lang/reflect/Field.set (Ljava/lang/Object;Ljava/lang/Object;)V
   L22
    LINENUMBER 177 L22
    ALOAD 1
    INVOKEVIRTUAL java/lang/Object.getClass ()Ljava/lang/Class;
    ALOAD 8
    INVOKEVIRTUAL java/lang/Class.getDeclaredField (Ljava/lang/String;)Ljava/lang/reflect/Field;
    ASTORE 12
   L23
    LINENUMBER 178 L23
    ALOAD 12
    INVOKEVIRTUAL java/lang/reflect/Field.trySetAccessible ()Z
    IFNE L24
   L25
    LINENUMBER 179 L25
    GOTO L26
   L24
    LINENUMBER 181 L24
   FRAME FULL [al/aoli/exchain/runtime/analyzers/AffectedVarDriver java/lang/Object al/aoli/exchain/runtime/objects/AffectedVarResult java/lang/Object I [Ljava/lang/String; I I java/lang/String java/lang/reflect/Field edu/columbia/cs/psl/phosphor/runtime/Taint edu/columbia/cs/psl/phosphor/runtime/Taint java/lang/reflect/Field] []
    ALOAD 12
    ALOAD 1
    INVOKEVIRTUAL java/lang/reflect/Field.get (Ljava/lang/Object;)Ljava/lang/Object;
    ASTORE 13
   L27
    LINENUMBER 182 L27
    ALOAD 13
    IFNULL L26
    ALOAD 13
    INSTANCEOF edu/columbia/cs/psl/phosphor/struct/TaintedWithObjTag
    IFEQ L26
   L28
    LINENUMBER 184 L28
    ALOAD 13
    CHECKCAST edu/columbia/cs/psl/phosphor/struct/TaintedWithObjTag
    INVOKEINTERFACE edu/columbia/cs/psl/phosphor/struct/TaintedWithObjTag.getPHOSPHOR_TAG ()Ljava/lang/Object; (itf)
    IFNONNULL L29
   L30
    LINENUMBER 185 L30
    ILOAD 4
    INVOKESTATIC java/lang/Integer.valueOf (I)Ljava/lang/Integer;
    INVOKESTATIC edu/columbia/cs/psl/phosphor/runtime/Taint.withLabel (Ljava/lang/Object;)Ledu/columbia/cs/psl/phosphor/runtime/Taint;
    GOTO L31
   L29
    LINENUMBER 187 L29
   FRAME FULL [al/aoli/exchain/runtime/analyzers/AffectedVarDriver java/lang/Object al/aoli/exchain/runtime/objects/AffectedVarResult java/lang/Object I [Ljava/lang/String; I I java/lang/String java/lang/reflect/Field edu/columbia/cs/psl/phosphor/runtime/Taint edu/columbia/cs/psl/phosphor/runtime/Taint java/lang/reflect/Field java/lang/Object] []
    ALOAD 13
    CHECKCAST edu/columbia/cs/psl/phosphor/struct/TaintedWithObjTag
    INVOKEINTERFACE edu/columbia/cs/psl/phosphor/struct/TaintedWithObjTag.getPHOSPHOR_TAG ()Ljava/lang/Object; (itf)
    DUP
    LDC "null cannot be cast to non-null type edu.columbia.cs.psl.phosphor.runtime.Taint<kotlin.Int>"
    INVOKESTATIC kotlin/jvm/internal/Intrinsics.checkNotNull (Ljava/lang/Object;Ljava/lang/String;)V
    CHECKCAST edu/columbia/cs/psl/phosphor/runtime/Taint
    ILOAD 4
    INVOKESTATIC java/lang/Integer.valueOf (I)Ljava/lang/Integer;
    INVOKESTATIC edu/columbia/cs/psl/phosphor/runtime/Taint.withLabel (Ljava/lang/Object;)Ledu/columbia/cs/psl/phosphor/runtime/Taint;
    INVOKEVIRTUAL edu/columbia/cs/psl/phosphor/runtime/Taint.union (Ledu/columbia/cs/psl/phosphor/runtime/Taint;)Ledu/columbia/cs/psl/phosphor/runtime/Taint;
   L31
    LINENUMBER 184 L31
    LINENUMBER 183 L31
   FRAME FULL [al/aoli/exchain/runtime/analyzers/AffectedVarDriver java/lang/Object al/aoli/exchain/runtime/objects/AffectedVarResult java/lang/Object I [Ljava/lang/String; I I java/lang/String java/lang/reflect/Field edu/columbia/cs/psl/phosphor/runtime/Taint edu/columbia/cs/psl/phosphor/runtime/Taint java/lang/reflect/Field java/lang/Object] [edu/columbia/cs/psl/phosphor/runtime/Taint]
    ASTORE 14
   L32
    LINENUMBER 189 L32
    ALOAD 13
    CHECKCAST edu/columbia/cs/psl/phosphor/struct/TaintedWithObjTag
    ALOAD 14
    INVOKEINTERFACE edu/columbia/cs/psl/phosphor/struct/TaintedWithObjTag.setPHOSPHOR_TAG (Ljava/lang/Object;)V (itf)
   L1
    GOTO L26
   L2
    LINENUMBER 191 L2
   FRAME FULL [al/aoli/exchain/runtime/analyzers/AffectedVarDriver java/lang/Object al/aoli/exchain/runtime/objects/AffectedVarResult java/lang/Object I [Ljava/lang/String; I I java/lang/String] [java/lang/Exception]
    ASTORE 9
   L33
    LINENUMBER 192 L33
    INVOKESTATIC al/aoli/exchain/runtime/analyzers/AffectedVarDriverKt.access$getLogger$p ()Lal/aoli/exchain/runtime/logger/Logger;
    NEW al/aoli/exchain/runtime/analyzers/AffectedVarDriver$updateAffectedFields$1
    DUP
    ALOAD 8
    ALOAD 1
    ALOAD 9
    INVOKESPECIAL al/aoli/exchain/runtime/analyzers/AffectedVarDriver$updateAffectedFields$1.<init> (Ljava/lang/String;Ljava/lang/Object;Ljava/lang/Exception;)V
    CHECKCAST kotlin/jvm/functions/Function0
    INVOKEVIRTUAL al/aoli/exchain/runtime/logger/Logger.warn (Lkotlin/jvm/functions/Function0;)V
   L26
    LINENUMBER 164 L26
   FRAME FULL [al/aoli/exchain/runtime/analyzers/AffectedVarDriver java/lang/Object al/aoli/exchain/runtime/objects/AffectedVarResult java/lang/Object I [Ljava/lang/String; I I java/lang/String java/lang/Object] []
    IINC 6 1
    GOTO L13
   L11
    LINENUMBER 199 L11
   FRAME FULL [al/aoli/exchain/runtime/analyzers/AffectedVarDriver java/lang/Object al/aoli/exchain/runtime/objects/AffectedVarResult java/lang/Object I] []
    ALOAD 2
    INVOKEVIRTUAL al/aoli/exchain/runtime/objects/AffectedVarResult.getAffectedStaticFieldName ()[Ljava/lang/String;
    ASTORE 5
    ICONST_0
    ISTORE 6
    ALOAD 5
    ARRAYLENGTH
    ISTORE 7
   L34
   FRAME FULL [al/aoli/exchain/runtime/analyzers/AffectedVarDriver java/lang/Object al/aoli/exchain/runtime/objects/AffectedVarResult java/lang/Object I [Ljava/lang/String; I I] []
    ILOAD 6
    ILOAD 7
    IF_ICMPGE L35
    ALOAD 5
    ILOAD 6
    AALOAD
    ASTORE 8
   L3
    LINENUMBER 200 L3
    NOP
   L36
    LINENUMBER 201 L36
    ALOAD 8
    CHECKCAST java/lang/CharSequence
    ICONST_1
    ANEWARRAY java/lang/String
    ASTORE 10
    ALOAD 10
    ICONST_0
    LDC "#"
    AASTORE
    ALOAD 10
    ICONST_0
    ICONST_0
    BIPUSH 6
    ACONST_NULL
    INVOKESTATIC kotlin/text/StringsKt.split$default (Ljava/lang/CharSequence;[Ljava/lang/String;ZIILjava/lang/Object;)Ljava/util/List;
    ASTORE 9
    ALOAD 9
    ICONST_0
    INVOKEINTERFACE java/util/List.get (I)Ljava/lang/Object; (itf)
   L37
    LINENUMBER 201 L37
    CHECKCAST java/lang/String
    ASTORE 10
   L38
    ALOAD 9
    ICONST_1
    INVOKEINTERFACE java/util/List.get (I)Ljava/lang/Object; (itf)
   L39
    LINENUMBER 201 L39
    CHECKCAST java/lang/String
    ASTORE 11
   L40
    LINENUMBER 202 L40
    ALOAD 10
    LDC "/"
    LDC "."
    ICONST_0
    ICONST_4
    ACONST_NULL
    INVOKESTATIC kotlin/text/StringsKt.replace$default (Ljava/lang/String;Ljava/lang/String;Ljava/lang/String;ZILjava/lang/Object;)Ljava/lang/String;
    INVOKESTATIC java/lang/Class.forName (Ljava/lang/String;)Ljava/lang/Class;
    ASTORE 12
   L41
    LINENUMBER 203 L41
    ALOAD 12
    NEW java/lang/StringBuilder
    DUP
    INVOKESPECIAL java/lang/StringBuilder.<init> ()V
    ALOAD 11
    INVOKEVIRTUAL java/lang/StringBuilder.append (Ljava/lang/String;)Ljava/lang/StringBuilder;
    LDC "PHOSPHOR_TAG"
    INVOKEVIRTUAL java/lang/StringBuilder.append (Ljava/lang/String;)Ljava/lang/StringBuilder;
    INVOKEVIRTUAL java/lang/StringBuilder.toString ()Ljava/lang/String;
    INVOKEVIRTUAL java/lang/Class.getField (Ljava/lang/String;)Ljava/lang/reflect/Field;
    ASTORE 13
   L42
    LINENUMBER 204 L42
    ALOAD 13
    ACONST_NULL
    INVOKEVIRTUAL java/lang/reflect/Field.get (Ljava/lang/Object;)Ljava/lang/Object;
    CHECKCAST edu/columbia/cs/psl/phosphor/runtime/Taint
    ASTORE 14
   L43
    LINENUMBER 206 L43
    ALOAD 14
    IFNONNULL L44
   L45
    LINENUMBER 207 L45
    ILOAD 4
    INVOKESTATIC java/lang/Integer.valueOf (I)Ljava/lang/Integer;
    INVOKESTATIC edu/columbia/cs/psl/phosphor/runtime/Taint.withLabel (Ljava/lang/Object;)Ledu/columbia/cs/psl/phosphor/runtime/Taint;
    GOTO L46
   L44
    LINENUMBER 209 L44
   FRAME FULL [al/aoli/exchain/runtime/analyzers/AffectedVarDriver java/lang/Object al/aoli/exchain/runtime/objects/AffectedVarResult java/lang/Object I [Ljava/lang/String; I I java/lang/String java/util/List java/lang/String java/lang/String java/lang/Class java/lang/reflect/Field edu/columbia/cs/psl/phosphor/runtime/Taint] []
    ALOAD 14
    ILOAD 4
    INVOKESTATIC java/lang/Integer.valueOf (I)Ljava/lang/Integer;
    INVOKESTATIC edu/columbia/cs/psl/phosphor/runtime/Taint.withLabel (Ljava/lang/Object;)Ledu/columbia/cs/psl/phosphor/runtime/Taint;
    INVOKEVIRTUAL edu/columbia/cs/psl/phosphor/runtime/Taint.union (Ledu/columbia/cs/psl/phosphor/runtime/Taint;)Ledu/columbia/cs/psl/phosphor/runtime/Taint;
   L46
    LINENUMBER 206 L46
    LINENUMBER 205 L46
   FRAME FULL [al/aoli/exchain/runtime/analyzers/AffectedVarDriver java/lang/Object al/aoli/exchain/runtime/objects/AffectedVarResult java/lang/Object I [Ljava/lang/String; I I java/lang/String java/util/List java/lang/String java/lang/String java/lang/Class java/lang/reflect/Field edu/columbia/cs/psl/phosphor/runtime/Taint] [edu/columbia/cs/psl/phosphor/runtime/Taint]
    ASTORE 15
   L47
    LINENUMBER 211 L47
    ALOAD 13
    ACONST_NULL
    ALOAD 15
    INVOKEVIRTUAL java/lang/reflect/Field.set (Ljava/lang/Object;Ljava/lang/Object;)V
   L4
    GOTO L48
   L5
    LINENUMBER 212 L5
   FRAME FULL [al/aoli/exchain/runtime/analyzers/AffectedVarDriver java/lang/Object al/aoli/exchain/runtime/objects/AffectedVarResult java/lang/Object I [Ljava/lang/String; I I java/lang/String] [java/lang/Exception]
    ASTORE 9
   L49
    LINENUMBER 213 L49
    INVOKESTATIC al/aoli/exchain/runtime/analyzers/AffectedVarDriverKt.access$getLogger$p ()Lal/aoli/exchain/runtime/logger/Logger;
    NEW al/aoli/exchain/runtime/analyzers/AffectedVarDriver$updateAffectedFields$2
    DUP
    ALOAD 8
    ALOAD 9
    INVOKESPECIAL al/aoli/exchain/runtime/analyzers/AffectedVarDriver$updateAffectedFields$2.<init> (Ljava/lang/String;Ljava/lang/Exception;)V
    CHECKCAST kotlin/jvm/functions/Function0
    INVOKEVIRTUAL al/aoli/exchain/runtime/logger/Logger.warn (Lkotlin/jvm/functions/Function0;)V
   L48
    LINENUMBER 199 L48
   FRAME FULL [al/aoli/exchain/runtime/analyzers/AffectedVarDriver java/lang/Object al/aoli/exchain/runtime/objects/AffectedVarResult java/lang/Object I [Ljava/lang/String; I I java/lang/String java/lang/Object] []
    IINC 6 1
    GOTO L34
   L35
    LINENUMBER 216 L35
   FRAME FULL [al/aoli/exchain/runtime/analyzers/AffectedVarDriver java/lang/Object al/aoli/exchain/runtime/objects/AffectedVarResult java/lang/Object I [Ljava/lang/String; I I] []
    RETURN
   L50
    LOCALVARIABLE tag Ledu/columbia/cs/psl/phosphor/runtime/Taint; L32 L1 14
    LOCALVARIABLE fieldTag Ljava/lang/reflect/Field; L15 L1 9
    LOCALVARIABLE value Ledu/columbia/cs/psl/phosphor/runtime/Taint; L17 L1 10
    LOCALVARIABLE tag Ledu/columbia/cs/psl/phosphor/runtime/Taint; L21 L1 11
    LOCALVARIABLE fieldRef Ljava/lang/reflect/Field; L23 L1 12
    LOCALVARIABLE fieldObj Ljava/lang/Object; L27 L1 13
    LOCALVARIABLE e Ljava/lang/Exception; L33 L26 9
    LOCALVARIABLE name Ljava/lang/String; L0 L11 8
    LOCALVARIABLE clazzName Ljava/lang/String; L38 L4 10
    LOCALVARIABLE fieldName Ljava/lang/String; L40 L4 11
    LOCALVARIABLE clazz Ljava/lang/Class; L41 L4 12
    LOCALVARIABLE field Ljava/lang/reflect/Field; L42 L4 13
    LOCALVARIABLE value Ledu/columbia/cs/psl/phosphor/runtime/Taint; L43 L4 14
    LOCALVARIABLE tag Ledu/columbia/cs/psl/phosphor/runtime/Taint; L47 L4 15
    LOCALVARIABLE e Ljava/lang/Exception; L49 L48 9
    LOCALVARIABLE name Ljava/lang/String; L3 L35 8
    LOCALVARIABLE label I L8 L50 4
    LOCALVARIABLE this Lal/aoli/exchain/runtime/analyzers/AffectedVarDriver; L6 L50 0
    LOCALVARIABLE obj Ljava/lang/Object; L6 L50 1
    LOCALVARIABLE affectedVarResult Lal/aoli/exchain/runtime/objects/AffectedVarResult; L6 L50 2
    LOCALVARIABLE exception Ljava/lang/Object; L6 L50 3
    MAXSTACK = 6
    MAXLOCALS = 16

  // access flags 0x11
  // signature (Ledu/columbia/cs/psl/phosphor/struct/PowerSetTree$SetNode;Ljava/lang/Object;)Ledu/columbia/cs/psl/phosphor/runtime/Taint<*>;
  // declaration: edu.columbia.cs.psl.phosphor.runtime.Taint<?> updateTaint(edu.columbia.cs.psl.phosphor.struct.PowerSetTree$SetNode, java.lang.Object)
  public final updateTaint(Ledu/columbia/cs/psl/phosphor/struct/PowerSetTree$SetNode;Ljava/lang/Object;)Ledu/columbia/cs/psl/phosphor/runtime/Taint;
   L0
    ALOAD 1
    LDC "obj"
    INVOKESTATIC kotlin/jvm/internal/Intrinsics.checkNotNullParameter (Ljava/lang/Object;Ljava/lang/String;)V
    ALOAD 2
    LDC "exception"
    INVOKESTATIC kotlin/jvm/internal/Intrinsics.checkNotNullParameter (Ljava/lang/Object;Ljava/lang/String;)V
   L1
    LINENUMBER 155 L1
    ALOAD 2
    INVOKESTATIC java/lang/System.identityHashCode (Ljava/lang/Object;)I
    ISTORE 3
   L2
    ILOAD 3
    INVOKESTATIC java/lang/Integer.valueOf (I)Ljava/lang/Integer;
    ASTORE 4
   L3
    LINENUMBER 156 L3
    GETSTATIC al/aoli/exchain/runtime/analyzers/AffectedVarDriver.exceptionStore : Ljava/util/Map;
    ALOAD 4
    ALOAD 2
    INVOKEINTERFACE java/util/Map.put (Ljava/lang/Object;Ljava/lang/Object;)Ljava/lang/Object; (itf)
    POP
   L4
    LINENUMBER 157 L4
    ALOAD 1
    ILOAD 3
    INVOKESTATIC java/lang/Integer.valueOf (I)Ljava/lang/Integer;
    INVOKESTATIC edu/columbia/cs/psl/phosphor/runtime/Taint.withLabel (Ljava/lang/Object;)Ledu/columbia/cs/psl/phosphor/runtime/Taint;
    INVOKEVIRTUAL edu/columbia/cs/psl/phosphor/struct/PowerSetTree$SetNode.union (Ledu/columbia/cs/psl/phosphor/runtime/Taint;)Ledu/columbia/cs/psl/phosphor/struct/PowerSetTree$SetNode;
    DUP
    LDC "obj.union(Taint.withLabel(label))"
    INVOKESTATIC kotlin/jvm/internal/Intrinsics.checkNotNullExpressionValue (Ljava/lang/Object;Ljava/lang/String;)V
    CHECKCAST edu/columbia/cs/psl/phosphor/runtime/Taint
    ARETURN
   L5
    LOCALVARIABLE label I L2 L5 3
    LOCALVARIABLE this Lal/aoli/exchain/runtime/analyzers/AffectedVarDriver; L0 L5 0
    LOCALVARIABLE obj Ledu/columbia/cs/psl/phosphor/struct/PowerSetTree$SetNode; L0 L5 1
    LOCALVARIABLE exception Ljava/lang/Object; L0 L5 2
    MAXSTACK = 3
    MAXLOCALS = 5

  // access flags 0x2
  private <init>()V
   L0
    LINENUMBER 18 L0
    ALOAD 0
    INVOKESPECIAL java/lang/Object.<init> ()V
    RETURN
   L1
    LOCALVARIABLE this Lal/aoli/exchain/runtime/analyzers/AffectedVarDriver; L0 L1 0
    MAXSTACK = 1
    MAXLOCALS = 1

  // access flags 0x8
  static <clinit>()V
    NEW al/aoli/exchain/runtime/analyzers/AffectedVarDriver
    DUP
    INVOKESPECIAL al/aoli/exchain/runtime/analyzers/AffectedVarDriver.<init> ()V
    PUTSTATIC al/aoli/exchain/runtime/analyzers/AffectedVarDriver.INSTANCE : Lal/aoli/exchain/runtime/analyzers/AffectedVarDriver;
   L0
    LINENUMBER 20 L0
    GETSTATIC al/aoli/exchain/runtime/objects/Type.Dynamic : Lal/aoli/exchain/runtime/objects/Type;
    PUTSTATIC al/aoli/exchain/runtime/analyzers/AffectedVarDriver.type : Lal/aoli/exchain/runtime/objects/Type;
   L1
    LINENUMBER 21 L1
    GETSTATIC al/aoli/exchain/runtime/analyzers/AffectedVarDriver$store$2.INSTANCE : Lal/aoli/exchain/runtime/analyzers/AffectedVarDriver$store$2;
    CHECKCAST kotlin/jvm/functions/Function0
    INVOKESTATIC kotlin/LazyKt.lazy (Lkotlin/jvm/functions/Function0;)Lkotlin/Lazy;
    PUTSTATIC al/aoli/exchain/runtime/analyzers/AffectedVarDriver.store$delegate : Lkotlin/Lazy;
   L2
    LINENUMBER 28 L2
    NEW java/util/LinkedHashMap
    DUP
    INVOKESPECIAL java/util/LinkedHashMap.<init> ()V
    CHECKCAST java/util/Map
   L3
    LINENUMBER 28 L3
    PUTSTATIC al/aoli/exchain/runtime/analyzers/AffectedVarDriver.exceptionSourceIdentified : Ljava/util/Map;
   L4
    LINENUMBER 152 L4
    NEW java/util/LinkedHashMap
    DUP
    INVOKESPECIAL java/util/LinkedHashMap.<init> ()V
    CHECKCAST java/util/Map
   L5
    LINENUMBER 152 L5
    PUTSTATIC al/aoli/exchain/runtime/analyzers/AffectedVarDriver.exceptionStore : Ljava/util/Map;
    RETURN
    MAXSTACK = 2
    MAXLOCALS = 0

  // access flags 0x11
  public final getType()Lal/aoli/exchain/runtime/objects/Type;
   L0
    LINENUMBER 20 L0
    GETSTATIC al/aoli/exchain/runtime/analyzers/AffectedVarDriver.type : Lal/aoli/exchain/runtime/objects/Type;
    ARETURN
   L1
    LOCALVARIABLE this Lal/aoli/exchain/runtime/analyzers/AffectedVarDriver; L0 L1 0
    MAXSTACK = 1
    MAXLOCALS = 1
}
// class version 52.0 (52)
// access flags 0x31
public final class al/aoli/exchain/runtime/analyzers/AffectedVarDriver {

  // compiled from: AffectedVarDriver.kt

  @Lkotlin/Metadata;(mv={1, 7, 1}, k=1, xi=48, d1={"\u0000`\n\u0002\u0018\u0002\n\u0002\u0010\u0000\n\u0002\u0008\u0002\n\u0002\u0010%\n\u0002\u0010\u0008\n\u0002\u0010\u000b\n\u0002\u0008\u0004\n\u0002\u0010\u000e\n\u0002\u0008\u0005\n\u0002\u0018\u0002\n\u0002\u0008\u0005\n\u0002\u0018\u0002\n\u0002\u0008\u0005\n\u0002\u0018\u0002\n\u0000\n\u0002\u0010\u0003\n\u0002\u0008\u0003\n\u0002\u0010\u0009\n\u0002\u0008\u0009\n\u0002\u0010\u0002\n\u0002\u0018\u0002\n\u0002\u0008\u0002\n\u0002\u0018\u0002\n\u0002\u0018\u0002\n\u0000\u0008\u00c6\u0002\u0018\u00002\u00020\u0001B\u0007\u0008\u0002\u00a2\u0006\u0002\u0010\u0002J8\u0010\u001c\u001a\u0004\u0018\u00010\u001d2\u0006\u0010\u001e\u001a\u00020\u001f2\u0006\u0010 \u001a\u00020\u000b2\u0006\u0010!\u001a\u00020\u000b2\u0006\u0010\"\u001a\u00020#2\u0006\u0010$\u001a\u00020#2\u0006\u0010%\u001a\u00020\u0006J(\u0010&\u001a\u00020\u00062\u0008\u0010'\u001a\u0004\u0018\u00010\u00012\u0006\u0010(\u001a\u00020\u001d2\u0006\u0010)\u001a\u00020\u00012\u0006\u0010*\u001a\u00020\u000bJ\u001e\u0010+\u001a\u00020\u00062\u0006\u0010'\u001a\u00020\u00012\u0006\u0010)\u001a\u00020\u00012\u0006\u0010*\u001a\u00020\u000bJ\u0016\u0010,\u001a\u00020-2\u0006\u0010'\u001a\u00020.2\u0006\u0010)\u001a\u00020\u0001J \u0010/\u001a\u00020-2\u0008\u0010'\u001a\u0004\u0018\u00010\u00012\u0006\u0010(\u001a\u00020\u001d2\u0006\u0010)\u001a\u00020\u0001J\u001a\u00100\u001a\u0006\u0012\u0002\u0008\u0003012\u0006\u0010'\u001a\u0002022\u0006\u0010)\u001a\u00020\u0001R\u001d\u0010\u0003\u001a\u000e\u0012\u0004\u0012\u00020\u0005\u0012\u0004\u0012\u00020\u00060\u0004\u00a2\u0006\u0008\n\u0000\u001a\u0004\u0008\u0007\u0010\u0008R\u001a\u0010\u0009\u001a\u000e\u0012\u0004\u0012\u00020\u0005\u0012\u0004\u0012\u00020\u00010\u0004X\u0082\u0004\u00a2\u0006\u0002\n\u0000R\u001c\u0010\n\u001a\u0004\u0018\u00010\u000bX\u0086\u000e\u00a2\u0006\u000e\n\u0000\u001a\u0004\u0008\u000c\u0010\r\"\u0004\u0008\u000e\u0010\u000fR\u001b\u0010\u0010\u001a\u00020\u00118FX\u0086\u0084\u0002\u00a2\u0006\u000c\n\u0004\u0008\u0014\u0010\u0015\u001a\u0004\u0008\u0012\u0010\u0013R\u001a\u0010\u0016\u001a\u00020\u0017X\u0086\u000e\u00a2\u0006\u000e\n\u0000\u001a\u0004\u0008\u0018\u0010\u0019\"\u0004\u0008\u001a\u0010\u001b\u00a8\u00063"}, d2={"Lal/aoli/exchain/runtime/analyzers/AffectedVarDriver;", "", "()V", "exceptionSourceIdentified", "", "", "", "getExceptionSourceIdentified", "()Ljava/util/Map;", "exceptionStore", "instrumentedClassPath", "", "getInstrumentedClassPath", "()Ljava/lang/String;", "setInstrumentedClassPath", "(Ljava/lang/String;)V", "store", "Lal/aoli/exchain/runtime/store/AffectedVarStore;", "getStore", "()Lal/aoli/exchain/runtime/store/AffectedVarStore;", "store$delegate", "Lkotlin/Lazy;", "type", "Lal/aoli/exchain/runtime/objects/Type;", "getType", "()Lal/aoli/exchain/runtime/objects/Type;", "setType", "(Lal/aoli/exchain/runtime/objects/Type;)V", "analyzeAffectedVar", "Lal/aoli/exchain/runtime/objects/AffectedVarResult;", "e", "", "clazz", "method", "throwIndex", "", "catchIndex", "isThrowInsn", "analyzeSourceFields", "obj", "affectedVarResult", "exception", "location", "analyzeSourceVars", "taintObject", "", "Ledu/columbia/cs/psl/phosphor/struct/TaintedWithObjTag;", "updateAffectedFields", "updateTaint", "Ledu/columbia/cs/psl/phosphor/runtime/Taint;", "Ledu/columbia/cs/psl/phosphor/struct/PowerSetTree$SetNode;", "runtime"})
  // access flags 0x18
  final static INNERCLASS al/aoli/exchain/runtime/analyzers/AffectedVarDriver$analyzeAffectedVar$1 null null
  // access flags 0x18
  final static INNERCLASS al/aoli/exchain/runtime/analyzers/AffectedVarDriver$analyzeAffectedVar$classReader$1 null null
  // access flags 0x18
  final static INNERCLASS al/aoli/exchain/runtime/analyzers/AffectedVarDriver$analyzeAffectedVar$2 null null
  // access flags 0x18
  final static INNERCLASS al/aoli/exchain/runtime/analyzers/AffectedVarDriver$updateAffectedFields$1 null null
  // access flags 0x18
  final static INNERCLASS al/aoli/exchain/runtime/analyzers/AffectedVarDriver$updateAffectedFields$2 null null
  // access flags 0x18
  final static INNERCLASS al/aoli/exchain/runtime/analyzers/AffectedVarDriver$analyzeSourceFields$1 null null
  // access flags 0x18
  final static INNERCLASS al/aoli/exchain/runtime/analyzers/AffectedVarDriver$analyzeSourceFields$2 null null
  // access flags 0x18
  final static INNERCLASS al/aoli/exchain/runtime/analyzers/AffectedVarDriver$analyzeSourceFields$3 null null
  // access flags 0x18
  final static INNERCLASS al/aoli/exchain/runtime/analyzers/AffectedVarDriver$analyzeSourceVars$1 null null
  // access flags 0x18
  final static INNERCLASS al/aoli/exchain/runtime/analyzers/AffectedVarDriver$store$2 null null

  // access flags 0x19
  public final static Lal/aoli/exchain/runtime/analyzers/AffectedVarDriver; INSTANCE

  // access flags 0xA
  private static Ljava/lang/String; instrumentedClassPath

  // access flags 0xA
  private static Lal/aoli/exchain/runtime/objects/Type; type

  // access flags 0x1A
  private final static Lkotlin/Lazy; store$delegate

  // access flags 0x1A
  // signature Ljava/util/Map<Ljava/lang/Integer;Ljava/lang/Boolean;>;
  // declaration: exceptionSourceIdentified extends java.util.Map<java.lang.Integer, java.lang.Boolean>
  private final static Ljava/util/Map; exceptionSourceIdentified

  // access flags 0x1A
  // signature Ljava/util/Map<Ljava/lang/Integer;Ljava/lang/Object;>;
  // declaration: exceptionStore extends java.util.Map<java.lang.Integer, java.lang.Object>
  private final static Ljava/util/Map; exceptionStore

  // access flags 0x11
  public final setType(Lal/aoli/exchain/runtime/objects/Type;)V
   L0
    ALOAD 1
    LDC "<set-?>"
    INVOKESTATIC kotlin/jvm/internal/Intrinsics.checkNotNullParameter (Ljava/lang/Object;Ljava/lang/String;)V
   L1
    LINENUMBER 20 L1
    ALOAD 1
    PUTSTATIC al/aoli/exchain/runtime/analyzers/AffectedVarDriver.type : Lal/aoli/exchain/runtime/objects/Type;
    RETURN
   L2
    LOCALVARIABLE this Lal/aoli/exchain/runtime/analyzers/AffectedVarDriver; L0 L2 0
    LOCALVARIABLE <set-?> Lal/aoli/exchain/runtime/objects/Type; L0 L2 1
    MAXSTACK = 2
    MAXLOCALS = 2

  // access flags 0x11
  public final setInstrumentedClassPath(Ljava/lang/String;)V
   L0
    LINENUMBER 19 L0
    ALOAD 1
    PUTSTATIC al/aoli/exchain/runtime/analyzers/AffectedVarDriver.instrumentedClassPath : Ljava/lang/String;
    RETURN
   L1
    LOCALVARIABLE this Lal/aoli/exchain/runtime/analyzers/AffectedVarDriver; L0 L1 0
    LOCALVARIABLE <set-?> Ljava/lang/String; L0 L1 1
    MAXSTACK = 1
    MAXLOCALS = 2

  // access flags 0x11
  // signature ()Ljava/util/Map<Ljava/lang/Integer;Ljava/lang/Boolean;>;
  // declaration: java.util.Map<java.lang.Integer, java.lang.Boolean> getExceptionSourceIdentified()
  public final getExceptionSourceIdentified()Ljava/util/Map;
   L0
    LINENUMBER 28 L0
    GETSTATIC al/aoli/exchain/runtime/analyzers/AffectedVarDriver.exceptionSourceIdentified : Ljava/util/Map;
    ARETURN
   L1
    LOCALVARIABLE this Lal/aoli/exchain/runtime/analyzers/AffectedVarDriver; L0 L1 0
    MAXSTACK = 1
    MAXLOCALS = 1

  // access flags 0x11
  public final getInstrumentedClassPath()Ljava/lang/String;
   L0
    LINENUMBER 19 L0
    GETSTATIC al/aoli/exchain/runtime/analyzers/AffectedVarDriver.instrumentedClassPath : Ljava/lang/String;
    ARETURN
   L1
    LOCALVARIABLE this Lal/aoli/exchain/runtime/analyzers/AffectedVarDriver; L0 L1 0
    MAXSTACK = 1
    MAXLOCALS = 1

  // access flags 0x11
  public final getStore()Lal/aoli/exchain/runtime/store/AffectedVarStore;
   L0
    LINENUMBER 21 L0
    GETSTATIC al/aoli/exchain/runtime/analyzers/AffectedVarDriver.store$delegate : Lkotlin/Lazy;
    ASTORE 1
    ALOAD 1
    INVOKEINTERFACE kotlin/Lazy.getValue ()Ljava/lang/Object; (itf)
    CHECKCAST al/aoli/exchain/runtime/store/AffectedVarStore
   L1
    LINENUMBER 21 L1
    ARETURN
   L2
    LOCALVARIABLE this Lal/aoli/exchain/runtime/analyzers/AffectedVarDriver; L0 L2 0
    MAXSTACK = 1
    MAXLOCALS = 2

  // access flags 0x11
  public final analyzeAffectedVar(Ljava/lang/Throwable;Ljava/lang/String;Ljava/lang/String;JJZ)Lal/aoli/exchain/runtime/objects/AffectedVarResult;
    TRYCATCHBLOCK L0 L1 L2 java/lang/Throwable
    TRYCATCHBLOCK L3 L4 L5 java/io/IOException
   L6
    ALOAD 1
    LDC "e"
    INVOKESTATIC kotlin/jvm/internal/Intrinsics.checkNotNullParameter (Ljava/lang/Object;Ljava/lang/String;)V
    ALOAD 2
    LDC "clazz"
    INVOKESTATIC kotlin/jvm/internal/Intrinsics.checkNotNullParameter (Ljava/lang/Object;Ljava/lang/String;)V
    ALOAD 3
    LDC "method"
    INVOKESTATIC kotlin/jvm/internal/Intrinsics.checkNotNullParameter (Ljava/lang/Object;Ljava/lang/String;)V
   L7
    LINENUMBER 37 L7
    GETSTATIC al/aoli/exchain/runtime/analyzers/ExceptionLogger.INSTANCE : Lal/aoli/exchain/runtime/analyzers/ExceptionLogger;
    ALOAD 1
    INVOKEVIRTUAL al/aoli/exchain/runtime/analyzers/ExceptionLogger.logException (Ljava/lang/Throwable;)I
    ISTORE 9
   L8
    LINENUMBER 38 L8
    GETSTATIC al/aoli/exchain/runtime/analyzers/AffectedVarDriver.type : Lal/aoli/exchain/runtime/objects/Type;
    GETSTATIC al/aoli/exchain/runtime/objects/Type.Static : Lal/aoli/exchain/runtime/objects/Type;
    IF_ACMPNE L9
   L10
    LINENUMBER 40 L10
    NEW al/aoli/exchain/runtime/objects/AffectedVarResult
    DUP
   L11
    LINENUMBER 41 L11
    ILOAD 9
   L12
    LINENUMBER 42 L12
    ALOAD 1
    INVOKEVIRTUAL java/lang/Object.getClass ()Ljava/lang/Class;
    INVOKEVIRTUAL java/lang/Class.getName ()Ljava/lang/String;
    DUP
    LDC "e.javaClass.name"
    INVOKESTATIC kotlin/jvm/internal/Intrinsics.checkNotNullExpressionValue (Ljava/lang/Object;Ljava/lang/String;)V
   L13
    LINENUMBER 43 L13
    ALOAD 2
   L14
    LINENUMBER 44 L14
    ALOAD 3
   L15
    LINENUMBER 45 L15
    LLOAD 4
   L16
    LINENUMBER 46 L16
    LLOAD 6
   L17
    LINENUMBER 47 L17
    ILOAD 8
   L18
    LINENUMBER 40 L18
    ACONST_NULL
    ACONST_NULL
    ACONST_NULL
    ACONST_NULL
    ACONST_NULL
    ACONST_NULL
    ACONST_NULL
    ACONST_NULL
    ACONST_NULL
    ACONST_NULL
    ACONST_NULL
    LDC 262016
    ACONST_NULL
    INVOKESPECIAL al/aoli/exchain/runtime/objects/AffectedVarResult.<init> (ILjava/lang/String;Ljava/lang/String;Ljava/lang/String;JJZ[I[Ljava/lang/String;[I[Ljava/lang/String;[I[Ljava/lang/String;[I[Lkotlin/Pair;[I[Ljava/lang/String;[Ljava/lang/String;ILkotlin/jvm/internal/DefaultConstructorMarker;)V
   L19
    LINENUMBER 39 L19
    ASTORE 10
   L20
    LINENUMBER 49 L20
    GETSTATIC al/aoli/exchain/runtime/analyzers/ExceptionLogger.INSTANCE : Lal/aoli/exchain/runtime/analyzers/ExceptionLogger;
    ALOAD 10
    INVOKEVIRTUAL al/aoli/exchain/runtime/analyzers/ExceptionLogger.logAffectedVarResult (Lal/aoli/exchain/runtime/objects/AffectedVarResult;)V
   L21
    LINENUMBER 50 L21
    ACONST_NULL
    ARETURN
   L9
    LINENUMBER 53 L9
   FRAME FULL [al/aoli/exchain/runtime/analyzers/AffectedVarDriver java/lang/Throwable java/lang/String java/lang/String J J I I] []
    ALOAD 0
    INVOKEVIRTUAL al/aoli/exchain/runtime/analyzers/AffectedVarDriver.getStore ()Lal/aoli/exchain/runtime/store/AffectedVarStore;
    ALOAD 2
    ALOAD 3
    LLOAD 4
    LLOAD 6
    ILOAD 8
    INVOKEINTERFACE al/aoli/exchain/runtime/store/AffectedVarStore.getCachedAffectedVarResult (Ljava/lang/String;Ljava/lang/String;JJZ)Lal/aoli/exchain/runtime/objects/AffectedVarResult; (itf)
   L22
    LINENUMBER 52 L22
    ASTORE 10
   L23
    LINENUMBER 54 L23
    ALOAD 10
    IFNULL L24
   L25
    LINENUMBER 55 L25
    ALOAD 10
    ILOAD 9
    INVOKEVIRTUAL al/aoli/exchain/runtime/objects/AffectedVarResult.setLabel (I)V
   L26
    LINENUMBER 56 L26
    GETSTATIC al/aoli/exchain/runtime/analyzers/ExceptionLogger.INSTANCE : Lal/aoli/exchain/runtime/analyzers/ExceptionLogger;
    ALOAD 10
    INVOKEVIRTUAL al/aoli/exchain/runtime/analyzers/ExceptionLogger.logAffectedVarResult (Lal/aoli/exchain/runtime/objects/AffectedVarResult;)V
   L27
    LINENUMBER 57 L27
    ALOAD 10
    ARETURN
   L24
    LINENUMBER 59 L24
   FRAME FULL [al/aoli/exchain/runtime/analyzers/AffectedVarDriver java/lang/Throwable java/lang/String java/lang/String J J I I al/aoli/exchain/runtime/objects/AffectedVarResult] []
    ALOAD 2
    ICONST_1
    ALOAD 2
    INVOKEVIRTUAL java/lang/String.length ()I
    ICONST_1
    ISUB
    INVOKESTATIC kotlin/ranges/RangesKt.until (II)Lkotlin/ranges/IntRange;
    INVOKESTATIC kotlin/text/StringsKt.substring (Ljava/lang/String;Lkotlin/ranges/IntRange;)Ljava/lang/String;
    ASTORE 11
   L28
    LINENUMBER 60 L28
    ALOAD 11
    LDC "/"
    LDC "."
    ICONST_0
    ICONST_4
    ACONST_NULL
    INVOKESTATIC kotlin/text/StringsKt.replace$default (Ljava/lang/String;Ljava/lang/String;Ljava/lang/String;ZILjava/lang/Object;)Ljava/lang/String;
    ASTORE 12
   L29
    LINENUMBER 61 L29
    INVOKESTATIC al/aoli/exchain/runtime/analyzers/AffectedVarDriverKt.access$getLogger$p ()Lal/aoli/exchain/runtime/logger/Logger;
    NEW al/aoli/exchain/runtime/analyzers/AffectedVarDriver$analyzeAffectedVar$1
    DUP
    ALOAD 12
    ALOAD 3
    LLOAD 4
    LLOAD 6
    INVOKESPECIAL al/aoli/exchain/runtime/analyzers/AffectedVarDriver$analyzeAffectedVar$1.<init> (Ljava/lang/String;Ljava/lang/String;JJ)V
    CHECKCAST kotlin/jvm/functions/Function0
    INVOKEVIRTUAL al/aoli/exchain/runtime/logger/Logger.info (Lkotlin/jvm/functions/Function0;)V
   L3
    LINENUMBER 65 L3
    NOP
   L30
    LINENUMBER 66 L30
    NEW al/aoli/exchain/runtime/analyzers/AffectedVarClassReader
    DUP
    ALOAD 12
    INVOKESPECIAL al/aoli/exchain/runtime/analyzers/AffectedVarClassReader.<init> (Ljava/lang/String;)V
    ASTORE 14
   L4
    GOTO L31
   L5
    LINENUMBER 67 L5
   FRAME FULL [al/aoli/exchain/runtime/analyzers/AffectedVarDriver java/lang/Throwable java/lang/String java/lang/String J J I I al/aoli/exchain/runtime/objects/AffectedVarResult java/lang/String java/lang/String] [java/io/IOException]
    ASTORE 15
   L0
    LINENUMBER 68 L0
    NOP
   L32
    LINENUMBER 69 L32
    GETSTATIC al/aoli/exchain/runtime/analyzers/AffectedVarDriver.instrumentedClassPath : Ljava/lang/String;
    DUP
    IFNONNULL L33
    POP
    ACONST_NULL
    ARETURN
   L33
   FRAME FULL [al/aoli/exchain/runtime/analyzers/AffectedVarDriver java/lang/Throwable java/lang/String java/lang/String J J I I al/aoli/exchain/runtime/objects/AffectedVarResult java/lang/String java/lang/String T T java/io/IOException] [java/lang/String]
    ASTORE 16
   L34
    LINENUMBER 70 L34
    NEW al/aoli/exchain/runtime/analyzers/AffectedVarClassReader
    DUP
    NEW java/io/File
    DUP
    NEW java/lang/StringBuilder
    DUP
    INVOKESPECIAL java/lang/StringBuilder.<init> ()V
    ALOAD 16
    INVOKEVIRTUAL java/lang/StringBuilder.append (Ljava/lang/String;)Ljava/lang/StringBuilder;
    BIPUSH 47
    INVOKEVIRTUAL java/lang/StringBuilder.append (C)Ljava/lang/StringBuilder;
    ALOAD 11
    INVOKEVIRTUAL java/lang/StringBuilder.append (Ljava/lang/String;)Ljava/lang/StringBuilder;
    LDC ".class"
    INVOKEVIRTUAL java/lang/StringBuilder.append (Ljava/lang/String;)Ljava/lang/StringBuilder;
    INVOKEVIRTUAL java/lang/StringBuilder.toString ()Ljava/lang/String;
    INVOKESPECIAL java/io/File.<init> (Ljava/lang/String;)V
    INVOKESTATIC kotlin/io/FilesKt.readBytes (Ljava/io/File;)[B
    INVOKESPECIAL al/aoli/exchain/runtime/analyzers/AffectedVarClassReader.<init> ([B)V
   L35
    ASTORE 16
   L1
    GOTO L36
   L2
    LINENUMBER 71 L2
   FRAME FULL [al/aoli/exchain/runtime/analyzers/AffectedVarDriver java/lang/Throwable java/lang/String java/lang/String J J I I al/aoli/exchain/runtime/objects/AffectedVarResult java/lang/String java/lang/String T T java/io/IOException] [java/lang/Throwable]
    ASTORE 17
   L37
    LINENUMBER 72 L37
    INVOKESTATIC al/aoli/exchain/runtime/analyzers/AffectedVarDriverKt.access$getLogger$p ()Lal/aoli/exchain/runtime/logger/Logger;
    NEW al/aoli/exchain/runtime/analyzers/AffectedVarDriver$analyzeAffectedVar$classReader$1
    DUP
    ALOAD 12
    INVOKESPECIAL al/aoli/exchain/runtime/analyzers/AffectedVarDriver$analyzeAffectedVar$classReader$1.<init> (Ljava/lang/String;)V
    CHECKCAST kotlin/jvm/functions/Function0
    INVOKEVIRTUAL al/aoli/exchain/runtime/logger/Logger.error (Lkotlin/jvm/functions/Function0;)V
   L38
    LINENUMBER 73 L38
    ACONST_NULL
    ARETURN
   L36
   FRAME FULL [al/aoli/exchain/runtime/analyzers/AffectedVarDriver java/lang/Throwable java/lang/String java/lang/String J J I I al/aoli/exchain/runtime/objects/AffectedVarResult java/lang/String java/lang/String T T java/io/IOException al/aoli/exchain/runtime/analyzers/AffectedVarClassReader] []
    ALOAD 16
    ASTORE 14
   L31
    LINENUMBER 65 L31
   FRAME FULL [al/aoli/exchain/runtime/analyzers/AffectedVarDriver java/lang/Throwable java/lang/String java/lang/String J J I I al/aoli/exchain/runtime/objects/AffectedVarResult java/lang/String java/lang/String T al/aoli/exchain/runtime/analyzers/AffectedVarClassReader] []
    ALOAD 14
   L39
    LINENUMBER 64 L39
    ASTORE 13
   L40
    LINENUMBER 76 L40
    GETSTATIC al/aoli/exchain/runtime/analyzers/AffectedVarDriver.exceptionSourceIdentified : Ljava/util/Map;
    ILOAD 9
    INVOKESTATIC java/lang/Integer.valueOf (I)Ljava/lang/Integer;
    ICONST_0
    INVOKESTATIC java/lang/Boolean.valueOf (Z)Ljava/lang/Boolean;
    INVOKEINTERFACE java/util/Map.getOrDefault (Ljava/lang/Object;Ljava/lang/Object;)Ljava/lang/Object; (itf)
    CHECKCAST java/lang/Boolean
    INVOKEVIRTUAL java/lang/Boolean.booleanValue ()Z
    ISTORE 14
   L41
    LINENUMBER 79 L41
    NEW al/aoli/exchain/runtime/analyzers/AffectedVarClassVisitor
    DUP
   L42
    LINENUMBER 80 L42
    ALOAD 1
   L43
    LINENUMBER 81 L43
    LLOAD 4
   L44
    LINENUMBER 82 L44
    LLOAD 6
   L45
    LINENUMBER 83 L45
    ILOAD 8
   L46
    LINENUMBER 84 L46
    ILOAD 14
    IFNE L47
    ICONST_1
    GOTO L48
   L47
   FRAME FULL [al/aoli/exchain/runtime/analyzers/AffectedVarDriver java/lang/Throwable java/lang/String java/lang/String J J I I al/aoli/exchain/runtime/objects/AffectedVarResult java/lang/String java/lang/String al/aoli/exchain/runtime/analyzers/AffectedVarClassReader I] [L41 L41 java/lang/Throwable J J I]
    ICONST_0
   L48
    LINENUMBER 85 L48
   FRAME FULL [al/aoli/exchain/runtime/analyzers/AffectedVarDriver java/lang/Throwable java/lang/String java/lang/String J J I I al/aoli/exchain/runtime/objects/AffectedVarResult java/lang/String java/lang/String al/aoli/exchain/runtime/analyzers/AffectedVarClassReader I] [L41 L41 java/lang/Throwable J J I I]
    ALOAD 12
   L49
    LINENUMBER 86 L49
    ALOAD 3
   L50
    LINENUMBER 87 L50
    ALOAD 13
   L51
    LINENUMBER 79 L51
    INVOKESPECIAL al/aoli/exchain/runtime/analyzers/AffectedVarClassVisitor.<init> (Ljava/lang/Throwable;JJZZLjava/lang/String;Ljava/lang/String;Lal/aoli/exchain/runtime/analyzers/AffectedVarClassReader;)V
   L52
    LINENUMBER 78 L52
    ASTORE 15
   L53
    LINENUMBER 89 L53
    ALOAD 13
    ALOAD 15
    CHECKCAST al/aoli/exchain/instrumentation/asm/ClassVisitor
    ICONST_0
    INVOKEVIRTUAL al/aoli/exchain/runtime/analyzers/AffectedVarClassReader.accept (Lal/aoli/exchain/instrumentation/asm/ClassVisitor;I)V
   L54
    LINENUMBER 93 L54
    ALOAD 15
    INVOKEVIRTUAL al/aoli/exchain/runtime/analyzers/AffectedVarClassVisitor.getMethodVisitor ()Lal/aoli/exchain/runtime/analyzers/AffectedVarMethodVisitor;
    ASTORE 17
   L55
    LINENUMBER 94 L55
    ALOAD 17
    IFNULL L56
   L57
    LINENUMBER 93 L57
    ALOAD 17
   L58
    LINENUMBER 94 L58
    INVOKEVIRTUAL al/aoli/exchain/runtime/analyzers/AffectedVarMethodVisitor.getAffectedFields ()Ljava/util/Set;
    ASTORE 18
   L59
    LINENUMBER 95 L59
    ALOAD 18
    IFNULL L56
   L60
    LINENUMBER 94 L60
    ALOAD 18
    CHECKCAST java/lang/Iterable
    ASTORE 20
   L61
    LINENUMBER 95 L61
    NOP
   L62
    ICONST_0
    ISTORE 21
   L63
    LINENUMBER 325 L63
    ALOAD 20
    ASTORE 22
    NEW java/util/ArrayList
    DUP
    INVOKESPECIAL java/util/ArrayList.<init> ()V
    CHECKCAST java/util/Collection
    ASTORE 23
   L64
    ICONST_0
    ISTORE 24
   L65
    LINENUMBER 326 L65
    ALOAD 22
    INVOKEINTERFACE java/lang/Iterable.iterator ()Ljava/util/Iterator; (itf)
    ASTORE 25
   L66
   FRAME FULL [al/aoli/exchain/runtime/analyzers/AffectedVarDriver java/lang/Throwable java/lang/String java/lang/String J J I I al/aoli/exchain/runtime/objects/AffectedVarResult java/lang/String java/lang/String al/aoli/exchain/runtime/analyzers/AffectedVarClassReader I al/aoli/exchain/runtime/analyzers/AffectedVarClassVisitor T al/aoli/exchain/runtime/analyzers/AffectedVarMethodVisitor java/util/Set T java/lang/Iterable I java/lang/Iterable java/util/Collection I java/util/Iterator] []
    ALOAD 25
    INVOKEINTERFACE java/util/Iterator.hasNext ()Z (itf)
    IFEQ L67
    ALOAD 25
    INVOKEINTERFACE java/util/Iterator.next ()Ljava/lang/Object; (itf)
    ASTORE 26
   L68
    ALOAD 26
    CHECKCAST kotlin/Pair
    ASTORE 27
   L69
    ICONST_0
    ISTORE 28
   L70
    LINENUMBER 95 L70
    ALOAD 27
    INVOKEVIRTUAL kotlin/Pair.getSecond ()Ljava/lang/Object;
    CHECKCAST java/lang/CharSequence
    LDC "PHOSPHOR"
    CHECKCAST java/lang/CharSequence
    ICONST_0
    ICONST_2
    ACONST_NULL
    INVOKESTATIC kotlin/text/StringsKt.contains$default (Ljava/lang/CharSequence;Ljava/lang/CharSequence;ZILjava/lang/Object;)Z
    IFNE L71
    ICONST_1
    GOTO L72
   L71
   FRAME FULL [al/aoli/exchain/runtime/analyzers/AffectedVarDriver java/lang/Throwable java/lang/String java/lang/String J J I I al/aoli/exchain/runtime/objects/AffectedVarResult java/lang/String java/lang/String al/aoli/exchain/runtime/analyzers/AffectedVarClassReader I al/aoli/exchain/runtime/analyzers/AffectedVarClassVisitor T al/aoli/exchain/runtime/analyzers/AffectedVarMethodVisitor java/util/Set T java/lang/Iterable I java/lang/Iterable java/util/Collection I java/util/Iterator java/lang/Object kotlin/Pair I] []
    ICONST_0
   L72
   FRAME FULL [al/aoli/exchain/runtime/analyzers/AffectedVarDriver java/lang/Throwable java/lang/String java/lang/String J J I I al/aoli/exchain/runtime/objects/AffectedVarResult java/lang/String java/lang/String al/aoli/exchain/runtime/analyzers/AffectedVarClassReader I al/aoli/exchain/runtime/analyzers/AffectedVarClassVisitor T al/aoli/exchain/runtime/analyzers/AffectedVarMethodVisitor java/util/Set T java/lang/Iterable I java/lang/Iterable java/util/Collection I java/util/Iterator java/lang/Object kotlin/Pair I] [I]
    IFEQ L66
    ALOAD 23
    ALOAD 26
    INVOKEINTERFACE java/util/Collection.add (Ljava/lang/Object;)Z (itf)
    POP
   L73
    GOTO L66
   L67
    LINENUMBER 327 L67
   FRAME FULL [al/aoli/exchain/runtime/analyzers/AffectedVarDriver java/lang/Throwable java/lang/String java/lang/String J J I I al/aoli/exchain/runtime/objects/AffectedVarResult java/lang/String java/lang/String al/aoli/exchain/runtime/analyzers/AffectedVarClassReader I al/aoli/exchain/runtime/analyzers/AffectedVarClassVisitor T al/aoli/exchain/runtime/analyzers/AffectedVarMethodVisitor java/util/Set T java/lang/Iterable I java/lang/Iterable java/util/Collection I java/util/Iterator] []
    ALOAD 23
   L74
    CHECKCAST java/util/List
   L75
    LINENUMBER 325 L75
    NOP
   L76
    LINENUMBER 95 L76
    LINENUMBER 96 L76
    LINENUMBER 95 L76
    CHECKCAST java/util/Collection
    ASTORE 21
   L77
    LINENUMBER 96 L77
    NOP
   L78
    ICONST_0
    ISTORE 22
   L79
    LINENUMBER 328 L79
    ALOAD 21
   L80
    LINENUMBER 329 L80
    ASTORE 23
   L81
    LINENUMBER 331 L81
    ALOAD 23
    ICONST_0
    ANEWARRAY kotlin/Pair
    INVOKEINTERFACE java/util/Collection.toArray ([Ljava/lang/Object;)[Ljava/lang/Object; (itf)
    DUP
    LDC "null cannot be cast to non-null type kotlin.Array<T of kotlin.collections.ArraysKt__ArraysJVMKt.toTypedArray>"
    INVOKESTATIC kotlin/jvm/internal/Intrinsics.checkNotNull (Ljava/lang/Object;Ljava/lang/String;)V
   L82
    LINENUMBER 96 L82
    CHECKCAST [Lkotlin/Pair;
   L83
    LINENUMBER 93 L83
    ASTORE 20
    ALOAD 20
    IFNULL L56
    ALOAD 20
    GOTO L84
   L56
    LINENUMBER 97 L56
   FRAME FULL [al/aoli/exchain/runtime/analyzers/AffectedVarDriver java/lang/Throwable java/lang/String java/lang/String J J I I al/aoli/exchain/runtime/objects/AffectedVarResult java/lang/String java/lang/String al/aoli/exchain/runtime/analyzers/AffectedVarClassReader I al/aoli/exchain/runtime/analyzers/AffectedVarClassVisitor T al/aoli/exchain/runtime/analyzers/AffectedVarMethodVisitor] []
    ICONST_0
    ISTORE 21
   L85
    LINENUMBER 332 L85
    ICONST_0
    ANEWARRAY kotlin/Pair
    CHECKCAST [Ljava/lang/Object;
   L86
    CHECKCAST [Lkotlin/Pair;
   L84
    LINENUMBER 93 L84
    LINENUMBER 92 L84
   FRAME FULL [al/aoli/exchain/runtime/analyzers/AffectedVarDriver java/lang/Throwable java/lang/String java/lang/String J J I I al/aoli/exchain/runtime/objects/AffectedVarResult java/lang/String java/lang/String al/aoli/exchain/runtime/analyzers/AffectedVarClassReader I al/aoli/exchain/runtime/analyzers/AffectedVarClassVisitor T al/aoli/exchain/runtime/analyzers/AffectedVarMethodVisitor] [[Lkotlin/Pair;]
    ASTORE 16
   L87
    LINENUMBER 98 L87
    ALOAD 16
    INVOKESTATIC kotlin/collections/ArraysKt.unzip ([Lkotlin/Pair;)Lkotlin/Pair;
    ASTORE 17
    ALOAD 17
    INVOKEVIRTUAL kotlin/Pair.component1 ()Ljava/lang/Object;
    CHECKCAST java/util/List
    ASTORE 18
   L88
    ALOAD 17
    INVOKEVIRTUAL kotlin/Pair.component2 ()Ljava/lang/Object;
    CHECKCAST java/util/List
    ASTORE 19
   L89
    LINENUMBER 100 L89
    ALOAD 15
    INVOKEVIRTUAL al/aoli/exchain/runtime/analyzers/AffectedVarClassVisitor.getMethodVisitor ()Lal/aoli/exchain/runtime/analyzers/AffectedVarMethodVisitor;
    DUP
    IFNULL L90
    INVOKEVIRTUAL al/aoli/exchain/runtime/analyzers/AffectedVarMethodVisitor.getAffectedVars ()Ljava/util/Set;
    DUP
    IFNULL L90
    CHECKCAST java/util/Collection
    ASTORE 24
   L91
    ICONST_0
    ISTORE 25
   L92
    LINENUMBER 333 L92
    ALOAD 24
   L93
    LINENUMBER 334 L93
    ASTORE 26
   L94
    LINENUMBER 336 L94
    ALOAD 26
    ICONST_0
    ANEWARRAY kotlin/Triple
    INVOKEINTERFACE java/util/Collection.toArray ([Ljava/lang/Object;)[Ljava/lang/Object; (itf)
    DUP
    LDC "null cannot be cast to non-null type kotlin.Array<T of kotlin.collections.ArraysKt__ArraysJVMKt.toTypedArray>"
    INVOKESTATIC kotlin/jvm/internal/Intrinsics.checkNotNull (Ljava/lang/Object;Ljava/lang/String;)V
   L95
    LINENUMBER 100 L95
    CHECKCAST [Lkotlin/Triple;
    DUP
    IFNONNULL L96
   L90
   FRAME FULL [al/aoli/exchain/runtime/analyzers/AffectedVarDriver java/lang/Throwable java/lang/String java/lang/String J J I I al/aoli/exchain/runtime/objects/AffectedVarResult java/lang/String java/lang/String al/aoli/exchain/runtime/analyzers/AffectedVarClassReader I al/aoli/exchain/runtime/analyzers/AffectedVarClassVisitor [Lkotlin/Pair; kotlin/Pair java/util/List java/util/List] [java/lang/Object]
    POP
    ICONST_0
    ISTORE 24
   L97
    LINENUMBER 337 L97
    ICONST_0
    ANEWARRAY kotlin/Triple
    CHECKCAST [Ljava/lang/Object;
   L98
    CHECKCAST [Lkotlin/Triple;
   L96
    LINENUMBER 100 L96
   FRAME FULL [al/aoli/exchain/runtime/analyzers/AffectedVarDriver java/lang/Throwable java/lang/String java/lang/String J J I I al/aoli/exchain/runtime/objects/AffectedVarResult java/lang/String java/lang/String al/aoli/exchain/runtime/analyzers/AffectedVarClassReader I al/aoli/exchain/runtime/analyzers/AffectedVarClassVisitor [Lkotlin/Pair; kotlin/Pair java/util/List java/util/List] [[Lkotlin/Triple;]
    ASTORE 20
   L99
    LINENUMBER 102 L99
    ALOAD 15
    INVOKEVIRTUAL al/aoli/exchain/runtime/analyzers/AffectedVarClassVisitor.getMethodVisitor ()Lal/aoli/exchain/runtime/analyzers/AffectedVarMethodVisitor;
    DUP
    IFNULL L100
    INVOKEVIRTUAL al/aoli/exchain/runtime/analyzers/AffectedVarMethodVisitor.getSourceLocalVariable ()Ljava/util/Set;
    DUP
    IFNULL L100
    CHECKCAST java/util/Collection
    INVOKESTATIC kotlin/collections/CollectionsKt.toIntArray (Ljava/util/Collection;)[I
    DUP
    IFNONNULL L101
   L100
   FRAME FULL [al/aoli/exchain/runtime/analyzers/AffectedVarDriver java/lang/Throwable java/lang/String java/lang/String J J I I al/aoli/exchain/runtime/objects/AffectedVarResult java/lang/String java/lang/String al/aoli/exchain/runtime/analyzers/AffectedVarClassReader I al/aoli/exchain/runtime/analyzers/AffectedVarClassVisitor [Lkotlin/Pair; kotlin/Pair java/util/List java/util/List [Lkotlin/Triple;] [java/lang/Object]
    POP
    ICONST_0
    NEWARRAY T_INT
   L101
    LINENUMBER 101 L101
   FRAME FULL [al/aoli/exchain/runtime/analyzers/AffectedVarDriver java/lang/Throwable java/lang/String java/lang/String J J I I al/aoli/exchain/runtime/objects/AffectedVarResult java/lang/String java/lang/String al/aoli/exchain/runtime/analyzers/AffectedVarClassReader I al/aoli/exchain/runtime/analyzers/AffectedVarClassVisitor [Lkotlin/Pair; kotlin/Pair java/util/List java/util/List [Lkotlin/Triple;] [[I]
    ASTORE 21
   L102
    LINENUMBER 103 L102
    ALOAD 3
    CHECKCAST java/lang/CharSequence
    LDC "clinit"
    CHECKCAST java/lang/CharSequence
    ICONST_0
    ICONST_2
    ACONST_NULL
    INVOKESTATIC kotlin/text/StringsKt.contains$default (Ljava/lang/CharSequence;Ljava/lang/CharSequence;ZILjava/lang/Object;)Z
    IFEQ L103
   L104
    LINENUMBER 104 L104
    ALOAD 15
    INVOKEVIRTUAL al/aoli/exchain/runtime/analyzers/AffectedVarClassVisitor.getMethodVisitor ()Lal/aoli/exchain/runtime/analyzers/AffectedVarMethodVisitor;
    DUP
    IFNULL L105
    INVOKEVIRTUAL al/aoli/exchain/runtime/analyzers/AffectedVarMethodVisitor.getAffectedStaticField ()Ljava/util/Set;
    DUP
    IFNULL L105
    INVOKEINTERFACE java/util/Set.clear ()V (itf)
    GETSTATIC kotlin/Unit.INSTANCE : Lkotlin/Unit;
    GOTO L106
   L105
   FRAME FULL [al/aoli/exchain/runtime/analyzers/AffectedVarDriver java/lang/Throwable java/lang/String java/lang/String J J I I al/aoli/exchain/runtime/objects/AffectedVarResult java/lang/String java/lang/String al/aoli/exchain/runtime/analyzers/AffectedVarClassReader I al/aoli/exchain/runtime/analyzers/AffectedVarClassVisitor [Lkotlin/Pair; kotlin/Pair java/util/List java/util/List [Lkotlin/Triple; [I] [java/lang/Object]
    POP
    ACONST_NULL
   L106
   FRAME FULL [al/aoli/exchain/runtime/analyzers/AffectedVarDriver java/lang/Throwable java/lang/String java/lang/String J J I I al/aoli/exchain/runtime/objects/AffectedVarResult java/lang/String java/lang/String al/aoli/exchain/runtime/analyzers/AffectedVarClassReader I al/aoli/exchain/runtime/analyzers/AffectedVarClassVisitor [Lkotlin/Pair; kotlin/Pair java/util/List java/util/List [Lkotlin/Triple; [I] [kotlin/Unit]
    POP
   L107
    LINENUMBER 105 L107
    ALOAD 15
    INVOKEVIRTUAL al/aoli/exchain/runtime/analyzers/AffectedVarClassVisitor.getMethodVisitor ()Lal/aoli/exchain/runtime/analyzers/AffectedVarMethodVisitor;
    DUP
    IFNULL L108
    INVOKEVIRTUAL al/aoli/exchain/runtime/analyzers/AffectedVarMethodVisitor.getSourceStaticField ()Ljava/util/Set;
    DUP
    IFNULL L108
    INVOKEINTERFACE java/util/Set.clear ()V (itf)
    GETSTATIC kotlin/Unit.INSTANCE : Lkotlin/Unit;
    GOTO L109
   L108
   FRAME FULL [al/aoli/exchain/runtime/analyzers/AffectedVarDriver java/lang/Throwable java/lang/String java/lang/String J J I I al/aoli/exchain/runtime/objects/AffectedVarResult java/lang/String java/lang/String al/aoli/exchain/runtime/analyzers/AffectedVarClassReader I al/aoli/exchain/runtime/analyzers/AffectedVarClassVisitor [Lkotlin/Pair; kotlin/Pair java/util/List java/util/List [Lkotlin/Triple; [I] [java/lang/Object]
    POP
    ACONST_NULL
   L109
   FRAME FULL [al/aoli/exchain/runtime/analyzers/AffectedVarDriver java/lang/Throwable java/lang/String java/lang/String J J I I al/aoli/exchain/runtime/objects/AffectedVarResult java/lang/String java/lang/String al/aoli/exchain/runtime/analyzers/AffectedVarClassReader I al/aoli/exchain/runtime/analyzers/AffectedVarClassVisitor [Lkotlin/Pair; kotlin/Pair java/util/List java/util/List [Lkotlin/Triple; [I] [kotlin/Unit]
    POP
   L103
    LINENUMBER 108 L103
   FRAME FULL [al/aoli/exchain/runtime/analyzers/AffectedVarDriver java/lang/Throwable java/lang/String java/lang/String J J I I al/aoli/exchain/runtime/objects/AffectedVarResult java/lang/String java/lang/String al/aoli/exchain/runtime/analyzers/AffectedVarClassReader I al/aoli/exchain/runtime/analyzers/AffectedVarClassVisitor [Lkotlin/Pair; kotlin/Pair java/util/List java/util/List [Lkotlin/Triple; [I] []
    ALOAD 20
    INVOKESTATIC al/aoli/exchain/runtime/analyzers/AffectedVarDriverKt.access$unzip ([Lkotlin/Triple;)Lkotlin/Triple;
    ASTORE 22
    ALOAD 22
    INVOKEVIRTUAL kotlin/Triple.component1 ()Ljava/lang/Object;
    CHECKCAST java/util/List
    ASTORE 23
   L110
    ALOAD 22
    INVOKEVIRTUAL kotlin/Triple.component2 ()Ljava/lang/Object;
    CHECKCAST java/util/List
    ASTORE 24
   L111
    ALOAD 22
    INVOKEVIRTUAL kotlin/Triple.component3 ()Ljava/lang/Object;
    CHECKCAST java/util/List
    ASTORE 25
   L112
    LINENUMBER 110 L112
    ALOAD 15
    INVOKEVIRTUAL al/aoli/exchain/runtime/analyzers/AffectedVarClassVisitor.getMethodVisitor ()Lal/aoli/exchain/runtime/analyzers/AffectedVarMethodVisitor;
    DUP
    IFNULL L113
    INVOKEVIRTUAL al/aoli/exchain/runtime/analyzers/AffectedVarMethodVisitor.getAffectedStaticField ()Ljava/util/Set;
    DUP
    IFNULL L113
    CHECKCAST java/util/Collection
    ASTORE 30
   L114
    ICONST_0
    ISTORE 31
   L115
    LINENUMBER 338 L115
    ALOAD 30
   L116
    LINENUMBER 339 L116
    ASTORE 32
   L117
    LINENUMBER 341 L117
    ALOAD 32
    ICONST_0
    ANEWARRAY kotlin/Pair
    INVOKEINTERFACE java/util/Collection.toArray ([Ljava/lang/Object;)[Ljava/lang/Object; (itf)
    DUP
    LDC "null cannot be cast to non-null type kotlin.Array<T of kotlin.collections.ArraysKt__ArraysJVMKt.toTypedArray>"
    INVOKESTATIC kotlin/jvm/internal/Intrinsics.checkNotNull (Ljava/lang/Object;Ljava/lang/String;)V
   L118
    LINENUMBER 110 L118
    CHECKCAST [Lkotlin/Pair;
    DUP
    IFNONNULL L119
   L113
   FRAME FULL [al/aoli/exchain/runtime/analyzers/AffectedVarDriver java/lang/Throwable java/lang/String java/lang/String J J I I al/aoli/exchain/runtime/objects/AffectedVarResult java/lang/String java/lang/String al/aoli/exchain/runtime/analyzers/AffectedVarClassReader I al/aoli/exchain/runtime/analyzers/AffectedVarClassVisitor [Lkotlin/Pair; kotlin/Pair java/util/List java/util/List [Lkotlin/Triple; [I kotlin/Triple java/util/List java/util/List java/util/List] [java/lang/Object]
    POP
    ICONST_0
    ISTORE 30
   L120
    LINENUMBER 342 L120
    ICONST_0
    ANEWARRAY kotlin/Pair
    CHECKCAST [Ljava/lang/Object;
   L121
    CHECKCAST [Lkotlin/Pair;
   L119
    LINENUMBER 110 L119
   FRAME FULL [al/aoli/exchain/runtime/analyzers/AffectedVarDriver java/lang/Throwable java/lang/String java/lang/String J J I I al/aoli/exchain/runtime/objects/AffectedVarResult java/lang/String java/lang/String al/aoli/exchain/runtime/analyzers/AffectedVarClassReader I al/aoli/exchain/runtime/analyzers/AffectedVarClassVisitor [Lkotlin/Pair; kotlin/Pair java/util/List java/util/List [Lkotlin/Triple; [I kotlin/Triple java/util/List java/util/List java/util/List] [[Lkotlin/Pair;]
    INVOKESTATIC kotlin/collections/ArraysKt.unzip ([Lkotlin/Pair;)Lkotlin/Pair;
    ASTORE 26
    ALOAD 26
   L122
    LINENUMBER 109 L122
    INVOKEVIRTUAL kotlin/Pair.component1 ()Ljava/lang/Object;
    CHECKCAST java/util/List
    ASTORE 27
   L123
    LINENUMBER 110 L123
    ALOAD 26
   L124
    LINENUMBER 109 L124
    INVOKEVIRTUAL kotlin/Pair.component2 ()Ljava/lang/Object;
    CHECKCAST java/util/List
    ASTORE 28
   L125
    LINENUMBER 111 L125
    ALOAD 15
    INVOKEVIRTUAL al/aoli/exchain/runtime/analyzers/AffectedVarClassVisitor.getMethodVisitor ()Lal/aoli/exchain/runtime/analyzers/AffectedVarMethodVisitor;
    DUP
    IFNULL L126
    INVOKEVIRTUAL al/aoli/exchain/runtime/analyzers/AffectedVarMethodVisitor.getSourceLines ()Ljava/util/Set;
    DUP
    IFNULL L126
    CHECKCAST java/util/Collection
    ASTORE 33
   L127
    ICONST_0
    ISTORE 34
   L128
    LINENUMBER 343 L128
    ALOAD 33
   L129
    LINENUMBER 344 L129
    ASTORE 35
   L130
    LINENUMBER 346 L130
    ALOAD 35
    ICONST_0
    ANEWARRAY kotlin/Pair
    INVOKEINTERFACE java/util/Collection.toArray ([Ljava/lang/Object;)[Ljava/lang/Object; (itf)
    DUP
    LDC "null cannot be cast to non-null type kotlin.Array<T of kotlin.collections.ArraysKt__ArraysJVMKt.toTypedArray>"
    INVOKESTATIC kotlin/jvm/internal/Intrinsics.checkNotNull (Ljava/lang/Object;Ljava/lang/String;)V
   L131
    LINENUMBER 111 L131
    CHECKCAST [Lkotlin/Pair;
    DUP
    IFNONNULL L132
   L126
   FRAME FULL [al/aoli/exchain/runtime/analyzers/AffectedVarDriver java/lang/Throwable java/lang/String java/lang/String J J I I al/aoli/exchain/runtime/objects/AffectedVarResult java/lang/String java/lang/String al/aoli/exchain/runtime/analyzers/AffectedVarClassReader I al/aoli/exchain/runtime/analyzers/AffectedVarClassVisitor [Lkotlin/Pair; kotlin/Pair java/util/List java/util/List [Lkotlin/Triple; [I kotlin/Triple java/util/List java/util/List java/util/List kotlin/Pair java/util/List java/util/List] [java/lang/Object]
    POP
    ICONST_0
    ISTORE 33
   L133
    LINENUMBER 347 L133
    ICONST_0
    ANEWARRAY kotlin/Pair
    CHECKCAST [Ljava/lang/Object;
   L134
    CHECKCAST [Lkotlin/Pair;
   L132
    LINENUMBER 111 L132
   FRAME FULL [al/aoli/exchain/runtime/analyzers/AffectedVarDriver java/lang/Throwable java/lang/String java/lang/String J J I I al/aoli/exchain/runtime/objects/AffectedVarResult java/lang/String java/lang/String al/aoli/exchain/runtime/analyzers/AffectedVarClassReader I al/aoli/exchain/runtime/analyzers/AffectedVarClassVisitor [Lkotlin/Pair; kotlin/Pair java/util/List java/util/List [Lkotlin/Triple; [I kotlin/Triple java/util/List java/util/List java/util/List kotlin/Pair java/util/List java/util/List] [[Lkotlin/Pair;]
    ASTORE 29
   L135
    LINENUMBER 112 L135
    ALOAD 29
    ARRAYLENGTH
    IFNE L136
    ICONST_1
    GOTO L137
   L136
   FRAME FULL [al/aoli/exchain/runtime/analyzers/AffectedVarDriver java/lang/Throwable java/lang/String java/lang/String J J I I al/aoli/exchain/runtime/objects/AffectedVarResult java/lang/String java/lang/String al/aoli/exchain/runtime/analyzers/AffectedVarClassReader I al/aoli/exchain/runtime/analyzers/AffectedVarClassVisitor [Lkotlin/Pair; kotlin/Pair java/util/List java/util/List [Lkotlin/Triple; [I kotlin/Triple java/util/List java/util/List java/util/List kotlin/Pair java/util/List java/util/List [Lkotlin/Pair;] []
    ICONST_0
   L137
   FRAME FULL [al/aoli/exchain/runtime/analyzers/AffectedVarDriver java/lang/Throwable java/lang/String java/lang/String J J I I al/aoli/exchain/runtime/objects/AffectedVarResult java/lang/String java/lang/String al/aoli/exchain/runtime/analyzers/AffectedVarClassReader I al/aoli/exchain/runtime/analyzers/AffectedVarClassVisitor [Lkotlin/Pair; kotlin/Pair java/util/List java/util/List [Lkotlin/Triple; [I kotlin/Triple java/util/List java/util/List java/util/List kotlin/Pair java/util/List java/util/List [Lkotlin/Pair;] [I]
    IFNE L138
    ICONST_1
    GOTO L139
   L138
   FRAME FULL [al/aoli/exchain/runtime/analyzers/AffectedVarDriver java/lang/Throwable java/lang/String java/lang/String J J I I al/aoli/exchain/runtime/objects/AffectedVarResult java/lang/String java/lang/String al/aoli/exchain/runtime/analyzers/AffectedVarClassReader I al/aoli/exchain/runtime/analyzers/AffectedVarClassVisitor [Lkotlin/Pair; kotlin/Pair java/util/List java/util/List [Lkotlin/Triple; [I kotlin/Triple java/util/List java/util/List java/util/List kotlin/Pair java/util/List java/util/List [Lkotlin/Pair;] []
    ICONST_0
   L139
    LINENUMBER 112 L139
   FRAME FULL [al/aoli/exchain/runtime/analyzers/AffectedVarDriver java/lang/Throwable java/lang/String java/lang/String J J I I al/aoli/exchain/runtime/objects/AffectedVarResult java/lang/String java/lang/String al/aoli/exchain/runtime/analyzers/AffectedVarClassReader I al/aoli/exchain/runtime/analyzers/AffectedVarClassVisitor [Lkotlin/Pair; kotlin/Pair java/util/List java/util/List [Lkotlin/Triple; [I kotlin/Triple java/util/List java/util/List java/util/List kotlin/Pair java/util/List java/util/List [Lkotlin/Pair;] [I]
    IFEQ L140
    ILOAD 9
    INVOKESTATIC java/lang/Integer.valueOf (I)Ljava/lang/Integer;
    ASTORE 31
   L141
    LINENUMBER 113 L141
    GETSTATIC al/aoli/exchain/runtime/analyzers/AffectedVarDriver.exceptionSourceIdentified : Ljava/util/Map;
    ALOAD 31
    ICONST_1
    INVOKESTATIC java/lang/Boolean.valueOf (Z)Ljava/lang/Boolean;
    INVOKEINTERFACE java/util/Map.put (Ljava/lang/Object;Ljava/lang/Object;)Ljava/lang/Object; (itf)
    POP
   L140
    LINENUMBER 115 L140
   FRAME FULL [al/aoli/exchain/runtime/analyzers/AffectedVarDriver java/lang/Throwable java/lang/String java/lang/String J J I I al/aoli/exchain/runtime/objects/AffectedVarResult java/lang/String java/lang/String al/aoli/exchain/runtime/analyzers/AffectedVarClassReader I al/aoli/exchain/runtime/analyzers/AffectedVarClassVisitor [Lkotlin/Pair; kotlin/Pair java/util/List java/util/List [Lkotlin/Triple; [I kotlin/Triple java/util/List java/util/List java/util/List kotlin/Pair java/util/List java/util/List [Lkotlin/Pair;] []
    ALOAD 15
    INVOKEVIRTUAL al/aoli/exchain/runtime/analyzers/AffectedVarClassVisitor.getMethodVisitor ()Lal/aoli/exchain/runtime/analyzers/AffectedVarMethodVisitor;
    DUP
    IFNULL L142
    INVOKEVIRTUAL al/aoli/exchain/runtime/analyzers/AffectedVarMethodVisitor.getSourceField ()Ljava/util/Set;
    DUP
    IFNULL L142
    CHECKCAST java/util/Collection
    ASTORE 34
   L143
    ICONST_0
    ISTORE 35
   L144
    LINENUMBER 348 L144
    ALOAD 34
   L145
    LINENUMBER 349 L145
    ASTORE 36
   L146
    LINENUMBER 351 L146
    ALOAD 36
    ICONST_0
    ANEWARRAY java/lang/String
    INVOKEINTERFACE java/util/Collection.toArray ([Ljava/lang/Object;)[Ljava/lang/Object; (itf)
    DUP
    LDC "null cannot be cast to non-null type kotlin.Array<T of kotlin.collections.ArraysKt__ArraysJVMKt.toTypedArray>"
    INVOKESTATIC kotlin/jvm/internal/Intrinsics.checkNotNull (Ljava/lang/Object;Ljava/lang/String;)V
   L147
    LINENUMBER 115 L147
    CHECKCAST [Ljava/lang/String;
    DUP
    IFNONNULL L148
   L142
   FRAME FULL [al/aoli/exchain/runtime/analyzers/AffectedVarDriver java/lang/Throwable java/lang/String java/lang/String J J I I al/aoli/exchain/runtime/objects/AffectedVarResult java/lang/String java/lang/String al/aoli/exchain/runtime/analyzers/AffectedVarClassReader I al/aoli/exchain/runtime/analyzers/AffectedVarClassVisitor [Lkotlin/Pair; kotlin/Pair java/util/List java/util/List [Lkotlin/Triple; [I kotlin/Triple java/util/List java/util/List java/util/List kotlin/Pair java/util/List java/util/List [Lkotlin/Pair;] [java/lang/Object]
    POP
    ICONST_0
    ISTORE 34
   L149
    LINENUMBER 352 L149
    ICONST_0
    ANEWARRAY java/lang/String
    CHECKCAST [Ljava/lang/Object;
   L150
    CHECKCAST [Ljava/lang/String;
   L148
    LINENUMBER 115 L148
   FRAME FULL [al/aoli/exchain/runtime/analyzers/AffectedVarDriver java/lang/Throwable java/lang/String java/lang/String J J I I al/aoli/exchain/runtime/objects/AffectedVarResult java/lang/String java/lang/String al/aoli/exchain/runtime/analyzers/AffectedVarClassReader I al/aoli/exchain/runtime/analyzers/AffectedVarClassVisitor [Lkotlin/Pair; kotlin/Pair java/util/List java/util/List [Lkotlin/Triple; [I kotlin/Triple java/util/List java/util/List java/util/List kotlin/Pair java/util/List java/util/List [Lkotlin/Pair;] [[Ljava/lang/String;]
    ASTORE 30
   L151
    LINENUMBER 116 L151
    ALOAD 15
    INVOKEVIRTUAL al/aoli/exchain/runtime/analyzers/AffectedVarClassVisitor.getMethodVisitor ()Lal/aoli/exchain/runtime/analyzers/AffectedVarMethodVisitor;
    DUP
    IFNULL L152
    INVOKEVIRTUAL al/aoli/exchain/runtime/analyzers/AffectedVarMethodVisitor.getSourceStaticField ()Ljava/util/Set;
    DUP
    IFNULL L152
    CHECKCAST java/util/Collection
    ASTORE 35
   L153
    ICONST_0
    ISTORE 36
   L154
    LINENUMBER 353 L154
    ALOAD 35
   L155
    LINENUMBER 354 L155
    ASTORE 37
   L156
    LINENUMBER 356 L156
    ALOAD 37
    ICONST_0
    ANEWARRAY java/lang/String
    INVOKEINTERFACE java/util/Collection.toArray ([Ljava/lang/Object;)[Ljava/lang/Object; (itf)
    DUP
    LDC "null cannot be cast to non-null type kotlin.Array<T of kotlin.collections.ArraysKt__ArraysJVMKt.toTypedArray>"
    INVOKESTATIC kotlin/jvm/internal/Intrinsics.checkNotNull (Ljava/lang/Object;Ljava/lang/String;)V
   L157
    LINENUMBER 116 L157
    CHECKCAST [Ljava/lang/String;
    DUP
    IFNONNULL L158
   L152
   FRAME FULL [al/aoli/exchain/runtime/analyzers/AffectedVarDriver java/lang/Throwable java/lang/String java/lang/String J J I I al/aoli/exchain/runtime/objects/AffectedVarResult java/lang/String java/lang/String al/aoli/exchain/runtime/analyzers/AffectedVarClassReader I al/aoli/exchain/runtime/analyzers/AffectedVarClassVisitor [Lkotlin/Pair; kotlin/Pair java/util/List java/util/List [Lkotlin/Triple; [I kotlin/Triple java/util/List java/util/List java/util/List kotlin/Pair java/util/List java/util/List [Lkotlin/Pair; [Ljava/lang/String;] [java/lang/Object]
    POP
    ICONST_0
    ISTORE 35
   L159
    LINENUMBER 357 L159
    ICONST_0
    ANEWARRAY java/lang/String
    CHECKCAST [Ljava/lang/Object;
   L160
    CHECKCAST [Ljava/lang/String;
   L158
    LINENUMBER 116 L158
   FRAME FULL [al/aoli/exchain/runtime/analyzers/AffectedVarDriver java/lang/Throwable java/lang/String java/lang/String J J I I al/aoli/exchain/runtime/objects/AffectedVarResult java/lang/String java/lang/String al/aoli/exchain/runtime/analyzers/AffectedVarClassReader I al/aoli/exchain/runtime/analyzers/AffectedVarClassVisitor [Lkotlin/Pair; kotlin/Pair java/util/List java/util/List [Lkotlin/Triple; [I kotlin/Triple java/util/List java/util/List java/util/List kotlin/Pair java/util/List java/util/List [Lkotlin/Pair; [Ljava/lang/String;] [[Ljava/lang/String;]
    ASTORE 31
   L161
    LINENUMBER 118 L161
    NEW al/aoli/exchain/runtime/objects/AffectedVarResult
    DUP
   L162
    LINENUMBER 119 L162
    ILOAD 9
   L163
    LINENUMBER 120 L163
    ALOAD 1
    INVOKEVIRTUAL java/lang/Object.getClass ()Ljava/lang/Class;
    INVOKEVIRTUAL java/lang/Class.getName ()Ljava/lang/String;
    DUP
    LDC "e.javaClass.name"
    INVOKESTATIC kotlin/jvm/internal/Intrinsics.checkNotNullExpressionValue (Ljava/lang/Object;Ljava/lang/String;)V
   L164
    LINENUMBER 121 L164
    ALOAD 2
   L165
    LINENUMBER 122 L165
    ALOAD 3
   L166
    LINENUMBER 123 L166
    LLOAD 4
   L167
    LINENUMBER 124 L167
    LLOAD 6
   L168
    LINENUMBER 125 L168
    ILOAD 8
   L169
    LINENUMBER 126 L169
    GETSTATIC al/aoli/exchain/runtime/analyzers/AffectedVarDriver.type : Lal/aoli/exchain/runtime/objects/Type;
    GETSTATIC al/aoli/exchain/runtime/objects/Type.Hybrid : Lal/aoli/exchain/runtime/objects/Type;
    IF_ACMPNE L170
    ICONST_0
    NEWARRAY T_INT
    GOTO L171
   L170
    LINENUMBER 129 L170
   FRAME FULL [al/aoli/exchain/runtime/analyzers/AffectedVarDriver java/lang/Throwable java/lang/String java/lang/String J J I I al/aoli/exchain/runtime/objects/AffectedVarResult java/lang/String java/lang/String al/aoli/exchain/runtime/analyzers/AffectedVarClassReader I al/aoli/exchain/runtime/analyzers/AffectedVarClassVisitor [Lkotlin/Pair; kotlin/Pair java/util/List java/util/List [Lkotlin/Triple; [I kotlin/Triple java/util/List java/util/List java/util/List kotlin/Pair java/util/List java/util/List [Lkotlin/Pair; [Ljava/lang/String; [Ljava/lang/String;] [L161 L161 I java/lang/String java/lang/String java/lang/String J J I]
    ALOAD 24
    CHECKCAST java/util/Collection
    INVOKESTATIC kotlin/collections/CollectionsKt.toIntArray (Ljava/util/Collection;)[I
   L171
    LINENUMBER 131 L171
   FRAME FULL [al/aoli/exchain/runtime/analyzers/AffectedVarDriver java/lang/Throwable java/lang/String java/lang/String J J I I al/aoli/exchain/runtime/objects/AffectedVarResult java/lang/String java/lang/String al/aoli/exchain/runtime/analyzers/AffectedVarClassReader I al/aoli/exchain/runtime/analyzers/AffectedVarClassVisitor [Lkotlin/Pair; kotlin/Pair java/util/List java/util/List [Lkotlin/Triple; [I kotlin/Triple java/util/List java/util/List java/util/List kotlin/Pair java/util/List java/util/List [Lkotlin/Pair; [Ljava/lang/String; [Ljava/lang/String;] [L161 L161 I java/lang/String java/lang/String java/lang/String J J I [I]
    ALOAD 25
    CHECKCAST java/util/Collection
    ASTORE 33
   L172
    ICONST_0
    ISTORE 34
   L173
    LINENUMBER 358 L173
    ALOAD 33
   L174
    LINENUMBER 359 L174
    ASTORE 35
   L175
    LINENUMBER 361 L175
    ALOAD 35
    ICONST_0
    ANEWARRAY java/lang/String
    INVOKEINTERFACE java/util/Collection.toArray ([Ljava/lang/Object;)[Ljava/lang/Object; (itf)
    DUP
    LDC "null cannot be cast to non-null type kotlin.Array<T of kotlin.collections.ArraysKt__ArraysJVMKt.toTypedArray>"
    INVOKESTATIC kotlin/jvm/internal/Intrinsics.checkNotNull (Ljava/lang/Object;Ljava/lang/String;)V
   L176
    CHECKCAST [Ljava/lang/String;
   L177
    LINENUMBER 132 L177
    ALOAD 23
    CHECKCAST java/util/Collection
    INVOKESTATIC kotlin/collections/CollectionsKt.toIntArray (Ljava/util/Collection;)[I
   L178
    LINENUMBER 133 L178
    ALOAD 19
    CHECKCAST java/util/Collection
    ASTORE 33
   L179
    ICONST_0
    ISTORE 34
   L180
    LINENUMBER 362 L180
    ALOAD 33
   L181
    LINENUMBER 363 L181
    ASTORE 35
   L182
    LINENUMBER 365 L182
    ALOAD 35
    ICONST_0
    ANEWARRAY java/lang/String
    INVOKEINTERFACE java/util/Collection.toArray ([Ljava/lang/Object;)[Ljava/lang/Object; (itf)
    DUP
    LDC "null cannot be cast to non-null type kotlin.Array<T of kotlin.collections.ArraysKt__ArraysJVMKt.toTypedArray>"
    INVOKESTATIC kotlin/jvm/internal/Intrinsics.checkNotNull (Ljava/lang/Object;Ljava/lang/String;)V
   L183
    CHECKCAST [Ljava/lang/String;
   L184
    LINENUMBER 134 L184
    ALOAD 18
    CHECKCAST java/util/Collection
    INVOKESTATIC kotlin/collections/CollectionsKt.toIntArray (Ljava/util/Collection;)[I
   L185
    LINENUMBER 135 L185
    ALOAD 28
    CHECKCAST java/util/Collection
    ASTORE 33
   L186
    ICONST_0
    ISTORE 34
   L187
    LINENUMBER 366 L187
    ALOAD 33
   L188
    LINENUMBER 367 L188
    ASTORE 35
   L189
    LINENUMBER 369 L189
    ALOAD 35
    ICONST_0
    ANEWARRAY java/lang/String
    INVOKEINTERFACE java/util/Collection.toArray ([Ljava/lang/Object;)[Ljava/lang/Object; (itf)
    DUP
    LDC "null cannot be cast to non-null type kotlin.Array<T of kotlin.collections.ArraysKt__ArraysJVMKt.toTypedArray>"
    INVOKESTATIC kotlin/jvm/internal/Intrinsics.checkNotNull (Ljava/lang/Object;Ljava/lang/String;)V
   L190
    CHECKCAST [Ljava/lang/String;
   L191
    LINENUMBER 136 L191
    ALOAD 27
    CHECKCAST java/util/Collection
    INVOKESTATIC kotlin/collections/CollectionsKt.toIntArray (Ljava/util/Collection;)[I
   L192
    LINENUMBER 137 L192
    ALOAD 29
   L193
    LINENUMBER 138 L193
    GETSTATIC al/aoli/exchain/runtime/analyzers/AffectedVarDriver.type : Lal/aoli/exchain/runtime/objects/Type;
    GETSTATIC al/aoli/exchain/runtime/objects/Type.Hybrid : Lal/aoli/exchain/runtime/objects/Type;
    IF_ACMPNE L194
    ICONST_0
    NEWARRAY T_INT
    GOTO L195
   L194
    LINENUMBER 141 L194
   FRAME FULL [al/aoli/exchain/runtime/analyzers/AffectedVarDriver java/lang/Throwable java/lang/String java/lang/String J J I I al/aoli/exchain/runtime/objects/AffectedVarResult java/lang/String java/lang/String al/aoli/exchain/runtime/analyzers/AffectedVarClassReader I al/aoli/exchain/runtime/analyzers/AffectedVarClassVisitor [Lkotlin/Pair; kotlin/Pair java/util/List java/util/List [Lkotlin/Triple; [I kotlin/Triple java/util/List java/util/List java/util/List kotlin/Pair java/util/List java/util/List [Lkotlin/Pair; [Ljava/lang/String; [Ljava/lang/String; T java/util/Collection I java/util/Collection] [L161 L161 I java/lang/String java/lang/String java/lang/String J J I [I [Ljava/lang/String; [I [Ljava/lang/String; [I [Ljava/lang/String; [I [Lkotlin/Pair;]
    ALOAD 21
   L195
    LINENUMBER 143 L195
   FRAME FULL [al/aoli/exchain/runtime/analyzers/AffectedVarDriver java/lang/Throwable java/lang/String java/lang/String J J I I al/aoli/exchain/runtime/objects/AffectedVarResult java/lang/String java/lang/String al/aoli/exchain/runtime/analyzers/AffectedVarClassReader I al/aoli/exchain/runtime/analyzers/AffectedVarClassVisitor [Lkotlin/Pair; kotlin/Pair java/util/List java/util/List [Lkotlin/Triple; [I kotlin/Triple java/util/List java/util/List java/util/List kotlin/Pair java/util/List java/util/List [Lkotlin/Pair; [Ljava/lang/String; [Ljava/lang/String; T java/util/Collection I java/util/Collection] [L161 L161 I java/lang/String java/lang/String java/lang/String J J I [I [Ljava/lang/String; [I [Ljava/lang/String; [I [Ljava/lang/String; [I [Lkotlin/Pair; [I]
    ALOAD 30
   L196
    LINENUMBER 144 L196
    ALOAD 31
   L197
    LINENUMBER 118 L197
    INVOKESPECIAL al/aoli/exchain/runtime/objects/AffectedVarResult.<init> (ILjava/lang/String;Ljava/lang/String;Ljava/lang/String;JJZ[I[Ljava/lang/String;[I[Ljava/lang/String;[I[Ljava/lang/String;[I[Lkotlin/Pair;[I[Ljava/lang/String;[Ljava/lang/String;)V
   L198
    LINENUMBER 117 L198
    ASTORE 32
   L199
    LINENUMBER 146 L199
    GETSTATIC al/aoli/exchain/runtime/analyzers/ExceptionLogger.INSTANCE : Lal/aoli/exchain/runtime/analyzers/ExceptionLogger;
    ALOAD 32
    INVOKEVIRTUAL al/aoli/exchain/runtime/analyzers/ExceptionLogger.logAffectedVarResult (Lal/aoli/exchain/runtime/objects/AffectedVarResult;)V
   L200
    LINENUMBER 147 L200
    ALOAD 0
    INVOKEVIRTUAL al/aoli/exchain/runtime/analyzers/AffectedVarDriver.getStore ()Lal/aoli/exchain/runtime/store/AffectedVarStore;
    ALOAD 2
    ALOAD 3
    LLOAD 4
    LLOAD 6
    ILOAD 8
    ALOAD 32
    INVOKEINTERFACE al/aoli/exchain/runtime/store/AffectedVarStore.putCachedAffectedVarResult (Ljava/lang/String;Ljava/lang/String;JJZLal/aoli/exchain/runtime/objects/AffectedVarResult;)V (itf)
   L201
    LINENUMBER 148 L201
    INVOKESTATIC al/aoli/exchain/runtime/analyzers/AffectedVarDriverKt.access$getLogger$p ()Lal/aoli/exchain/runtime/logger/Logger;
    NEW al/aoli/exchain/runtime/analyzers/AffectedVarDriver$analyzeAffectedVar$2
    DUP
    ALOAD 32
    INVOKESPECIAL al/aoli/exchain/runtime/analyzers/AffectedVarDriver$analyzeAffectedVar$2.<init> (Lal/aoli/exchain/runtime/objects/AffectedVarResult;)V
    CHECKCAST kotlin/jvm/functions/Function0
    INVOKEVIRTUAL al/aoli/exchain/runtime/logger/Logger.info (Lkotlin/jvm/functions/Function0;)V
   L202
    LINENUMBER 149 L202
    ALOAD 32
    ARETURN
   L203
    LOCALVARIABLE result Lal/aoli/exchain/runtime/objects/AffectedVarResult; L20 L9 10
    LOCALVARIABLE path Ljava/lang/String; L34 L35 16
    LOCALVARIABLE e2 Ljava/lang/Throwable; L37 L36 17
    LOCALVARIABLE e1 Ljava/io/IOException; L0 L31 15
    LOCALVARIABLE $i$a$-filter-AffectedVarDriver$analyzeAffectedVar$affectedFields$1 I L70 L72 28
    LOCALVARIABLE it Lkotlin/Pair; L69 L72 27
    LOCALVARIABLE element$iv$iv Ljava/lang/Object; L68 L73 26
    LOCALVARIABLE $i$f$filterTo I L65 L74 24
    LOCALVARIABLE $this$filterTo$iv$iv Ljava/lang/Iterable; L64 L74 22
    LOCALVARIABLE destination$iv$iv Ljava/util/Collection; L64 L74 23
    LOCALVARIABLE $i$f$filter I L63 L76 21
    LOCALVARIABLE $this$filter$iv Ljava/lang/Iterable; L62 L76 20
    LOCALVARIABLE $i$f$toTypedArray I L79 L82 22
    LOCALVARIABLE thisCollection$iv Ljava/util/Collection; L81 L82 23
    LOCALVARIABLE $this$toTypedArray$iv Ljava/util/Collection; L78 L82 21
    LOCALVARIABLE $i$f$emptyArray I L85 L86 21
    LOCALVARIABLE $i$f$toTypedArray I L92 L95 25
    LOCALVARIABLE thisCollection$iv Ljava/util/Collection; L94 L95 26
    LOCALVARIABLE $this$toTypedArray$iv Ljava/util/Collection; L91 L95 24
    LOCALVARIABLE $i$f$emptyArray I L97 L98 24
    LOCALVARIABLE $i$f$toTypedArray I L115 L118 31
    LOCALVARIABLE thisCollection$iv Ljava/util/Collection; L117 L118 32
    LOCALVARIABLE $this$toTypedArray$iv Ljava/util/Collection; L114 L118 30
    LOCALVARIABLE $i$f$emptyArray I L120 L121 30
    LOCALVARIABLE $i$f$toTypedArray I L128 L131 34
    LOCALVARIABLE thisCollection$iv Ljava/util/Collection; L130 L131 35
    LOCALVARIABLE $this$toTypedArray$iv Ljava/util/Collection; L127 L131 33
    LOCALVARIABLE $i$f$emptyArray I L133 L134 33
    LOCALVARIABLE $i$f$toTypedArray I L144 L147 35
    LOCALVARIABLE thisCollection$iv Ljava/util/Collection; L146 L147 36
    LOCALVARIABLE $this$toTypedArray$iv Ljava/util/Collection; L143 L147 34
    LOCALVARIABLE $i$f$emptyArray I L149 L150 34
    LOCALVARIABLE $i$f$toTypedArray I L154 L157 36
    LOCALVARIABLE thisCollection$iv Ljava/util/Collection; L156 L157 37
    LOCALVARIABLE $this$toTypedArray$iv Ljava/util/Collection; L153 L157 35
    LOCALVARIABLE $i$f$emptyArray I L159 L160 35
    LOCALVARIABLE $i$f$toTypedArray I L173 L176 34
    LOCALVARIABLE thisCollection$iv Ljava/util/Collection; L175 L176 35
    LOCALVARIABLE $this$toTypedArray$iv Ljava/util/Collection; L172 L176 33
    LOCALVARIABLE $i$f$toTypedArray I L180 L183 34
    LOCALVARIABLE thisCollection$iv Ljava/util/Collection; L182 L183 35
    LOCALVARIABLE $this$toTypedArray$iv Ljava/util/Collection; L179 L183 33
    LOCALVARIABLE $i$f$toTypedArray I L187 L190 34
    LOCALVARIABLE thisCollection$iv Ljava/util/Collection; L189 L190 35
    LOCALVARIABLE $this$toTypedArray$iv Ljava/util/Collection; L186 L190 33
    LOCALVARIABLE label I L8 L203 9
    LOCALVARIABLE cached Lal/aoli/exchain/runtime/objects/AffectedVarResult; L23 L203 10
    LOCALVARIABLE classPath Ljava/lang/String; L28 L203 11
    LOCALVARIABLE className Ljava/lang/String; L29 L203 12
    LOCALVARIABLE classReader Lal/aoli/exchain/runtime/analyzers/AffectedVarClassReader; L40 L203 13
    LOCALVARIABLE sourceIdentified Z L41 L203 14
    LOCALVARIABLE visitor Lal/aoli/exchain/runtime/analyzers/AffectedVarClassVisitor; L53 L203 15
    LOCALVARIABLE affectedFields [Lkotlin/Pair; L87 L203 16
    LOCALVARIABLE affectedFieldLine Ljava/util/List; L88 L203 18
    LOCALVARIABLE affectedFieldName Ljava/util/List; L89 L203 19
    LOCALVARIABLE affectedVars [Lkotlin/Triple; L99 L203 20
    LOCALVARIABLE sourceLocalVariable [I L102 L203 21
    LOCALVARIABLE affectedLocalLine Ljava/util/List; L110 L203 23
    LOCALVARIABLE affectedLocalIndex Ljava/util/List; L111 L203 24
    LOCALVARIABLE affectedLocalName Ljava/util/List; L112 L203 25
    LOCALVARIABLE affectedStaticFieldLine Ljava/util/List; L123 L203 27
    LOCALVARIABLE affectedStaticFieldName Ljava/util/List; L125 L203 28
    LOCALVARIABLE sourceLines [Lkotlin/Pair; L135 L203 29
    LOCALVARIABLE sourceField [Ljava/lang/String; L151 L203 30
    LOCALVARIABLE sourceStaticField [Ljava/lang/String; L161 L203 31
    LOCALVARIABLE result Lal/aoli/exchain/runtime/objects/AffectedVarResult; L199 L203 32
    LOCALVARIABLE this Lal/aoli/exchain/runtime/analyzers/AffectedVarDriver; L6 L203 0
    LOCALVARIABLE e Ljava/lang/Throwable; L6 L203 1
    LOCALVARIABLE clazz Ljava/lang/String; L6 L203 2
    LOCALVARIABLE method Ljava/lang/String; L6 L203 3
    LOCALVARIABLE throwIndex J L6 L203 4
    LOCALVARIABLE catchIndex J L6 L203 6
    LOCALVARIABLE isThrowInsn Z L6 L203 8
    MAXSTACK = 24
    MAXLOCALS = 38

  // access flags 0x11
  public final analyzeSourceFields(Ljava/lang/Object;Lal/aoli/exchain/runtime/objects/AffectedVarResult;Ljava/lang/Object;Ljava/lang/String;)Z
    TRYCATCHBLOCK L0 L1 L1 java/lang/Exception
    TRYCATCHBLOCK L2 L3 L3 java/lang/Exception
    TRYCATCHBLOCK L4 L5 L5 java/lang/Exception
   L6
    ALOAD 2
    LDC "affectedVarResult"
    INVOKESTATIC kotlin/jvm/internal/Intrinsics.checkNotNullParameter (Ljava/lang/Object;Ljava/lang/String;)V
    ALOAD 3
    LDC "exception"
    INVOKESTATIC kotlin/jvm/internal/Intrinsics.checkNotNullParameter (Ljava/lang/Object;Ljava/lang/String;)V
    ALOAD 4
    LDC "location"
    INVOKESTATIC kotlin/jvm/internal/Intrinsics.checkNotNullParameter (Ljava/lang/Object;Ljava/lang/String;)V
   L7
    LINENUMBER 234 L7
    ALOAD 3
    INVOKESTATIC java/lang/System.identityHashCode (Ljava/lang/Object;)I
    ISTORE 5
   L8
    LINENUMBER 235 L8
    ICONST_0
    ISTORE 6
   L9
    LINENUMBER 236 L9
    ALOAD 1
    IFNULL L10
    ALOAD 1
    INSTANCEOF edu/columbia/cs/psl/phosphor/struct/TaintedWithObjTag
    IFEQ L10
   L0
    LINENUMBER 237 L0
    NOP
   L11
    LINENUMBER 238 L11
    ALOAD 1
    CHECKCAST edu/columbia/cs/psl/phosphor/struct/TaintedWithObjTag
    INVOKEINTERFACE edu/columbia/cs/psl/phosphor/struct/TaintedWithObjTag.getPHOSPHOR_TAG ()Ljava/lang/Object; (itf)
    CHECKCAST edu/columbia/cs/psl/phosphor/runtime/Taint
    ASTORE 7
   L12
    LINENUMBER 239 L12
    ALOAD 7
    IFNULL L10
   L13
    LINENUMBER 240 L13
    ALOAD 7
    INVOKEVIRTUAL edu/columbia/cs/psl/phosphor/runtime/Taint.getLabels ()[Ljava/lang/Object;
    DUP
    LDC "taint.labels"
    INVOKESTATIC kotlin/jvm/internal/Intrinsics.checkNotNullExpressionValue (Ljava/lang/Object;Ljava/lang/String;)V
    ASTORE 8
    ICONST_0
    ISTORE 9
    ALOAD 8
    ARRAYLENGTH
    ISTORE 10
   L14
   FRAME FULL [al/aoli/exchain/runtime/analyzers/AffectedVarDriver java/lang/Object al/aoli/exchain/runtime/objects/AffectedVarResult java/lang/Object java/lang/String I I edu/columbia/cs/psl/phosphor/runtime/Taint [Ljava/lang/Object; I I] []
    ILOAD 9
    ILOAD 10
    IF_ICMPGE L10
    ALOAD 8
    ILOAD 9
    AALOAD
    ASTORE 11
   L15
    LINENUMBER 241 L15
    ALOAD 11
    INSTANCEOF java/lang/Integer
    IFEQ L16
    GETSTATIC al/aoli/exchain/runtime/analyzers/AffectedVarDriver.exceptionStore : Ljava/util/Map;
    ALOAD 11
    INVOKEINTERFACE java/util/Map.containsKey (Ljava/lang/Object;)Z (itf)
   L17
    LINENUMBER 241 L17
    IFEQ L16
    ALOAD 11
    ILOAD 5
    INVOKESTATIC java/lang/Integer.valueOf (I)Ljava/lang/Integer;
    INVOKESTATIC kotlin/jvm/internal/Intrinsics.areEqual (Ljava/lang/Object;Ljava/lang/Object;)Z
    IFNE L16
   L18
    LINENUMBER 242 L18
    GETSTATIC al/aoli/exchain/runtime/analyzers/ExceptionLogger.INSTANCE : Lal/aoli/exchain/runtime/analyzers/ExceptionLogger;
    ALOAD 11
    CHECKCAST java/lang/Number
    INVOKEVIRTUAL java/lang/Number.intValue ()I
    ILOAD 5
    INVOKEVIRTUAL al/aoli/exchain/runtime/analyzers/ExceptionLogger.logDependency (II)V
   L19
    LINENUMBER 243 L19
    ICONST_1
    ISTORE 6
   L16
    LINENUMBER 240 L16
   FRAME FULL [al/aoli/exchain/runtime/analyzers/AffectedVarDriver java/lang/Object al/aoli/exchain/runtime/objects/AffectedVarResult java/lang/Object java/lang/String I I edu/columbia/cs/psl/phosphor/runtime/Taint [Ljava/lang/Object; I I java/lang/Object] []
    IINC 9 1
    GOTO L14
   L1
    LINENUMBER 247 L1
   FRAME FULL [al/aoli/exchain/runtime/analyzers/AffectedVarDriver java/lang/Object al/aoli/exchain/runtime/objects/AffectedVarResult java/lang/Object java/lang/String I I] [java/lang/Exception]
    ASTORE 7
   L20
    LINENUMBER 248 L20
    INVOKESTATIC al/aoli/exchain/runtime/analyzers/AffectedVarDriverKt.access$getLogger$p ()Lal/aoli/exchain/runtime/logger/Logger;
    NEW al/aoli/exchain/runtime/analyzers/AffectedVarDriver$analyzeSourceFields$1
    DUP
    ALOAD 1
    ALOAD 7
    INVOKESPECIAL al/aoli/exchain/runtime/analyzers/AffectedVarDriver$analyzeSourceFields$1.<init> (Ljava/lang/Object;Ljava/lang/Exception;)V
    CHECKCAST kotlin/jvm/functions/Function0
    INVOKEVIRTUAL al/aoli/exchain/runtime/logger/Logger.warn (Lkotlin/jvm/functions/Function0;)V
   L10
    LINENUMBER 252 L10
   FRAME FULL [al/aoli/exchain/runtime/analyzers/AffectedVarDriver java/lang/Object al/aoli/exchain/runtime/objects/AffectedVarResult java/lang/Object java/lang/String I I] []
    ALOAD 1
    IFNULL L21
   L22
    LINENUMBER 253 L22
    ALOAD 2
    INVOKEVIRTUAL al/aoli/exchain/runtime/objects/AffectedVarResult.getSourceField ()[Ljava/lang/String;
    ASTORE 7
    ICONST_0
    ISTORE 8
    ALOAD 7
    ARRAYLENGTH
    ISTORE 9
   L23
   FRAME FULL [al/aoli/exchain/runtime/analyzers/AffectedVarDriver java/lang/Object al/aoli/exchain/runtime/objects/AffectedVarResult java/lang/Object java/lang/String I I [Ljava/lang/String; I I] []
    ILOAD 8
    ILOAD 9
    IF_ICMPGE L21
    ALOAD 7
    ILOAD 8
    AALOAD
    ASTORE 10
   L2
    LINENUMBER 254 L2
    NOP
   L24
    LINENUMBER 255 L24
    ALOAD 1
    INVOKEVIRTUAL java/lang/Object.getClass ()Ljava/lang/Class;
    NEW java/lang/StringBuilder
    DUP
    INVOKESPECIAL java/lang/StringBuilder.<init> ()V
    ALOAD 10
    INVOKEVIRTUAL java/lang/StringBuilder.append (Ljava/lang/String;)Ljava/lang/StringBuilder;
    LDC "PHOSPHOR_TAG"
    INVOKEVIRTUAL java/lang/StringBuilder.append (Ljava/lang/String;)Ljava/lang/StringBuilder;
    INVOKEVIRTUAL java/lang/StringBuilder.toString ()Ljava/lang/String;
    INVOKEVIRTUAL java/lang/Class.getDeclaredField (Ljava/lang/String;)Ljava/lang/reflect/Field;
    ASTORE 11
   L25
    LINENUMBER 256 L25
    ALOAD 11
    ICONST_1
    INVOKEVIRTUAL java/lang/reflect/Field.setAccessible (Z)V
   L26
    LINENUMBER 257 L26
    ALOAD 11
    ALOAD 1
    INVOKEVIRTUAL java/lang/reflect/Field.get (Ljava/lang/Object;)Ljava/lang/Object;
    CHECKCAST edu/columbia/cs/psl/phosphor/runtime/Taint
    DUP
    IFNONNULL L27
    POP
    GOTO L28
   L27
   FRAME FULL [al/aoli/exchain/runtime/analyzers/AffectedVarDriver java/lang/Object al/aoli/exchain/runtime/objects/AffectedVarResult java/lang/Object java/lang/String I I [Ljava/lang/String; I I java/lang/String java/lang/reflect/Field] [edu/columbia/cs/psl/phosphor/runtime/Taint]
    ASTORE 12
   L29
    LINENUMBER 258 L29
    ALOAD 12
    INVOKEVIRTUAL edu/columbia/cs/psl/phosphor/runtime/Taint.getLabels ()[Ljava/lang/Object;
    DUP
    LDC "taint.labels"
    INVOKESTATIC kotlin/jvm/internal/Intrinsics.checkNotNullExpressionValue (Ljava/lang/Object;Ljava/lang/String;)V
    ASTORE 13
    ICONST_0
    ISTORE 14
    ALOAD 13
    ARRAYLENGTH
    ISTORE 15
   L30
   FRAME FULL [al/aoli/exchain/runtime/analyzers/AffectedVarDriver java/lang/Object al/aoli/exchain/runtime/objects/AffectedVarResult java/lang/Object java/lang/String I I [Ljava/lang/String; I I java/lang/String java/lang/reflect/Field edu/columbia/cs/psl/phosphor/runtime/Taint [Ljava/lang/Object; I I] []
    ILOAD 14
    ILOAD 15
    IF_ICMPGE L28
    ALOAD 13
    ILOAD 14
    AALOAD
    ASTORE 16
   L31
    LINENUMBER 259 L31
    ALOAD 16
    INSTANCEOF java/lang/Integer
    IFEQ L32
    GETSTATIC al/aoli/exchain/runtime/analyzers/AffectedVarDriver.exceptionStore : Ljava/util/Map;
    ALOAD 16
    INVOKEINTERFACE java/util/Map.containsKey (Ljava/lang/Object;)Z (itf)
   L33
    LINENUMBER 259 L33
    IFEQ L32
    ALOAD 16
    ILOAD 5
    INVOKESTATIC java/lang/Integer.valueOf (I)Ljava/lang/Integer;
    INVOKESTATIC kotlin/jvm/internal/Intrinsics.areEqual (Ljava/lang/Object;Ljava/lang/Object;)Z
    IFNE L32
   L34
    LINENUMBER 260 L34
    GETSTATIC al/aoli/exchain/runtime/analyzers/ExceptionLogger.INSTANCE : Lal/aoli/exchain/runtime/analyzers/ExceptionLogger;
    ALOAD 16
    CHECKCAST java/lang/Number
    INVOKEVIRTUAL java/lang/Number.intValue ()I
    ILOAD 5
    INVOKEVIRTUAL al/aoli/exchain/runtime/analyzers/ExceptionLogger.logDependency (II)V
   L35
    LINENUMBER 261 L35
    ICONST_1
    ISTORE 6
   L32
    LINENUMBER 258 L32
   FRAME FULL [al/aoli/exchain/runtime/analyzers/AffectedVarDriver java/lang/Object al/aoli/exchain/runtime/objects/AffectedVarResult java/lang/Object java/lang/String I I [Ljava/lang/String; I I java/lang/String java/lang/reflect/Field edu/columbia/cs/psl/phosphor/runtime/Taint [Ljava/lang/Object; I I java/lang/Object] []
    IINC 14 1
    GOTO L30
   L3
    LINENUMBER 264 L3
   FRAME FULL [al/aoli/exchain/runtime/analyzers/AffectedVarDriver java/lang/Object al/aoli/exchain/runtime/objects/AffectedVarResult java/lang/Object java/lang/String I I [Ljava/lang/String; I I java/lang/String] [java/lang/Exception]
    ASTORE 11
   L36
    LINENUMBER 265 L36
    INVOKESTATIC al/aoli/exchain/runtime/analyzers/AffectedVarDriverKt.access$getLogger$p ()Lal/aoli/exchain/runtime/logger/Logger;
    NEW al/aoli/exchain/runtime/analyzers/AffectedVarDriver$analyzeSourceFields$2
    DUP
    ALOAD 10
    ALOAD 1
    ALOAD 11
    INVOKESPECIAL al/aoli/exchain/runtime/analyzers/AffectedVarDriver$analyzeSourceFields$2.<init> (Ljava/lang/String;Ljava/lang/Object;Ljava/lang/Exception;)V
    CHECKCAST kotlin/jvm/functions/Function0
    INVOKEVIRTUAL al/aoli/exchain/runtime/logger/Logger.warn (Lkotlin/jvm/functions/Function0;)V
   L28
    LINENUMBER 253 L28
   FRAME FULL [al/aoli/exchain/runtime/analyzers/AffectedVarDriver java/lang/Object al/aoli/exchain/runtime/objects/AffectedVarResult java/lang/Object java/lang/String I I [Ljava/lang/String; I I java/lang/String java/lang/Object] []
    IINC 8 1
    GOTO L23
   L21
    LINENUMBER 273 L21
   FRAME FULL [al/aoli/exchain/runtime/analyzers/AffectedVarDriver java/lang/Object al/aoli/exchain/runtime/objects/AffectedVarResult java/lang/Object java/lang/String I I] []
    ALOAD 2
    INVOKEVIRTUAL al/aoli/exchain/runtime/objects/AffectedVarResult.getSourceStaticField ()[Ljava/lang/String;
    ASTORE 7
    ICONST_0
    ISTORE 8
    ALOAD 7
    ARRAYLENGTH
    ISTORE 9
   L37
   FRAME FULL [al/aoli/exchain/runtime/analyzers/AffectedVarDriver java/lang/Object al/aoli/exchain/runtime/objects/AffectedVarResult java/lang/Object java/lang/String I I [Ljava/lang/String; I I] []
    ILOAD 8
    ILOAD 9
    IF_ICMPGE L38
    ALOAD 7
    ILOAD 8
    AALOAD
    ASTORE 10
   L4
    LINENUMBER 274 L4
    NOP
   L39
    LINENUMBER 275 L39
    ALOAD 10
    CHECKCAST java/lang/CharSequence
    ICONST_1
    ANEWARRAY java/lang/String
    ASTORE 12
    ALOAD 12
    ICONST_0
    LDC "#"
    AASTORE
    ALOAD 12
    ICONST_0
    ICONST_0
    BIPUSH 6
    ACONST_NULL
    INVOKESTATIC kotlin/text/StringsKt.split$default (Ljava/lang/CharSequence;[Ljava/lang/String;ZIILjava/lang/Object;)Ljava/util/List;
    ASTORE 11
    ALOAD 11
    ICONST_0
    INVOKEINTERFACE java/util/List.get (I)Ljava/lang/Object; (itf)
   L40
    LINENUMBER 275 L40
    CHECKCAST java/lang/String
    ASTORE 12
   L41
    ALOAD 11
    ICONST_1
    INVOKEINTERFACE java/util/List.get (I)Ljava/lang/Object; (itf)
   L42
    LINENUMBER 275 L42
    CHECKCAST java/lang/String
    ASTORE 13
   L43
    LINENUMBER 276 L43
    ALOAD 12
    LDC "/"
    LDC "."
    ICONST_0
    ICONST_4
    ACONST_NULL
    INVOKESTATIC kotlin/text/StringsKt.replace$default (Ljava/lang/String;Ljava/lang/String;Ljava/lang/String;ZILjava/lang/Object;)Ljava/lang/String;
    INVOKESTATIC java/lang/Class.forName (Ljava/lang/String;)Ljava/lang/Class;
    ASTORE 14
   L44
    LINENUMBER 277 L44
    ALOAD 14
    NEW java/lang/StringBuilder
    DUP
    INVOKESPECIAL java/lang/StringBuilder.<init> ()V
    ALOAD 13
    INVOKEVIRTUAL java/lang/StringBuilder.append (Ljava/lang/String;)Ljava/lang/StringBuilder;
    LDC "PHOSPHOR_TAG"
    INVOKEVIRTUAL java/lang/StringBuilder.append (Ljava/lang/String;)Ljava/lang/StringBuilder;
    INVOKEVIRTUAL java/lang/StringBuilder.toString ()Ljava/lang/String;
    INVOKEVIRTUAL java/lang/Class.getField (Ljava/lang/String;)Ljava/lang/reflect/Field;
    ASTORE 15
   L45
    LINENUMBER 278 L45
    ALOAD 15
    ALOAD 1
    INVOKEVIRTUAL java/lang/reflect/Field.get (Ljava/lang/Object;)Ljava/lang/Object;
    CHECKCAST edu/columbia/cs/psl/phosphor/runtime/Taint
    DUP
    IFNONNULL L46
    POP
    GOTO L47
   L46
   FRAME FULL [al/aoli/exchain/runtime/analyzers/AffectedVarDriver java/lang/Object al/aoli/exchain/runtime/objects/AffectedVarResult java/lang/Object java/lang/String I I [Ljava/lang/String; I I java/lang/String java/util/List java/lang/String java/lang/String java/lang/Class java/lang/reflect/Field] [edu/columbia/cs/psl/phosphor/runtime/Taint]
    ASTORE 16
   L48
    LINENUMBER 279 L48
    ALOAD 16
    INVOKEVIRTUAL edu/columbia/cs/psl/phosphor/runtime/Taint.getLabels ()[Ljava/lang/Object;
    DUP
    LDC "taint.labels"
    INVOKESTATIC kotlin/jvm/internal/Intrinsics.checkNotNullExpressionValue (Ljava/lang/Object;Ljava/lang/String;)V
    ASTORE 17
    ICONST_0
    ISTORE 18
    ALOAD 17
    ARRAYLENGTH
    ISTORE 19
   L49
   FRAME FULL [al/aoli/exchain/runtime/analyzers/AffectedVarDriver java/lang/Object al/aoli/exchain/runtime/objects/AffectedVarResult java/lang/Object java/lang/String I I [Ljava/lang/String; I I java/lang/String java/util/List java/lang/String java/lang/String java/lang/Class java/lang/reflect/Field edu/columbia/cs/psl/phosphor/runtime/Taint [Ljava/lang/Object; I I] []
    ILOAD 18
    ILOAD 19
    IF_ICMPGE L47
    ALOAD 17
    ILOAD 18
    AALOAD
    ASTORE 20
   L50
    LINENUMBER 280 L50
    ALOAD 20
    INSTANCEOF java/lang/Integer
    IFEQ L51
    GETSTATIC al/aoli/exchain/runtime/analyzers/AffectedVarDriver.exceptionStore : Ljava/util/Map;
    ALOAD 20
    INVOKEINTERFACE java/util/Map.containsKey (Ljava/lang/Object;)Z (itf)
   L52
    LINENUMBER 280 L52
    IFEQ L51
    ALOAD 20
    ILOAD 5
    INVOKESTATIC java/lang/Integer.valueOf (I)Ljava/lang/Integer;
    INVOKESTATIC kotlin/jvm/internal/Intrinsics.areEqual (Ljava/lang/Object;Ljava/lang/Object;)Z
    IFNE L51
   L53
    LINENUMBER 281 L53
    GETSTATIC al/aoli/exchain/runtime/analyzers/ExceptionLogger.INSTANCE : Lal/aoli/exchain/runtime/analyzers/ExceptionLogger;
    ALOAD 20
    CHECKCAST java/lang/Number
    INVOKEVIRTUAL java/lang/Number.intValue ()I
    ILOAD 5
    INVOKEVIRTUAL al/aoli/exchain/runtime/analyzers/ExceptionLogger.logDependency (II)V
   L54
    LINENUMBER 282 L54
    ICONST_1
    ISTORE 6
   L51
    LINENUMBER 279 L51
   FRAME FULL [al/aoli/exchain/runtime/analyzers/AffectedVarDriver java/lang/Object al/aoli/exchain/runtime/objects/AffectedVarResult java/lang/Object java/lang/String I I [Ljava/lang/String; I I java/lang/String java/util/List java/lang/String java/lang/String java/lang/Class java/lang/reflect/Field edu/columbia/cs/psl/phosphor/runtime/Taint [Ljava/lang/Object; I I java/lang/Object] []
    IINC 18 1
    GOTO L49
   L5
    LINENUMBER 285 L5
   FRAME FULL [al/aoli/exchain/runtime/analyzers/AffectedVarDriver java/lang/Object al/aoli/exchain/runtime/objects/AffectedVarResult java/lang/Object java/lang/String I I [Ljava/lang/String; I I java/lang/String] [java/lang/Exception]
    ASTORE 11
   L55
    LINENUMBER 286 L55
    INVOKESTATIC al/aoli/exchain/runtime/analyzers/AffectedVarDriverKt.access$getLogger$p ()Lal/aoli/exchain/runtime/logger/Logger;
    NEW al/aoli/exchain/runtime/analyzers/AffectedVarDriver$analyzeSourceFields$3
    DUP
    ALOAD 10
    ALOAD 11
    INVOKESPECIAL al/aoli/exchain/runtime/analyzers/AffectedVarDriver$analyzeSourceFields$3.<init> (Ljava/lang/String;Ljava/lang/Exception;)V
    CHECKCAST kotlin/jvm/functions/Function0
    INVOKEVIRTUAL al/aoli/exchain/runtime/logger/Logger.warn (Lkotlin/jvm/functions/Function0;)V
   L47
    LINENUMBER 273 L47
   FRAME FULL [al/aoli/exchain/runtime/analyzers/AffectedVarDriver java/lang/Object al/aoli/exchain/runtime/objects/AffectedVarResult java/lang/Object java/lang/String I I [Ljava/lang/String; I I java/lang/String java/lang/Object] []
    IINC 8 1
    GOTO L37
   L38
    LINENUMBER 289 L38
   FRAME FULL [al/aoli/exchain/runtime/analyzers/AffectedVarDriver java/lang/Object al/aoli/exchain/runtime/objects/AffectedVarResult java/lang/Object java/lang/String I I [Ljava/lang/String; I I] []
    ILOAD 6
    IRETURN
   L56
    LOCALVARIABLE label Ljava/lang/Object; L15 L1 11
    LOCALVARIABLE taint Ledu/columbia/cs/psl/phosphor/runtime/Taint; L12 L1 7
    LOCALVARIABLE e Ljava/lang/Exception; L20 L10 7
    LOCALVARIABLE label Ljava/lang/Object; L31 L3 16
    LOCALVARIABLE field Ljava/lang/reflect/Field; L25 L3 11
    LOCALVARIABLE taint Ledu/columbia/cs/psl/phosphor/runtime/Taint; L29 L3 12
    LOCALVARIABLE e Ljava/lang/Exception; L36 L28 11
    LOCALVARIABLE name Ljava/lang/String; L2 L21 10
    LOCALVARIABLE label Ljava/lang/Object; L50 L5 20
    LOCALVARIABLE clazzName Ljava/lang/String; L41 L5 12
    LOCALVARIABLE fieldName Ljava/lang/String; L43 L5 13
    LOCALVARIABLE clazz Ljava/lang/Class; L44 L5 14
    LOCALVARIABLE field Ljava/lang/reflect/Field; L45 L5 15
    LOCALVARIABLE taint Ledu/columbia/cs/psl/phosphor/runtime/Taint; L48 L5 16
    LOCALVARIABLE e Ljava/lang/Exception; L55 L47 11
    LOCALVARIABLE name Ljava/lang/String; L4 L38 10
    LOCALVARIABLE origin I L8 L56 5
    LOCALVARIABLE causeIdentified Z L9 L56 6
    LOCALVARIABLE this Lal/aoli/exchain/runtime/analyzers/AffectedVarDriver; L6 L56 0
    LOCALVARIABLE obj Ljava/lang/Object; L6 L56 1
    LOCALVARIABLE affectedVarResult Lal/aoli/exchain/runtime/objects/AffectedVarResult; L6 L56 2
    LOCALVARIABLE exception Ljava/lang/Object; L6 L56 3
    LOCALVARIABLE location Ljava/lang/String; L6 L56 4
    MAXSTACK = 6
    MAXLOCALS = 21

  // access flags 0x11
  public final analyzeSourceVars(Ljava/lang/Object;Ljava/lang/Object;Ljava/lang/String;)Z
   L0
    ALOAD 1
    LDC "obj"
    INVOKESTATIC kotlin/jvm/internal/Intrinsics.checkNotNullParameter (Ljava/lang/Object;Ljava/lang/String;)V
    ALOAD 2
    LDC "exception"
    INVOKESTATIC kotlin/jvm/internal/Intrinsics.checkNotNullParameter (Ljava/lang/Object;Ljava/lang/String;)V
    ALOAD 3
    LDC "location"
    INVOKESTATIC kotlin/jvm/internal/Intrinsics.checkNotNullParameter (Ljava/lang/Object;Ljava/lang/String;)V
   L1
    LINENUMBER 293 L1
    INVOKESTATIC al/aoli/exchain/runtime/analyzers/AffectedVarDriverKt.access$getLogger$p ()Lal/aoli/exchain/runtime/logger/Logger;
    NEW al/aoli/exchain/runtime/analyzers/AffectedVarDriver$analyzeSourceVars$1
    DUP
    ALOAD 1
    ALOAD 3
    INVOKESPECIAL al/aoli/exchain/runtime/analyzers/AffectedVarDriver$analyzeSourceVars$1.<init> (Ljava/lang/Object;Ljava/lang/String;)V
    CHECKCAST kotlin/jvm/functions/Function0
    INVOKEVIRTUAL al/aoli/exchain/runtime/logger/Logger.info (Lkotlin/jvm/functions/Function0;)V
   L2
    LINENUMBER 294 L2
    ALOAD 2
    INVOKESTATIC java/lang/System.identityHashCode (Ljava/lang/Object;)I
    ISTORE 4
   L3
    LINENUMBER 296 L3
    ALOAD 1
    ASTORE 7
   L4
    LINENUMBER 297 L4
    ALOAD 7
    INSTANCEOF edu/columbia/cs/psl/phosphor/runtime/Taint
    IFEQ L5
    ALOAD 1
    CHECKCAST edu/columbia/cs/psl/phosphor/runtime/Taint
    GOTO L6
   L5
    LINENUMBER 298 L5
   FRAME FULL [al/aoli/exchain/runtime/analyzers/AffectedVarDriver java/lang/Object java/lang/Object java/lang/String I T T java/lang/Object] []
    ALOAD 7
    INSTANCEOF edu/columbia/cs/psl/phosphor/struct/TaintedWithObjTag
    IFEQ L7
    ALOAD 1
    CHECKCAST edu/columbia/cs/psl/phosphor/struct/TaintedWithObjTag
    INVOKEINTERFACE edu/columbia/cs/psl/phosphor/struct/TaintedWithObjTag.getPHOSPHOR_TAG ()Ljava/lang/Object; (itf)
    CHECKCAST edu/columbia/cs/psl/phosphor/runtime/Taint
    GOTO L6
   L7
    LINENUMBER 299 L7
   FRAME FULL [al/aoli/exchain/runtime/analyzers/AffectedVarDriver java/lang/Object java/lang/Object java/lang/String I T T java/lang/Object] []
    ACONST_NULL
   L6
    LINENUMBER 296 L6
   FRAME FULL [al/aoli/exchain/runtime/analyzers/AffectedVarDriver java/lang/Object java/lang/Object java/lang/String I T T java/lang/Object] [edu/columbia/cs/psl/phosphor/runtime/Taint]
    DUP
    IFNONNULL L8
    POP
   L9
    LINENUMBER 301 L9
    ICONST_0
    IRETURN
   L8
    LINENUMBER 296 L8
    LINENUMBER 295 L8
   FRAME FULL [al/aoli/exchain/runtime/analyzers/AffectedVarDriver java/lang/Object java/lang/Object java/lang/String I T T java/lang/Object] [edu/columbia/cs/psl/phosphor/runtime/Taint]
    ASTORE 5
   L10
    LINENUMBER 302 L10
    ICONST_0
    ISTORE 6
   L11
    LINENUMBER 303 L11
    ALOAD 5
    INVOKEVIRTUAL edu/columbia/cs/psl/phosphor/runtime/Taint.getLabels ()[Ljava/lang/Object;
    DUP
    LDC "taint.labels"
    INVOKESTATIC kotlin/jvm/internal/Intrinsics.checkNotNullExpressionValue (Ljava/lang/Object;Ljava/lang/String;)V
    ASTORE 7
    ICONST_0
    ISTORE 8
    ALOAD 7
    ARRAYLENGTH
    ISTORE 9
   L12
   FRAME FULL [al/aoli/exchain/runtime/analyzers/AffectedVarDriver java/lang/Object java/lang/Object java/lang/String I edu/columbia/cs/psl/phosphor/runtime/Taint I [Ljava/lang/Object; I I] []
    ILOAD 8
    ILOAD 9
    IF_ICMPGE L13
    ALOAD 7
    ILOAD 8
    AALOAD
    ASTORE 10
   L14
    LINENUMBER 304 L14
    ALOAD 10
    INSTANCEOF java/lang/Integer
    IFEQ L15
    GETSTATIC al/aoli/exchain/runtime/analyzers/AffectedVarDriver.exceptionStore : Ljava/util/Map;
    ALOAD 10
    INVOKEINTERFACE java/util/Map.containsKey (Ljava/lang/Object;)Z (itf)
   L16
    LINENUMBER 304 L16
    IFEQ L15
    ALOAD 10
    ILOAD 4
    INVOKESTATIC java/lang/Integer.valueOf (I)Ljava/lang/Integer;
    INVOKESTATIC kotlin/jvm/internal/Intrinsics.areEqual (Ljava/lang/Object;Ljava/lang/Object;)Z
    IFNE L15
   L17
    LINENUMBER 305 L17
    GETSTATIC al/aoli/exchain/runtime/analyzers/ExceptionLogger.INSTANCE : Lal/aoli/exchain/runtime/analyzers/ExceptionLogger;
    ALOAD 10
    CHECKCAST java/lang/Number
    INVOKEVIRTUAL java/lang/Number.intValue ()I
    ILOAD 4
    INVOKEVIRTUAL al/aoli/exchain/runtime/analyzers/ExceptionLogger.logDependency (II)V
   L18
    LINENUMBER 306 L18
    ICONST_1
    ISTORE 6
   L15
    LINENUMBER 303 L15
   FRAME FULL [al/aoli/exchain/runtime/analyzers/AffectedVarDriver java/lang/Object java/lang/Object java/lang/String I edu/columbia/cs/psl/phosphor/runtime/Taint I [Ljava/lang/Object; I I java/lang/Object] []
    IINC 8 1
    GOTO L12
   L13
    LINENUMBER 309 L13
   FRAME FULL [al/aoli/exchain/runtime/analyzers/AffectedVarDriver java/lang/Object java/lang/Object java/lang/String I edu/columbia/cs/psl/phosphor/runtime/Taint I [Ljava/lang/Object; I I] []
    ILOAD 6
    IRETURN
   L19
    LOCALVARIABLE label Ljava/lang/Object; L14 L13 10
    LOCALVARIABLE origin I L3 L19 4
    LOCALVARIABLE taint Ledu/columbia/cs/psl/phosphor/runtime/Taint; L10 L19 5
    LOCALVARIABLE causeIdentified Z L11 L19 6
    LOCALVARIABLE this Lal/aoli/exchain/runtime/analyzers/AffectedVarDriver; L0 L19 0
    LOCALVARIABLE obj Ljava/lang/Object; L0 L19 1
    LOCALVARIABLE exception Ljava/lang/Object; L0 L19 2
    LOCALVARIABLE location Ljava/lang/String; L0 L19 3
    MAXSTACK = 5
    MAXLOCALS = 11

  // access flags 0x11
  public final taintObject(Ledu/columbia/cs/psl/phosphor/struct/TaintedWithObjTag;Ljava/lang/Object;)V
   L0
    ALOAD 1
    LDC "obj"
    INVOKESTATIC kotlin/jvm/internal/Intrinsics.checkNotNullParameter (Ljava/lang/Object;Ljava/lang/String;)V
    ALOAD 2
    LDC "exception"
    INVOKESTATIC kotlin/jvm/internal/Intrinsics.checkNotNullParameter (Ljava/lang/Object;Ljava/lang/String;)V
   L1
    LINENUMBER 219 L1
    ALOAD 2
    INVOKESTATIC java/lang/System.identityHashCode (Ljava/lang/Object;)I
    ISTORE 3
   L2
    ILOAD 3
    INVOKESTATIC java/lang/Integer.valueOf (I)Ljava/lang/Integer;
    ASTORE 4
   L3
    LINENUMBER 220 L3
    GETSTATIC al/aoli/exchain/runtime/analyzers/AffectedVarDriver.exceptionStore : Ljava/util/Map;
    ALOAD 4
    ALOAD 2
    INVOKEINTERFACE java/util/Map.put (Ljava/lang/Object;Ljava/lang/Object;)Ljava/lang/Object; (itf)
    POP
   L4
    LINENUMBER 221 L4
    ALOAD 1
    INVOKEINTERFACE edu/columbia/cs/psl/phosphor/struct/TaintedWithObjTag.getPHOSPHOR_TAG ()Ljava/lang/Object; (itf)
    IFNULL L5
   L6
    LINENUMBER 222 L6
    ALOAD 1
    ALOAD 1
    INVOKEINTERFACE edu/columbia/cs/psl/phosphor/struct/TaintedWithObjTag.getPHOSPHOR_TAG ()Ljava/lang/Object; (itf)
    DUP
    LDC "null cannot be cast to non-null type edu.columbia.cs.psl.phosphor.runtime.Taint<kotlin.Int>"
    INVOKESTATIC kotlin/jvm/internal/Intrinsics.checkNotNull (Ljava/lang/Object;Ljava/lang/String;)V
    CHECKCAST edu/columbia/cs/psl/phosphor/runtime/Taint
    ILOAD 3
    INVOKESTATIC java/lang/Integer.valueOf (I)Ljava/lang/Integer;
    INVOKESTATIC edu/columbia/cs/psl/phosphor/runtime/Taint.withLabel (Ljava/lang/Object;)Ledu/columbia/cs/psl/phosphor/runtime/Taint;
    INVOKEVIRTUAL edu/columbia/cs/psl/phosphor/runtime/Taint.union (Ledu/columbia/cs/psl/phosphor/runtime/Taint;)Ledu/columbia/cs/psl/phosphor/runtime/Taint;
    INVOKEINTERFACE edu/columbia/cs/psl/phosphor/struct/TaintedWithObjTag.setPHOSPHOR_TAG (Ljava/lang/Object;)V (itf)
    GOTO L7
   L5
    LINENUMBER 224 L5
   FRAME FULL [al/aoli/exchain/runtime/analyzers/AffectedVarDriver edu/columbia/cs/psl/phosphor/struct/TaintedWithObjTag java/lang/Object I java/lang/Integer] []
    ALOAD 1
    ILOAD 3
    INVOKESTATIC java/lang/Integer.valueOf (I)Ljava/lang/Integer;
    INVOKESTATIC edu/columbia/cs/psl/phosphor/runtime/Taint.withLabel (Ljava/lang/Object;)Ledu/columbia/cs/psl/phosphor/runtime/Taint;
    INVOKEINTERFACE edu/columbia/cs/psl/phosphor/struct/TaintedWithObjTag.setPHOSPHOR_TAG (Ljava/lang/Object;)V (itf)
   L7
    LINENUMBER 226 L7
   FRAME FULL [al/aoli/exchain/runtime/analyzers/AffectedVarDriver edu/columbia/cs/psl/phosphor/struct/TaintedWithObjTag java/lang/Object I java/lang/Integer] []
    RETURN
   L8
    LOCALVARIABLE label I L2 L8 3
    LOCALVARIABLE this Lal/aoli/exchain/runtime/analyzers/AffectedVarDriver; L0 L8 0
    LOCALVARIABLE obj Ledu/columbia/cs/psl/phosphor/struct/TaintedWithObjTag; L0 L8 1
    LOCALVARIABLE exception Ljava/lang/Object; L0 L8 2
    MAXSTACK = 4
    MAXLOCALS = 5

  // access flags 0x11
  public final updateAffectedFields(Ljava/lang/Object;Lal/aoli/exchain/runtime/objects/AffectedVarResult;Ljava/lang/Object;)V
    TRYCATCHBLOCK L0 L1 L2 java/lang/Exception
    TRYCATCHBLOCK L3 L4 L5 java/lang/Exception
   L6
    ALOAD 2
    LDC "affectedVarResult"
    INVOKESTATIC kotlin/jvm/internal/Intrinsics.checkNotNullParameter (Ljava/lang/Object;Ljava/lang/String;)V
    ALOAD 3
    LDC "exception"
    INVOKESTATIC kotlin/jvm/internal/Intrinsics.checkNotNullParameter (Ljava/lang/Object;Ljava/lang/String;)V
   L7
    LINENUMBER 161 L7
    ALOAD 3
    INVOKESTATIC java/lang/System.identityHashCode (Ljava/lang/Object;)I
    ISTORE 4
   L8
    ILOAD 4
    INVOKESTATIC java/lang/Integer.valueOf (I)Ljava/lang/Integer;
    ASTORE 6
   L9
    LINENUMBER 162 L9
    GETSTATIC al/aoli/exchain/runtime/analyzers/AffectedVarDriver.exceptionStore : Ljava/util/Map;
    ALOAD 6
    ALOAD 3
    INVOKEINTERFACE java/util/Map.put (Ljava/lang/Object;Ljava/lang/Object;)Ljava/lang/Object; (itf)
    POP
   L10
    LINENUMBER 163 L10
    ALOAD 1
    IFNULL L11
   L12
    LINENUMBER 164 L12
    ALOAD 2
    INVOKEVIRTUAL al/aoli/exchain/runtime/objects/AffectedVarResult.getAffectedFieldName ()[Ljava/lang/String;
    ASTORE 5
    ICONST_0
    ISTORE 6
    ALOAD 5
    ARRAYLENGTH
    ISTORE 7
   L13
   FRAME FULL [al/aoli/exchain/runtime/analyzers/AffectedVarDriver java/lang/Object al/aoli/exchain/runtime/objects/AffectedVarResult java/lang/Object I [Ljava/lang/String; I I] []
    ILOAD 6
    ILOAD 7
    IF_ICMPGE L11
    ALOAD 5
    ILOAD 6
    AALOAD
    ASTORE 8
   L0
    LINENUMBER 165 L0
    NOP
   L14
    LINENUMBER 166 L14
    ALOAD 1
    INVOKEVIRTUAL java/lang/Object.getClass ()Ljava/lang/Class;
    NEW java/lang/StringBuilder
    DUP
    INVOKESPECIAL java/lang/StringBuilder.<init> ()V
    ALOAD 8
    INVOKEVIRTUAL java/lang/StringBuilder.append (Ljava/lang/String;)Ljava/lang/StringBuilder;
    LDC "PHOSPHOR_TAG"
    INVOKEVIRTUAL java/lang/StringBuilder.append (Ljava/lang/String;)Ljava/lang/StringBuilder;
    INVOKEVIRTUAL java/lang/StringBuilder.toString ()Ljava/lang/String;
    INVOKEVIRTUAL java/lang/Class.getField (Ljava/lang/String;)Ljava/lang/reflect/Field;
    ASTORE 9
   L15
    LINENUMBER 167 L15
    ALOAD 9
    ICONST_1
    INVOKEVIRTUAL java/lang/reflect/Field.setAccessible (Z)V
   L16
    LINENUMBER 168 L16
    ALOAD 9
    ALOAD 1
    INVOKEVIRTUAL java/lang/reflect/Field.get (Ljava/lang/Object;)Ljava/lang/Object;
    CHECKCAST edu/columbia/cs/psl/phosphor/runtime/Taint
    ASTORE 10
   L17
    LINENUMBER 170 L17
    ALOAD 10
    IFNONNULL L18
   L19
    LINENUMBER 171 L19
    ILOAD 4
    INVOKESTATIC java/lang/Integer.valueOf (I)Ljava/lang/Integer;
    INVOKESTATIC edu/columbia/cs/psl/phosphor/runtime/Taint.withLabel (Ljava/lang/Object;)Ledu/columbia/cs/psl/phosphor/runtime/Taint;
    GOTO L20
   L18
    LINENUMBER 173 L18
   FRAME FULL [al/aoli/exchain/runtime/analyzers/AffectedVarDriver java/lang/Object al/aoli/exchain/runtime/objects/AffectedVarResult java/lang/Object I [Ljava/lang/String; I I java/lang/String java/lang/reflect/Field edu/columbia/cs/psl/phosphor/runtime/Taint] []
    ALOAD 10
    ILOAD 4
    INVOKESTATIC java/lang/Integer.valueOf (I)Ljava/lang/Integer;
    INVOKESTATIC edu/columbia/cs/psl/phosphor/runtime/Taint.withLabel (Ljava/lang/Object;)Ledu/columbia/cs/psl/phosphor/runtime/Taint;
    INVOKEVIRTUAL edu/columbia/cs/psl/phosphor/runtime/Taint.union (Ledu/columbia/cs/psl/phosphor/runtime/Taint;)Ledu/columbia/cs/psl/phosphor/runtime/Taint;
   L20
    LINENUMBER 170 L20
    LINENUMBER 169 L20
   FRAME FULL [al/aoli/exchain/runtime/analyzers/AffectedVarDriver java/lang/Object al/aoli/exchain/runtime/objects/AffectedVarResult java/lang/Object I [Ljava/lang/String; I I java/lang/String java/lang/reflect/Field edu/columbia/cs/psl/phosphor/runtime/Taint] [edu/columbia/cs/psl/phosphor/runtime/Taint]
    ASTORE 11
   L21
    LINENUMBER 175 L21
    ALOAD 9
    ALOAD 1
    ALOAD 11
    INVOKEVIRTUAL java/lang/reflect/Field.set (Ljava/lang/Object;Ljava/lang/Object;)V
   L22
    LINENUMBER 177 L22
    ALOAD 1
    INVOKEVIRTUAL java/lang/Object.getClass ()Ljava/lang/Class;
    ALOAD 8
    INVOKEVIRTUAL java/lang/Class.getDeclaredField (Ljava/lang/String;)Ljava/lang/reflect/Field;
    ASTORE 12
   L23
    LINENUMBER 178 L23
    ALOAD 12
    INVOKEVIRTUAL java/lang/reflect/Field.trySetAccessible ()Z
    IFNE L24
   L25
    LINENUMBER 179 L25
    GOTO L26
   L24
    LINENUMBER 181 L24
   FRAME FULL [al/aoli/exchain/runtime/analyzers/AffectedVarDriver java/lang/Object al/aoli/exchain/runtime/objects/AffectedVarResult java/lang/Object I [Ljava/lang/String; I I java/lang/String java/lang/reflect/Field edu/columbia/cs/psl/phosphor/runtime/Taint edu/columbia/cs/psl/phosphor/runtime/Taint java/lang/reflect/Field] []
    ALOAD 12
    ALOAD 1
    INVOKEVIRTUAL java/lang/reflect/Field.get (Ljava/lang/Object;)Ljava/lang/Object;
    ASTORE 13
   L27
    LINENUMBER 182 L27
    ALOAD 13
    IFNULL L26
    ALOAD 13
    INSTANCEOF edu/columbia/cs/psl/phosphor/struct/TaintedWithObjTag
    IFEQ L26
   L28
    LINENUMBER 184 L28
    ALOAD 13
    CHECKCAST edu/columbia/cs/psl/phosphor/struct/TaintedWithObjTag
    INVOKEINTERFACE edu/columbia/cs/psl/phosphor/struct/TaintedWithObjTag.getPHOSPHOR_TAG ()Ljava/lang/Object; (itf)
    IFNONNULL L29
   L30
    LINENUMBER 185 L30
    ILOAD 4
    INVOKESTATIC java/lang/Integer.valueOf (I)Ljava/lang/Integer;
    INVOKESTATIC edu/columbia/cs/psl/phosphor/runtime/Taint.withLabel (Ljava/lang/Object;)Ledu/columbia/cs/psl/phosphor/runtime/Taint;
    GOTO L31
   L29
    LINENUMBER 187 L29
   FRAME FULL [al/aoli/exchain/runtime/analyzers/AffectedVarDriver java/lang/Object al/aoli/exchain/runtime/objects/AffectedVarResult java/lang/Object I [Ljava/lang/String; I I java/lang/String java/lang/reflect/Field edu/columbia/cs/psl/phosphor/runtime/Taint edu/columbia/cs/psl/phosphor/runtime/Taint java/lang/reflect/Field java/lang/Object] []
    ALOAD 13
    CHECKCAST edu/columbia/cs/psl/phosphor/struct/TaintedWithObjTag
    INVOKEINTERFACE edu/columbia/cs/psl/phosphor/struct/TaintedWithObjTag.getPHOSPHOR_TAG ()Ljava/lang/Object; (itf)
    DUP
    LDC "null cannot be cast to non-null type edu.columbia.cs.psl.phosphor.runtime.Taint<kotlin.Int>"
    INVOKESTATIC kotlin/jvm/internal/Intrinsics.checkNotNull (Ljava/lang/Object;Ljava/lang/String;)V
    CHECKCAST edu/columbia/cs/psl/phosphor/runtime/Taint
    ILOAD 4
    INVOKESTATIC java/lang/Integer.valueOf (I)Ljava/lang/Integer;
    INVOKESTATIC edu/columbia/cs/psl/phosphor/runtime/Taint.withLabel (Ljava/lang/Object;)Ledu/columbia/cs/psl/phosphor/runtime/Taint;
    INVOKEVIRTUAL edu/columbia/cs/psl/phosphor/runtime/Taint.union (Ledu/columbia/cs/psl/phosphor/runtime/Taint;)Ledu/columbia/cs/psl/phosphor/runtime/Taint;
   L31
    LINENUMBER 184 L31
    LINENUMBER 183 L31
   FRAME FULL [al/aoli/exchain/runtime/analyzers/AffectedVarDriver java/lang/Object al/aoli/exchain/runtime/objects/AffectedVarResult java/lang/Object I [Ljava/lang/String; I I java/lang/String java/lang/reflect/Field edu/columbia/cs/psl/phosphor/runtime/Taint edu/columbia/cs/psl/phosphor/runtime/Taint java/lang/reflect/Field java/lang/Object] [edu/columbia/cs/psl/phosphor/runtime/Taint]
    ASTORE 14
   L32
    LINENUMBER 189 L32
    ALOAD 13
    CHECKCAST edu/columbia/cs/psl/phosphor/struct/TaintedWithObjTag
    ALOAD 14
    INVOKEINTERFACE edu/columbia/cs/psl/phosphor/struct/TaintedWithObjTag.setPHOSPHOR_TAG (Ljava/lang/Object;)V (itf)
   L1
    GOTO L26
   L2
    LINENUMBER 191 L2
   FRAME FULL [al/aoli/exchain/runtime/analyzers/AffectedVarDriver java/lang/Object al/aoli/exchain/runtime/objects/AffectedVarResult java/lang/Object I [Ljava/lang/String; I I java/lang/String] [java/lang/Exception]
    ASTORE 9
   L33
    LINENUMBER 192 L33
    INVOKESTATIC al/aoli/exchain/runtime/analyzers/AffectedVarDriverKt.access$getLogger$p ()Lal/aoli/exchain/runtime/logger/Logger;
    NEW al/aoli/exchain/runtime/analyzers/AffectedVarDriver$updateAffectedFields$1
    DUP
    ALOAD 8
    ALOAD 1
    ALOAD 9
    INVOKESPECIAL al/aoli/exchain/runtime/analyzers/AffectedVarDriver$updateAffectedFields$1.<init> (Ljava/lang/String;Ljava/lang/Object;Ljava/lang/Exception;)V
    CHECKCAST kotlin/jvm/functions/Function0
    INVOKEVIRTUAL al/aoli/exchain/runtime/logger/Logger.warn (Lkotlin/jvm/functions/Function0;)V
   L26
    LINENUMBER 164 L26
   FRAME FULL [al/aoli/exchain/runtime/analyzers/AffectedVarDriver java/lang/Object al/aoli/exchain/runtime/objects/AffectedVarResult java/lang/Object I [Ljava/lang/String; I I java/lang/String java/lang/Object] []
    IINC 6 1
    GOTO L13
   L11
    LINENUMBER 199 L11
   FRAME FULL [al/aoli/exchain/runtime/analyzers/AffectedVarDriver java/lang/Object al/aoli/exchain/runtime/objects/AffectedVarResult java/lang/Object I] []
    ALOAD 2
    INVOKEVIRTUAL al/aoli/exchain/runtime/objects/AffectedVarResult.getAffectedStaticFieldName ()[Ljava/lang/String;
    ASTORE 5
    ICONST_0
    ISTORE 6
    ALOAD 5
    ARRAYLENGTH
    ISTORE 7
   L34
   FRAME FULL [al/aoli/exchain/runtime/analyzers/AffectedVarDriver java/lang/Object al/aoli/exchain/runtime/objects/AffectedVarResult java/lang/Object I [Ljava/lang/String; I I] []
    ILOAD 6
    ILOAD 7
    IF_ICMPGE L35
    ALOAD 5
    ILOAD 6
    AALOAD
    ASTORE 8
   L3
    LINENUMBER 200 L3
    NOP
   L36
    LINENUMBER 201 L36
    ALOAD 8
    CHECKCAST java/lang/CharSequence
    ICONST_1
    ANEWARRAY java/lang/String
    ASTORE 10
    ALOAD 10
    ICONST_0
    LDC "#"
    AASTORE
    ALOAD 10
    ICONST_0
    ICONST_0
    BIPUSH 6
    ACONST_NULL
    INVOKESTATIC kotlin/text/StringsKt.split$default (Ljava/lang/CharSequence;[Ljava/lang/String;ZIILjava/lang/Object;)Ljava/util/List;
    ASTORE 9
    ALOAD 9
    ICONST_0
    INVOKEINTERFACE java/util/List.get (I)Ljava/lang/Object; (itf)
   L37
    LINENUMBER 201 L37
    CHECKCAST java/lang/String
    ASTORE 10
   L38
    ALOAD 9
    ICONST_1
    INVOKEINTERFACE java/util/List.get (I)Ljava/lang/Object; (itf)
   L39
    LINENUMBER 201 L39
    CHECKCAST java/lang/String
    ASTORE 11
   L40
    LINENUMBER 202 L40
    ALOAD 10
    LDC "/"
    LDC "."
    ICONST_0
    ICONST_4
    ACONST_NULL
    INVOKESTATIC kotlin/text/StringsKt.replace$default (Ljava/lang/String;Ljava/lang/String;Ljava/lang/String;ZILjava/lang/Object;)Ljava/lang/String;
    INVOKESTATIC java/lang/Class.forName (Ljava/lang/String;)Ljava/lang/Class;
    ASTORE 12
   L41
    LINENUMBER 203 L41
    ALOAD 12
    NEW java/lang/StringBuilder
    DUP
    INVOKESPECIAL java/lang/StringBuilder.<init> ()V
    ALOAD 11
    INVOKEVIRTUAL java/lang/StringBuilder.append (Ljava/lang/String;)Ljava/lang/StringBuilder;
    LDC "PHOSPHOR_TAG"
    INVOKEVIRTUAL java/lang/StringBuilder.append (Ljava/lang/String;)Ljava/lang/StringBuilder;
    INVOKEVIRTUAL java/lang/StringBuilder.toString ()Ljava/lang/String;
    INVOKEVIRTUAL java/lang/Class.getField (Ljava/lang/String;)Ljava/lang/reflect/Field;
    ASTORE 13
   L42
    LINENUMBER 204 L42
    ALOAD 13
    ACONST_NULL
    INVOKEVIRTUAL java/lang/reflect/Field.get (Ljava/lang/Object;)Ljava/lang/Object;
    CHECKCAST edu/columbia/cs/psl/phosphor/runtime/Taint
    ASTORE 14
   L43
    LINENUMBER 206 L43
    ALOAD 14
    IFNONNULL L44
   L45
    LINENUMBER 207 L45
    ILOAD 4
    INVOKESTATIC java/lang/Integer.valueOf (I)Ljava/lang/Integer;
    INVOKESTATIC edu/columbia/cs/psl/phosphor/runtime/Taint.withLabel (Ljava/lang/Object;)Ledu/columbia/cs/psl/phosphor/runtime/Taint;
    GOTO L46
   L44
    LINENUMBER 209 L44
   FRAME FULL [al/aoli/exchain/runtime/analyzers/AffectedVarDriver java/lang/Object al/aoli/exchain/runtime/objects/AffectedVarResult java/lang/Object I [Ljava/lang/String; I I java/lang/String java/util/List java/lang/String java/lang/String java/lang/Class java/lang/reflect/Field edu/columbia/cs/psl/phosphor/runtime/Taint] []
    ALOAD 14
    ILOAD 4
    INVOKESTATIC java/lang/Integer.valueOf (I)Ljava/lang/Integer;
    INVOKESTATIC edu/columbia/cs/psl/phosphor/runtime/Taint.withLabel (Ljava/lang/Object;)Ledu/columbia/cs/psl/phosphor/runtime/Taint;
    INVOKEVIRTUAL edu/columbia/cs/psl/phosphor/runtime/Taint.union (Ledu/columbia/cs/psl/phosphor/runtime/Taint;)Ledu/columbia/cs/psl/phosphor/runtime/Taint;
   L46
    LINENUMBER 206 L46
    LINENUMBER 205 L46
   FRAME FULL [al/aoli/exchain/runtime/analyzers/AffectedVarDriver java/lang/Object al/aoli/exchain/runtime/objects/AffectedVarResult java/lang/Object I [Ljava/lang/String; I I java/lang/String java/util/List java/lang/String java/lang/String java/lang/Class java/lang/reflect/Field edu/columbia/cs/psl/phosphor/runtime/Taint] [edu/columbia/cs/psl/phosphor/runtime/Taint]
    ASTORE 15
   L47
    LINENUMBER 211 L47
    ALOAD 13
    ACONST_NULL
    ALOAD 15
    INVOKEVIRTUAL java/lang/reflect/Field.set (Ljava/lang/Object;Ljava/lang/Object;)V
   L4
    GOTO L48
   L5
    LINENUMBER 212 L5
   FRAME FULL [al/aoli/exchain/runtime/analyzers/AffectedVarDriver java/lang/Object al/aoli/exchain/runtime/objects/AffectedVarResult java/lang/Object I [Ljava/lang/String; I I java/lang/String] [java/lang/Exception]
    ASTORE 9
   L49
    LINENUMBER 213 L49
    INVOKESTATIC al/aoli/exchain/runtime/analyzers/AffectedVarDriverKt.access$getLogger$p ()Lal/aoli/exchain/runtime/logger/Logger;
    NEW al/aoli/exchain/runtime/analyzers/AffectedVarDriver$updateAffectedFields$2
    DUP
    ALOAD 8
    ALOAD 9
    INVOKESPECIAL al/aoli/exchain/runtime/analyzers/AffectedVarDriver$updateAffectedFields$2.<init> (Ljava/lang/String;Ljava/lang/Exception;)V
    CHECKCAST kotlin/jvm/functions/Function0
    INVOKEVIRTUAL al/aoli/exchain/runtime/logger/Logger.warn (Lkotlin/jvm/functions/Function0;)V
   L48
    LINENUMBER 199 L48
   FRAME FULL [al/aoli/exchain/runtime/analyzers/AffectedVarDriver java/lang/Object al/aoli/exchain/runtime/objects/AffectedVarResult java/lang/Object I [Ljava/lang/String; I I java/lang/String java/lang/Object] []
    IINC 6 1
    GOTO L34
   L35
    LINENUMBER 216 L35
   FRAME FULL [al/aoli/exchain/runtime/analyzers/AffectedVarDriver java/lang/Object al/aoli/exchain/runtime/objects/AffectedVarResult java/lang/Object I [Ljava/lang/String; I I] []
    RETURN
   L50
    LOCALVARIABLE tag Ledu/columbia/cs/psl/phosphor/runtime/Taint; L32 L1 14
    LOCALVARIABLE fieldTag Ljava/lang/reflect/Field; L15 L1 9
    LOCALVARIABLE value Ledu/columbia/cs/psl/phosphor/runtime/Taint; L17 L1 10
    LOCALVARIABLE tag Ledu/columbia/cs/psl/phosphor/runtime/Taint; L21 L1 11
    LOCALVARIABLE fieldRef Ljava/lang/reflect/Field; L23 L1 12
    LOCALVARIABLE fieldObj Ljava/lang/Object; L27 L1 13
    LOCALVARIABLE e Ljava/lang/Exception; L33 L26 9
    LOCALVARIABLE name Ljava/lang/String; L0 L11 8
    LOCALVARIABLE clazzName Ljava/lang/String; L38 L4 10
    LOCALVARIABLE fieldName Ljava/lang/String; L40 L4 11
    LOCALVARIABLE clazz Ljava/lang/Class; L41 L4 12
    LOCALVARIABLE field Ljava/lang/reflect/Field; L42 L4 13
    LOCALVARIABLE value Ledu/columbia/cs/psl/phosphor/runtime/Taint; L43 L4 14
    LOCALVARIABLE tag Ledu/columbia/cs/psl/phosphor/runtime/Taint; L47 L4 15
    LOCALVARIABLE e Ljava/lang/Exception; L49 L48 9
    LOCALVARIABLE name Ljava/lang/String; L3 L35 8
    LOCALVARIABLE label I L8 L50 4
    LOCALVARIABLE this Lal/aoli/exchain/runtime/analyzers/AffectedVarDriver; L6 L50 0
    LOCALVARIABLE obj Ljava/lang/Object; L6 L50 1
    LOCALVARIABLE affectedVarResult Lal/aoli/exchain/runtime/objects/AffectedVarResult; L6 L50 2
    LOCALVARIABLE exception Ljava/lang/Object; L6 L50 3
    MAXSTACK = 6
    MAXLOCALS = 16

  // access flags 0x11
  // signature (Ledu/columbia/cs/psl/phosphor/struct/PowerSetTree$SetNode;Ljava/lang/Object;)Ledu/columbia/cs/psl/phosphor/runtime/Taint<*>;
  // declaration: edu.columbia.cs.psl.phosphor.runtime.Taint<?> updateTaint(edu.columbia.cs.psl.phosphor.struct.PowerSetTree$SetNode, java.lang.Object)
  public final updateTaint(Ledu/columbia/cs/psl/phosphor/struct/PowerSetTree$SetNode;Ljava/lang/Object;)Ledu/columbia/cs/psl/phosphor/runtime/Taint;
   L0
    ALOAD 1
    LDC "obj"
    INVOKESTATIC kotlin/jvm/internal/Intrinsics.checkNotNullParameter (Ljava/lang/Object;Ljava/lang/String;)V
    ALOAD 2
    LDC "exception"
    INVOKESTATIC kotlin/jvm/internal/Intrinsics.checkNotNullParameter (Ljava/lang/Object;Ljava/lang/String;)V
   L1
    LINENUMBER 155 L1
    ALOAD 2
    INVOKESTATIC java/lang/System.identityHashCode (Ljava/lang/Object;)I
    ISTORE 3
   L2
    ILOAD 3
    INVOKESTATIC java/lang/Integer.valueOf (I)Ljava/lang/Integer;
    ASTORE 4
   L3
    LINENUMBER 156 L3
    GETSTATIC al/aoli/exchain/runtime/analyzers/AffectedVarDriver.exceptionStore : Ljava/util/Map;
    ALOAD 4
    ALOAD 2
    INVOKEINTERFACE java/util/Map.put (Ljava/lang/Object;Ljava/lang/Object;)Ljava/lang/Object; (itf)
    POP
   L4
    LINENUMBER 157 L4
    ALOAD 1
    ILOAD 3
    INVOKESTATIC java/lang/Integer.valueOf (I)Ljava/lang/Integer;
    INVOKESTATIC edu/columbia/cs/psl/phosphor/runtime/Taint.withLabel (Ljava/lang/Object;)Ledu/columbia/cs/psl/phosphor/runtime/Taint;
    INVOKEVIRTUAL edu/columbia/cs/psl/phosphor/struct/PowerSetTree$SetNode.union (Ledu/columbia/cs/psl/phosphor/runtime/Taint;)Ledu/columbia/cs/psl/phosphor/struct/PowerSetTree$SetNode;
    DUP
    LDC "obj.union(Taint.withLabel(label))"
    INVOKESTATIC kotlin/jvm/internal/Intrinsics.checkNotNullExpressionValue (Ljava/lang/Object;Ljava/lang/String;)V
    CHECKCAST edu/columbia/cs/psl/phosphor/runtime/Taint
    ARETURN
   L5
    LOCALVARIABLE label I L2 L5 3
    LOCALVARIABLE this Lal/aoli/exchain/runtime/analyzers/AffectedVarDriver; L0 L5 0
    LOCALVARIABLE obj Ledu/columbia/cs/psl/phosphor/struct/PowerSetTree$SetNode; L0 L5 1
    LOCALVARIABLE exception Ljava/lang/Object; L0 L5 2
    MAXSTACK = 3
    MAXLOCALS = 5

  // access flags 0x2
  private <init>()V
   L0
    LINENUMBER 18 L0
    ALOAD 0
    INVOKESPECIAL java/lang/Object.<init> ()V
    RETURN
   L1
    LOCALVARIABLE this Lal/aoli/exchain/runtime/analyzers/AffectedVarDriver; L0 L1 0
    MAXSTACK = 1
    MAXLOCALS = 1

  // access flags 0x8
  static <clinit>()V
    NEW al/aoli/exchain/runtime/analyzers/AffectedVarDriver
    DUP
    INVOKESPECIAL al/aoli/exchain/runtime/analyzers/AffectedVarDriver.<init> ()V
    PUTSTATIC al/aoli/exchain/runtime/analyzers/AffectedVarDriver.INSTANCE : Lal/aoli/exchain/runtime/analyzers/AffectedVarDriver;
   L0
    LINENUMBER 20 L0
    GETSTATIC al/aoli/exchain/runtime/objects/Type.Dynamic : Lal/aoli/exchain/runtime/objects/Type;
    PUTSTATIC al/aoli/exchain/runtime/analyzers/AffectedVarDriver.type : Lal/aoli/exchain/runtime/objects/Type;
   L1
    LINENUMBER 21 L1
    GETSTATIC al/aoli/exchain/runtime/analyzers/AffectedVarDriver$store$2.INSTANCE : Lal/aoli/exchain/runtime/analyzers/AffectedVarDriver$store$2;
    CHECKCAST kotlin/jvm/functions/Function0
    INVOKESTATIC kotlin/LazyKt.lazy (Lkotlin/jvm/functions/Function0;)Lkotlin/Lazy;
    PUTSTATIC al/aoli/exchain/runtime/analyzers/AffectedVarDriver.store$delegate : Lkotlin/Lazy;
   L2
    LINENUMBER 28 L2
    NEW java/util/LinkedHashMap
    DUP
    INVOKESPECIAL java/util/LinkedHashMap.<init> ()V
    CHECKCAST java/util/Map
   L3
    LINENUMBER 28 L3
    PUTSTATIC al/aoli/exchain/runtime/analyzers/AffectedVarDriver.exceptionSourceIdentified : Ljava/util/Map;
   L4
    LINENUMBER 152 L4
    NEW java/util/LinkedHashMap
    DUP
    INVOKESPECIAL java/util/LinkedHashMap.<init> ()V
    CHECKCAST java/util/Map
   L5
    LINENUMBER 152 L5
    PUTSTATIC al/aoli/exchain/runtime/analyzers/AffectedVarDriver.exceptionStore : Ljava/util/Map;
    RETURN
    MAXSTACK = 2
    MAXLOCALS = 0

  // access flags 0x11
  public final getType()Lal/aoli/exchain/runtime/objects/Type;
   L0
    LINENUMBER 20 L0
    GETSTATIC al/aoli/exchain/runtime/analyzers/AffectedVarDriver.type : Lal/aoli/exchain/runtime/objects/Type;
    ARETURN
   L1
    LOCALVARIABLE this Lal/aoli/exchain/runtime/analyzers/AffectedVarDriver; L0 L1 0
    MAXSTACK = 1
    MAXLOCALS = 1
}
